Workbook

Sheet Checklists
B2: Sl No. | C2: Incentive working Checklist Points | D2: Doc Path | E2: Action Jul 2026
C3: Field:-
B4: 1 | C4: Get specific months Incentive Target sheet from concern department head with approval. | D4: Google Sheet | E4: Done
B5: 2 | C5: Download the Consumption reports from Ikigai backend. | D5: Ikigai Report | E5: Done
B6: 3 | C6: Coupon audit done using the google sheet mentained by Data team with Consumption reports. | D6: Google Sheet Mentained by Data team | E6: Done
B7: 4 | C7: After download the Ikigai report, arrange all sales made by BDE's with proper date format to know the coupon applicable for Incentive or not | D7: NA | E7: Done
B8: 5 | C8: Field coupon Analysis report prepare with use of excel tool and also cross check with manually | D8: NA | E8: Done
B9: 6 | C9: Follow the Coupon logic to know the applicability the sale is applicable for Incentive or not | D9: Coupon Logic SOP | E9: Done
B10: 6 | C10: All clubing provision should check properly | D10: NA | E10: Done
B11: 7 | C11: With Effective from Sep 2025 onward Field Incentive calculation,for calculating we should check the ARPU individual wise if it is more than 33000 then that case we will consider which ever is maxmium (Unit or Revenue) if ARPU less than 33000 then we will consider the Revenue achievement to calculate the Incentive. | D11: Having the Email Thread | E11: Done
B12: 8 | C12: Cross verify with updated policy before finalising | D12: NA | E12: Done
B13: 9 | C13: Post Approval from Accounts-Manager send to Business Head and Finance Head | D13: NA
B14: 10 | C14: Check there is any exceptional cases of coupon or Incentive that approved by Management. If there is any case, consider Proper impact in Incentive Calculation and keep the document for future reference. | D14: No such Cases

Sheet Index
B3: S.No | C3: Particulars | D3: Contents | E3: Context | F3: POC Department
B4: 1 | C4: Input | D4: Policy | E4: This is the policy decided and approved by the Management for the | F4: Management
B5: 2 | C5: Input | D5: Target Achieved | E5: Target which are approved from the Management end are incorporated in this sheet. This also includes data related with penalty sales . Data from this sheet is linked to Incentive Report | F5: Management
B6: 3 | C6: Input | D6: Coupon Analysis | E6: This is prepared from the Coupon Analysis Report which is approved from accounts team's end | F6: Accounts Team
B7: 4 | C7: Process | D7: Incentive Report | E7: Incentive Report incorporates all the incentive details for the field sales team and is linked with input files for incentive calculations | F7: Accounts Team
B8: 5 | C8: Process | D8: RM Calculations Pro Rata | E8: This sheet is created to calculate the quarterly pay-out done to the RM's. | F8: Accounts Team
B9: 6 | C9: Output | D9: Incentive Summary | E9: Incentive Summary is the final output sheet which includes a snapshot view of incentives paid to the employee and their annual incentive accumulations. | F9: Accounts Team

Sheet Header Index
B4: S.No | C4: Headers | D4: Remarks | E4: Explanation
B5: 1 | C5: Name | D5: Name of the employee | E5: Name of the Business Development Executive.
B6: =B5+1 -> 2 | C6: Zone | D6: BDE's Zone. | E6: There are five zones namely, North , East , West , South TNKL and South KATS. All BDE along with the colleges are mapped zone wise.
B7: =B6+1 -> 3 | C7: BDE Target Units | D7: Targets decided by the Management. | E7: BDE targets are decided by the Management using Net Active Student count in the targeted colleges.
B8: =B7+1 -> 4 | C8: Winner Units | D8: Decided by the Management | E8: These units decide the performance incentives like Master Blaster , Half yearly incentive winner and best annual performers amongst the BDE's, TM's and RM's.
B9: =B8+1 -> 5 | C9: Rule >80%coupon utilization | D9: 80% of the coupon sales count to be utilized | E9: This rule is mentioned and logically calculated in the Coupon Analysis Sheet.
B10: =B9+1 -> 6 | C10: Refunds | D10: Refunds during the current month | E10: No incentives are paid on the refunds therefore it is represented in a difference column so that BDE wise refunds can be considered.
B11: =B10+1 -> 7 | C11: Achieved Units RM & TM | D11: Achieved Sales count by RM and TM in that month | E11: Achieved count is calculated as per the input sheets and incorporated in this column. This columns indicated the BDE achieve count. These sales count are considered for RM's and TM's incentive calculations.
B12: =B11+1 -> 8 | C12: Achieved units % BDE | D12: Achieved Sales count % | E12: This is the % of column "BDE targets Units " to column "Achieved Units RM & TM".
B13: =B12+1 -> 9 | C13: Target Revenue - NET | D13: BDE's target revenue Without GST | E13: BDE targets which are decided as per the input sheet Target sheets are multiplied by Average Rate Per User (ARPU ) of 29000 to arrive at revenue targets. This does not include GST and ARPU is again decided by the Management
B14: =B13+1 -> 10 | C14: Achieved Revenue - GROSS | D14: Achieved Revenue including GST | E14: Achieved Revenue including GST
B15: =B14+1 -> 11 | C15: Achieved Revenue - NET BDE Rue1 Diqualified | D15: Disqualified amount amongst the Achieved Revenue amount | E15: Coupon Analysis gives the disqualified sales figure ( without GST ) . These figure are then directly linked to the incentive reports to fill out this header
B16: =B15+1 -> 12 | C16: Achieved Revenue - NET BDE | D16: Column 9- column 11 | E16: This is the net revenue generated by the BDE for the month. To calculate this figure we subtract disqualified sales with Gross Sales. All figures are considered w/o GST.
B17: =B16+1 -> 13 | C17: Achieved Revenue % | D17: Revenue % achieved | E17: Achieved Revenue % is calculated by dividing the Achieved Revenue NET by Target Revenue .
... B32: =B31+1 -> 28 | C32: Incentive of the Month | D32: Includes all incentives earned | E32: This column includes the total incentives earned for the month. Total amounts comes here without any 2 lacs incentive restrictions.

Sheet Policy
B1: FY26-27 APJ QTR
B3: ARPU | C3: 33000
B4: BDE/Individual Incentives (Monthly) | D4: (Individual) | L4: First year MBBS units | M4: Incremental slab
B5: 0-49.99% | C5: 0 | L5: 0 | M5: 0
B6: 50-79.99% | C6: 0.005 | L6: 75 | M6: 0.0005
B7: 80-99.99% | C7: 0.01 | L7: 100 | M7: 0.001
B8: 100-129.99% | C8: 0.0225 | L8: 125 | M8: 0.0025
B9: 130% & Above | C9: 0.03
B11: TM/BDM/Sr.BDE - Sub Managers Incentives (Monthly) | D11: (All sub managers under Team Owners) | L11: BDE/Individual Incentives (Monthly) | M11: Slab
B12: 0-74.99% | C12: 0 | L12: 0 | M12: 0
B13: 75-99.99% | C13: 0.001 | L13: 0.5 | M13: 0.005
B14: 100-129.99% | C14: 0.0015 | L14: 0.8 | M14: 0.01
B15: 130% & Above | C15: 0.0025 | L15: 1 | M15: 0.0225
L16: 1.3 | M16: 0.03
B17: Team Owner Incentives (Quarterly) | D17: (11 Team Owners) | L17: TM/BDM/Sr.BDE - Sub Managers Incentives (Monthly) | M17: Slab
B18: 0-74.99% | C18: 0 | L18: 0 | M18: 0
B19: 75-99.99% | C19: 0.0025 | L19: 0.8 | M19: 0.001
B20: 100-129.99% | C20: 0.0035 | L20: 1 | M20: 0.0015
B21: 130% & Above | C21: 0.005 | L21: 1.3 | M21: 0.0025
L22: Team Owner Incentives (Quarterly) | M22: Slab
B23: ZM Incentives (Quarterly) | L23: 0 | M23: 0
B24: 0-74.99% | C24: 0 | L24: 0.8 | M24: 0.0025
B25: 75-99.99% | C25: 0.002 | L25: 1 | M25: 0.0035
B26: 100-129.99% | C26: 0.0025 | L26: 1.3 | M26: 0.005
B27: 130% & Above | C27: 0.0035 | L27: Zonal Managers Incentives (9 Months) | M27: Slab
L28: 0 | M28: 0
L29: 0.8 | M29: 0.002
L30: 1 | M30: 0.0025
L31: 1.3 | M31: 0.0035
B33: RM | C33: Base for April-June | D33: JAS | E33: OND | F33: JFM | G33: Base Revenue | H33: JAS | I33: OND | J33: JFM | L33: Annual Target 26-27 (AMJ Achievement+July to March)
B34: R3-Anjaney | C34: 1950 | D34: =C34*30% -> 585 | E34: =C34*30% -> 585 | F34: =C34*40% -> 780 | G34: =C34*33000 -> 64350000 | H34: =D34*33000 -> 19305000 | I34: =E34*33000 -> 19305000 | J34: =F34*33000 -> 25740000 | K34: R1-Ajeet | L34: Zone | M34: Region | N34: RM | O34: 9 Months Base | P34: 9 Months Revenue | Q34: JAS Base | R34: JAS Revenue | S34: OND Base | T34: OND Revenue | U34: JFM Base | V34: JFM Revenue | W34: AMJ achivement | X34: Annual Revenue Target
B35: R1-Ajeet | C35: 1250 | D35: =C35*30% -> 375 | E35: =C35*30% -> 375 | F35: =C35*40% -> 500 | G35: =C35*33000 -> 41250000 | H35: =D35*33000 -> 12375000 | I35: =E35*33000 -> 12375000 | J35: =F35*33000 -> 16500000 | K35: R2-Independent(Divyansh) | L35: Z1-Divyansh | M35: R1-Ajeet | N35: Ajeet Pandey | O35: 8050 | P35: 265650000 | Q35: 2800 | R35: 92400000 | S35: 3650 | T35: 120450000 | U35: 1600 | V35: 52800000 | W35: 59948037 | X35: 325598037
B36: R2-Akif | C36: 950 | D36: =C36*30% -> 285 | E36: =C36*30% -> 285 | F36: =C36*40% -> 380 | G36: =C36*33000 -> 31350000 | H36: =D36*33000 -> 9405000 | I36: =E36*33000 -> 9405000 | J36: =F36*33000 -> 12540000 | K36: R3-Anjaney | L36: Z1-Divyansh | M36: R2-Akif | N36: Akif Hannan | O36: 5750 | P36: 189750000 | Q36: 2000 | R36: 66000000 | S36: 2600 | T36: 85800000 | U36: 1150 | V36: 37950000 | W36: 22514496 | X36: 212264496
B37: R4-Sohaib | C37: 700 | D37: =C37*30% -> 210 | E37: =C37*30% -> 210 | F37: =C37*40% -> 280 | G37: =C37*33000 -> 23100000 | H37: =D37*33000 -> 6930000 | I37: =E37*33000 -> 6930000 | J37: =F37*33000 -> 9240000 | K37: R4-Susmita | L37: Z5-Independent(Anjaney) | M37: R3-Anjaney | N37: Anjaney Tripathi | O37: 12000 | P37: 396000000 | Q37: 4800 | R37: 158400000 | S37: 4800 | T37: 158400000 | U37: 2400 | V37: 79200000 | W37: 16438504 | X37: 412438504
B38: R5-Susmita | C38: 1600 | D38: =C38*30% -> 480 | E38: =C38*30% -> 480 | F38: =C38*40% -> 640 | G38: =C38*33000 -> 52800000 | H38: =D38*33000 -> 15840000 | I38: =E38*33000 -> 15840000 | J38: =F38*33000 -> 21120000 | K38: R5-Rameez | L38: Z1-Divyansh | M38: R4-Sohaib | N38: Sohaib Ahmed | O38: 4500 | P38: 148500000 | Q38: 1600 | R38: 52800000 | S38: 2000 | T38: 66000000 | U38: 900 | V38: 29700000 | W38: 11461545 | X38: 159961545
B39: R6-Independent(Biswadip) | C39: 1450 | D39: =C39*30% -> 435 | E39: =C39*30% -> 435 | F39: =C39*40% -> 580 | G39: =C39*33000 -> 47850000 | H39: =D39*33000 -> 14355000 | I39: =E39*33000 -> 14355000 | J39: =F39*33000 -> 19140000 | K39: R6-Saif | L39: Z2-Biswadip | M39: R5-Susmita | N39: Susmita Paul | O39: 9550 | P39: 315150000 | Q39: 3350 | R39: 110550000 | S39: 4300 | T39: 141900000 | U39: 1900 | V39: 62700000 | W39: 12339931 | X39: 327489931
B40: R7-Sufiyan | C40: 850 | D40: =C40*30% -> 255 | E40: =C40*30% -> 255 | F40: =C40*40% -> 340 | G40: =C40*33000 -> 28050000 | H40: =D40*33000 -> 8415000 | I40: =E40*33000 -> 8415000 | J40: =F40*33000 -> 11220000 | K40: R7-Independent MH (Rajat) | L40: Z2-Biswadip | M40: R6-Vinod | N40: Vinod Pathania | O40: 10250 | P40: 338250000 | Q40: 3600 | R40: 118800000 | S40: 4600 | T40: 151800000 | U40: 2050 | V40: 67650000 | W40: 10249470 | X40: 348499470
B41: R9-Ajay | C41: 750 | D41: =C41*30% -> 225 | E41: =C41*30% -> 225 | F41: =C41*40% -> 300 | G41: =C41*33000 -> 24750000 | H41: =D41*33000 -> 7425000 | I41: =E41*33000 -> 7425000 | J41: =F41*33000 -> 9900000 | K41: R8-Independent(Rajat) | L41: Z3-Rajat | M41: R7-Sufiyan | N41: Sufiyan Ansari | O41: 5400 | P41: 178200000 | Q41: 1900 | R41: 62700000 | S41: 2400 | T41: 79200000 | U41: 1100 | V41: 36300000 | W41: 17474741 | X41: 195674741
B42: R8-Tauseef | C42: 1100 | D42: =C42*30% -> 330 | E42: =C42*30% -> 330 | F42: =C42*40% -> 440 | G42: =C42*33000 -> 36300000 | H42: =D42*33000 -> 10890000 | I42: =E42*33000 -> 10890000 | J42: =F42*33000 -> 14520000 | K42: R9-Sukanthan | L42: Z3-Rajat | M42: R8-Tauseef | N42: Tauseef Ansari | O42: 7150 | P42: 235950000 | Q42: 2500 | R42: 82500000 | S42: 3200 | T42: 105600000 | U42: 1450 | V42: 47850000 | W42: 11188007 | X42: 247138007
B43: R11-Srinivasan | C43: 1300 | D43: =C43*30% -> 390 | E43: =C43*30% -> 390 | F43: =C43*40% -> 520 | G43: =C43*33000 -> 42900000 | H43: =D43*33000 -> 12870000 | I43: =E43*33000 -> 12870000 | J43: =F43*33000 -> 17160000 | K43: R10-Srinivasan | L43: Z3-Rajat | M43: R9-Ajay | N43: Ajay Kumar | O43: 4600 | P43: 151800000 | Q43: 1400 | R43: 46200000 | S43: 2100 | T43: 69300000 | U43: 1100 | V43: 36300000 | W43: 13394530 | X43: 165194530
B44: R12-Independent(Akshay) | C44: 750 | L44: Z4-Akshay | M44: R10-Sukanthan | N44: Sukanthan PK | O44: 7650 | P44: 252450000 | Q44: 2300 | R44: 75900000 | S44: 3450 | T44: 113850000 | U44: 1900 | V44: 62700000 | W44: 42119788 | X44: 294569788
B45: R10-Sukanthan | C45: 1250 | L45: Z4-Akshay | M45: R11-Srinivasan | N45: Srinivasan G | O45: 7950 | P45: 262350000 | Q45: 2400 | R45: 79200000 | S45: 3600 | T45: 118800000 | U45: 1950 | V45: 64350000 | W45: 20217840 | X45: 282567840
B46: R13-Saif | C46: 1200 | L46: Z4-Akshay | M46: R12-Sufian Shareeq | N46: Sufian Shareeq | O46: 5350 | P46: 176550000 | Q46: 1600 | R46: 52800000 | S46: 2400 | T46: 79200000 | U46: 1350 | V46: 44550000 | W46: 27605687 | X46: 204155687
B47: R14-Rameez | C47: 950 | L47: Z1-Divyansh | M47: R13-Saif | N47: Saif Khan | O47: 7750 | P47: 255750000 | Q47: 2750 | R47: 90750000 | S47: 3500 | T47: 115500000 | U47: 1500 | V47: 49500000 | W47: 18913877 | X47: 274663877
B48: Total | C48: =SUM(C34:C47) -> 16050 | D48: =C48*30% -> 4815 | E48: =C48*30% -> 4815 | F48: =C48*40% -> 6420 | G48: =C48*33000 -> 529650000 | H48: =D48*33000 -> 158895000 | I48: =E48*33000 -> 158895000 | J48: =F48*33000 -> 211860000 | L48: Z1-Divyansh | M48: R14-Rameez | N48: Rameez Arman | O48: 5750 | P48: 189750000 | Q48: 2000 | R48: 66000000 | S48: 2600 | T48: 85800000 | U48: 1150 | V48: 37950000 | W48: 38772283 | X48: 228522283
N49: Total | O49: =SUM(O35:O48) -> 101700 | P49: =O49*33000 -> 3356100000 | Q49: =SUM(Q35:Q48) -> 35000 | R49: =Q49*33000 -> 1155000000 | S49: =SUM(S35:S48) -> 45200 | T49: =S49*33000 -> 1491600000 | U49: =SUM(U35:U48) -> 21500 | V49: =U49*33000 -> 709500000 | W49: =SUM(W35:W48) -> 322638736 | X49: =SUM(P49:W49) -> 7034940436
L51: Zone | M51: Base Units | N51: Base Revenue | O51: 1.3
L52: Divyansh
L53: Biswadip
L54: Rajat
L55: Akshay
L56: Rohit
L57: Total
M59: =+M55*45% -> 0 | N59: =+N55*45% -> 0

Sheet Incentive Summary Output
B14: MONTH | E14: April-26 | F14: 46143 | G14: 46174 | H14: 46204 | I14: 46235 | J14: 46266 | K14: 46296 | L14: 46327 | M14: 46357 | N14: 46388 | O14: 46419 | P14: 46447 | Q14: Total | S14: Month | T14: Overall FY 26-27
B15: INCENTIVE (BDE+Sr BDE+TM) | E15: ='Incentive Report- Output'!AF93 -> 1153970.2 | F15: ='Incentive Report- Output'!AF188 -> 1764141.8 | G15: ='Incentive Report- Output'!AF284 -> 1533549.3 | H15: ='Incentive Report- Output'!AF382 -> 1354845.1 | I15: ='Incentive Report- Output'!AF481 -> 22414109 | Q15: =SUM(E15:P15) -> 28220615 | S15: Total Incentive Amount | T15: =Q104 -> 28220615
B16: RM INCENTIVE | E16: ='RM Calculation Pro Rata'!B135 -> 57534.068 | F16: ='RM Calculation Pro Rata'!C135 -> 73900.608 | G16: ='RM Calculation Pro Rata'!D135 -> 78383.449 | H16: ='RM Calculation Pro Rata'!I135 -> 84517.791 | I16: ='RM Calculation Pro Rata'!J135 -> 1245573.4 | Q16: =SUM(E16:P16) -> 1539909.3 | S16: Total Incentive Paid | T16: =AY104 -> 17453056
B17: ZM INCENTIVE | E17: 0 | Q17: =SUM(E17:P17) -> 0 | S17: Accumulation Above 2lacs | T17: =AH104 -> 10767559
B18: REVENUE (Marrow) | E18: ='Incentive Report- Output'!N93+'Incentive Report- Output'!O93 -> 1.0242471e+08 | F18: =+'Incentive Report- Output'!N188+'Incentive Report- Output'!O188 -> 1.4162671e+08 | G18: =+'Incentive Report- Output'!N284+'Incentive Report- Output'!O284 -> 1.2337624e+08 | H18: =+'Incentive Report- Output'!N382+'Incentive Report- Output'!O382 -> 1.0467109e+08 | I18: =+'Incentive Report- Output'!N481+'Incentive Report- Output'!O481 -> 8.353534e+08 | Q18: =SUM(E18:P18) -> 1.3074521e+09
B19: REVENUE (E-gurukul) | E19: 0 | F19: 0 | Q19: =SUM(E19:P19) -> 0 | S19: Accumulation withdrawn | T19: 0
B20: % of Revenue | E20: =(E15+E16+E21)/(E18+E19) -> 0.011828243 | F20: =(F15+F16+F21)/(F18+F19) -> 0.012978078 | G20: =(G15+G16+G21)/(G18+G19) -> 0.01306518 | H20: =(H15+H16+H21)/(H18+H19) -> 0.013751294 | I20: =(I15+I16+I21)/(I18+I19) -> 0.028322961 | Q20: =(Q15+Q16+Q21+Q17)/(Q18+Q19) -> 0.022762229
B21: Rewards ( Trip + Best RM Reward ) | E21: 0 | F21: 0 | Q21: =SUM(E21:P21) -> 0 | S21: =P18/O18 -> #DIV/0! | T21: 1 | U21: =T21-S21 -> #DIV/0!
B22: Penalty If any | E22: 0 | F22: 0 | Q22: =SUM(E22:P22) -> 0
B23: Total Incentive | E23: =SUBTOTAL(9,E25:E103) -> 1153970.2 | F23: =SUBTOTAL(9,F25:F103) -> 1764141.8 | G23: =SUBTOTAL(9,G25:G103) -> 1533549.3 | H23: =SUBTOTAL(9,H25:H103) -> 1354845.1 | I23: =SUBTOTAL(9,I25:I103) -> 22414109 | J23: =SUBTOTAL(9,J25:J103) -> 0 | K23: =SUBTOTAL(9,K25:K103) -> 0 | L23: =SUBTOTAL(9,L25:L103) -> 0 | ... Q23: =SUBTOTAL(9,Q25:Q103) -> 28220615 | S23: Cumulative Incentive | AJ23: Paid Incentive
B24: Employee Name | C24: Employee ID | D24: Designation | E24: April-26 | F24: 46143 | G24: 46174 | H24: 46204 | I24: 46235 | J24: 46266 | K24: 46296 | L24: 46327 | M24: 46357 | N24: 46388 | O24: 46419 | P24: 46447 | Q24: Total Incentive | S24: Employee Name | T24: Employee ID | U24: Designation | V24: April-26 | W24: 46143 | X24: 46174 | Y24: 46204 | Z24: 46235 | AA24: 46266 | AB24: 46296 | AC24: 46327 | AD24: 46357 | AE24: 46388 | AF24: 46419 | AG24: 46447 | AH24: Total Accumulation | AJ24: Employee Name | AK24: Employee ID | AL24: Designation | AM24: April-26 | AN24: 46143 | AO24: 46174 | AP24: 46204 | AQ24: 46235 | AR24: 46266 | AS24: 46296 | AT24: 46327 | AU24: 46357 | AV24: 46388 | AW24: 46419 | AX24: 46447 | AY24: Total Paid
B25: Ajeet Pandey | C25: NHP374 | D25: RM | E25: =SUMIF('Incentive Report- Output'!$B$4:$B$93,'Incentive Summary Output'!C25,'Incentive Report- Output'!$AF$4:$AF$93) -> 5032.9153 | F25: =SUMIF('Incentive Report- Output'!$B$98:$B$188,'Incentive Summary Output'!C25,'Incentive Report- Output'!$AF$98:$AF$188) -> 10166.483 | G25: =SUMIF('Incentive Report- Output'!$B$193:$B$283,'Incentive Summary Output'!C25,'Incentive Report- Output'!$AF$193:$AF$283) -> 6641.3432 | H25: =SUMIF('Incentive Report- Output'!$B$288:$B$382,'Incentive Summary Output'!C25,'Incentive Report- Output'!$AF$288:$AF$382) -> 0 | I25: =SUMIF('Incentive Report- Output'!$B$387:$B$480,'Incentive Summary Output'!C25,'Incentive Report- Output'!$AF$387:$AF$480) -> 544702.83 | Q25: =SUM(E25:P25) -> 566543.57 | S25: Ajeet Pandey | T25: NHP374 | U25: RM | V25: =IF(E25>200000,E25-200000,0) -> 0 | W25: =IF(F25>200000,F25-200000,0) -> 0 | X25: =IF(G25>200000,G25-200000,0) -> 0 | Y25: =IF(H25>200000,H25-200000,0) -> 0 | Z25: =IF(I25>200000,I25-200000,0) -> 344702.83 | AA25: =IF(J25>200000,J25-200000,0) -> 0 | AB25: =IF(K25>200000,K25-200000,0) -> 0 | AC25: =IF(L25>200000,L25-200000,0) -> 0 | ... AG25: =IF(P25>200000,P25-200000,0) -> 0 | AH25: =SUM(V25:AG25) -> 344702.83 | AJ25: Ajeet Pandey | AK25: NHP374 | AL25: RM | AM25: =E25-V25 -> 5032.9153 | AN25: =F25-W25 -> 10166.483 | AO25: =G25-X25 -> 6641.3432 | AP25: =H25-Y25 -> 0 | AQ25: =I25-Z25 -> 200000 | AR25: =J25-AA25 -> 0 | AS25: =K25-AB25 -> 0 | AT25: =L25-AC25 -> 0 | ... AX25: =P25-AG25 -> 0 | AY25: =SUM(AM25:AX25) -> 221840.74
B26: Ankit Madan | C26: NHP291 | D26: BDE | E26: =SUMIF('Incentive Report- Output'!$B$4:$B$93,'Incentive Summary Output'!C26,'Incentive Report- Output'!$AF$4:$AF$93) -> 16384.322 | F26: =SUMIF('Incentive Report- Output'!$B$98:$B$188,'Incentive Summary Output'!C26,'Incentive Report- Output'!$AF$98:$AF$188) -> 9887.8983 | G26: =SUMIF('Incentive Report- Output'!$B$193:$B$283,'Incentive Summary Output'!C26,'Incentive Report- Output'!$AF$193:$AF$283) -> 7365.9195 | H26: =SUMIF('Incentive Report- Output'!$B$288:$B$382,'Incentive Summary Output'!C26,'Incentive Report- Output'!$AF$288:$AF$382) -> 4320.0127 | I26: =SUMIF('Incentive Report- Output'!$B$387:$B$480,'Incentive Summary Output'!C26,'Incentive Report- Output'!$AF$387:$AF$480) -> 482371.07 | Q26: =SUM(E26:P26) -> 520329.22 | S26: Ankit Madan | T26: NHP291 | U26: BDE | V26: =IF(E26>200000,E26-200000,0) -> 0 | W26: =IF(F26>200000,F26-200000,0) -> 0 | X26: =IF(G26>200000,G26-200000,0) -> 0 | Y26: =IF(H26>200000,H26-200000,0) -> 0 | Z26: =IF(I26>200000,I26-200000,0) -> 282371.07 | AA26: =IF(J26>200000,J26-200000,0) -> 0 | AB26: =IF(K26>200000,K26-200000,0) -> 0 | AC26: =IF(L26>200000,L26-200000,0) -> 0 | ... AG26: =IF(P26>200000,P26-200000,0) -> 0 | AH26: =SUM(V26:AG26) -> 282371.07 | AJ26: Ankit Madan | AK26: NHP291 | AL26: BDE | AM26: =E26-V26 -> 16384.322 | AN26: =F26-W26 -> 9887.8983 | AO26: =G26-X26 -> 7365.9195 | AP26: =H26-Y26 -> 4320.0127 | AQ26: =I26-Z26 -> 200000 | AR26: =J26-AA26 -> 0 | AS26: =K26-AB26 -> 0 | AT26: =L26-AC26 -> 0 | ... AX26: =P26-AG26 -> 0 | AY26: =SUM(AM26:AX26) -> 237958.15
B27: Sachin Sharma | C27: NHP698 | D27: BDE | E27: =SUMIF('Incentive Report- Output'!$B$4:$B$93,'Incentive Summary Output'!C27,'Incentive Report- Output'!$AF$4:$AF$93) -> 0 | F27: =SUMIF('Incentive Report- Output'!$B$98:$B$188,'Incentive Summary Output'!C27,'Incentive Report- Output'!$AF$98:$AF$188) -> 65094.96 | G27: =SUMIF('Incentive Report- Output'!$B$193:$B$283,'Incentive Summary Output'!C27,'Incentive Report- Output'!$AF$193:$AF$283) -> 0 | H27: =SUMIF('Incentive Report- Output'!$B$288:$B$382,'Incentive Summary Output'!C27,'Incentive Report- Output'!$AF$288:$AF$382) -> 49999.83 | I27: =SUMIF('Incentive Report- Output'!$B$387:$B$480,'Incentive Summary Output'!C27,'Incentive Report- Output'!$AF$387:$AF$480) -> 418483.45 | Q27: =SUM(E27:P27) -> 533578.24 | S27: Sachin Sharma | T27: NHP698 | U27: BDE | V27: =IF(E27>200000,E27-200000,0) -> 0 | W27: =IF(F27>200000,F27-200000,0) -> 0 | X27: =IF(G27>200000,G27-200000,0) -> 0 | Y27: =IF(H27>200000,H27-200000,0) -> 0 | Z27: =IF(I27>200000,I27-200000,0) -> 218483.45 | AA27: =IF(J27>200000,J27-200000,0) -> 0 | AB27: =IF(K27>200000,K27-200000,0) -> 0 | AC27: =IF(L27>200000,L27-200000,0) -> 0 | ... AG27: =IF(P27>200000,P27-200000,0) -> 0 | AH27: =SUM(V27:AG27) -> 218483.45 | AJ27: Sachin Sharma | AK27: NHP698 | AL27: BDE | AM27: =E27-V27 -> 0 | AN27: =F27-W27 -> 65094.96 | AO27: =G27-X27 -> 0 | AP27: =H27-Y27 -> 49999.83 | AQ27: =I27-Z27 -> 200000 | AR27: =J27-AA27 -> 0 | AS27: =K27-AB27 -> 0 | AT27: =L27-AC27 -> 0 | ... AX27: =P27-AG27 -> 0 | AY27: =SUM(AM27:AX27) -> 315094.79
B28: Shariq Bhat | C28: NHP679 | D28: BDE | E28: =SUMIF('Incentive Report- Output'!$B$4:$B$93,'Incentive Summary Output'!C28,'Incentive Report- Output'!$AF$4:$AF$93) -> 13364.034 | F28: =SUMIF('Incentive Report- Output'!$B$98:$B$188,'Incentive Summary Output'!C28,'Incentive Report- Output'!$AF$98:$AF$188) -> 7496.6144 | G28: =SUMIF('Incentive Report- Output'!$B$193:$B$283,'Incentive Summary Output'!C28,'Incentive Report- Output'!$AF$193:$AF$283) -> 0 | H28: =SUMIF('Incentive Report- Output'!$B$288:$B$382,'Incentive Summary Output'!C28,'Incentive Report- Output'!$AF$288:$AF$382) -> 67499.898 | I28: =SUMIF('Incentive Report- Output'!$B$387:$B$480,'Incentive Summary Output'!C28,'Incentive Report- Output'!$AF$387:$AF$480) -> 451111.98 | Q28: =SUM(E28:P28) -> 539472.53 | S28: Shariq Bhat | T28: NHP679 | U28: BDE | V28: =IF(E28>200000,E28-200000,0) -> 0 | W28: =IF(F28>200000,F28-200000,0) -> 0 | X28: =IF(G28>200000,G28-200000,0) -> 0 | Y28: =IF(H28>200000,H28-200000,0) -> 0 | Z28: =IF(I28>200000,I28-200000,0) -> 251111.98 | AA28: =IF(J28>200000,J28-200000,0) -> 0 | AB28: =IF(K28>200000,K28-200000,0) -> 0 | AC28: =IF(L28>200000,L28-200000,0) -> 0 | ... AG28: =IF(P28>200000,P28-200000,0) -> 0 | AH28: =SUM(V28:AG28) -> 251111.98 | AJ28: Shariq Bhat | AK28: NHP679 | AL28: BDE | AM28: =E28-V28 -> 13364.034 | AN28: =F28-W28 -> 7496.6144 | AO28: =G28-X28 -> 0 | AP28: =H28-Y28 -> 67499.898 | AQ28: =I28-Z28 -> 200000 | AR28: =J28-AA28 -> 0 | AS28: =K28-AB28 -> 0 | AT28: =L28-AC28 -> 0 | ... AX28: =P28-AG28 -> 0 | AY28: =SUM(AM28:AX28) -> 288360.55
B29: Zahid Majeeb | C29: NHP479 | D29: BDE | E29: =SUMIF('Incentive Report- Output'!$B$4:$B$93,'Incentive Summary Output'!C29,'Incentive Report- Output'!$AF$4:$AF$93) -> 7347.2458 | F29: =SUMIF('Incentive Report- Output'!$B$98:$B$188,'Incentive Summary Output'!C29,'Incentive Report- Output'!$AF$98:$AF$188) -> 8391.2924 | G29: =SUMIF('Incentive Report- Output'!$B$193:$B$283,'Incentive Summary Output'!C29,'Incentive Report- Output'!$AF$193:$AF$283) -> 21395.627 | H29: =SUMIF('Incentive Report- Output'!$B$288:$B$382,'Incentive Summary Output'!C29,'Incentive Report- Output'!$AF$288:$AF$382) -> 0 | I29: =SUMIF('Incentive Report- Output'!$B$387:$B$480,'Incentive Summary Output'!C29,'Incentive Report- Output'!$AF$387:$AF$480) -> 449212.12 | Q29: =SUM(E29:P29) -> 486346.28 | S29: Zahid Majeeb | T29: NHP479 | U29: BDE | V29: =IF(E29>200000,E29-200000,0) -> 0 | W29: =IF(F29>200000,F29-200000,0) -> 0 | X29: =IF(G29>200000,G29-200000,0) -> 0 | Y29: =IF(H29>200000,H29-200000,0) -> 0 | Z29: =IF(I29>200000,I29-200000,0) -> 249212.12 | AA29: =IF(J29>200000,J29-200000,0) -> 0 | AB29: =IF(K29>200000,K29-200000,0) -> 0 | AC29: =IF(L29>200000,L29-200000,0) -> 0 | ... AG29: =IF(P29>200000,P29-200000,0) -> 0 | AH29: =SUM(V29:AG29) -> 249212.12 | AJ29: Zahid Majeeb | AK29: NHP479 | AL29: BDE | AM29: =E29-V29 -> 7347.2458 | AN29: =F29-W29 -> 8391.2924 | AO29: =G29-X29 -> 21395.627 | AP29: =H29-Y29 -> 0 | AQ29: =I29-Z29 -> 200000 | AR29: =J29-AA29 -> 0 | AS29: =K29-AB29 -> 0 | AT29: =L29-AC29 -> 0 | ... AX29: =P29-AG29 -> 0 | AY29: =SUM(AM29:AX29) -> 237134.17
B30: Akif Hannan | C30: NHP212 | D30: RM | E30: =SUMIF('Incentive Report- Output'!$B$4:$B$93,'Incentive Summary Output'!C30,'Incentive Report- Output'!$AF$4:$AF$93) -> 4900.9364 | F30: =SUMIF('Incentive Report- Output'!$B$98:$B$188,'Incentive Summary Output'!C30,'Incentive Report- Output'!$AF$98:$AF$188) -> 91033.805 | G30: =SUMIF('Incentive Report- Output'!$B$193:$B$283,'Incentive Summary Output'!C30,'Incentive Report- Output'!$AF$193:$AF$283) -> 89248.907 | H30: =SUMIF('Incentive Report- Output'!$B$288:$B$382,'Incentive Summary Output'!C30,'Incentive Report- Output'!$AF$288:$AF$382) -> 91124.542 | I30: =SUMIF('Incentive Report- Output'!$B$387:$B$480,'Incentive Summary Output'!C30,'Incentive Report- Output'!$AF$387:$AF$480) -> 1178119.6 | Q30: =SUM(E30:P30) -> 1454427.7 | S30: Akif Hannan | T30: NHP212 | U30: RM | V30: =IF(E30>200000,E30-200000,0) -> 0 | W30: =IF(F30>200000,F30-200000,0) -> 0 | X30: =IF(G30>200000,G30-200000,0) -> 0 | Y30: =IF(H30>200000,H30-200000,0) -> 0 | Z30: =IF(I30>200000,I30-200000,0) -> 978119.55 | AA30: =IF(J30>200000,J30-200000,0) -> 0 | AB30: =IF(K30>200000,K30-200000,0) -> 0 | AC30: =IF(L30>200000,L30-200000,0) -> 0 | ... AG30: =IF(P30>200000,P30-200000,0) -> 0 | AH30: =SUM(V30:AG30) -> 978119.55 | AJ30: Akif Hannan | AK30: NHP212 | AL30: RM | AM30: =E30-V30 -> 4900.9364 | AN30: =F30-W30 -> 91033.805 | AO30: =G30-X30 -> 89248.907 | AP30: =H30-Y30 -> 91124.542 | AQ30: =I30-Z30 -> 200000 | AR30: =J30-AA30 -> 0 | AS30: =K30-AB30 -> 0 | AT30: =L30-AC30 -> 0 | ... AX30: =P30-AG30 -> 0 | AY30: =SUM(AM30:AX30) -> 476308.19
B31: Ayush Choubey | C31: NHP727 | D31: BDE | E31: =SUMIF('Incentive Report- Output'!$B$4:$B$93,'Incentive Summary Output'!C31,'Incentive Report- Output'!$AF$4:$AF$93) -> 4968.0847 | F31: =SUMIF('Incentive Report- Output'!$B$98:$B$188,'Incentive Summary Output'!C31,'Incentive Report- Output'!$AF$98:$AF$188) -> 8240.6653 | G31: =SUMIF('Incentive Report- Output'!$B$193:$B$283,'Incentive Summary Output'!C31,'Incentive Report- Output'!$AF$193:$AF$283) -> 7635.1907 | H31: =SUMIF('Incentive Report- Output'!$B$288:$B$382,'Incentive Summary Output'!C31,'Incentive Report- Output'!$AF$288:$AF$382) -> 54812.517 | I31: =SUMIF('Incentive Report- Output'!$B$387:$B$480,'Incentive Summary Output'!C31,'Incentive Report- Output'!$AF$387:$AF$480) -> 172395 | Q31: =SUM(E31:P31) -> 248051.46 | S31: Ayush Choubey | T31: NHP727 | U31: BDE | V31: =IF(E31>200000,E31-200000,0) -> 0 | W31: =IF(F31>200000,F31-200000,0) -> 0 | X31: =IF(G31>200000,G31-200000,0) -> 0 | Y31: =IF(H31>200000,H31-200000,0) -> 0 | Z31: =IF(I31>200000,I31-200000,0) -> 0 | AA31: =IF(J31>200000,J31-200000,0) -> 0 | AB31: =IF(K31>200000,K31-200000,0) -> 0 | AC31: =IF(L31>200000,L31-200000,0) -> 0 | ... AG31: =IF(P31>200000,P31-200000,0) -> 0 | AH31: =SUM(V31:AG31) -> 0 | AJ31: Ayush Choubey | AK31: NHP727 | AL31: BDE | AM31: =E31-V31 -> 4968.0847 | AN31: =F31-W31 -> 8240.6653 | AO31: =G31-X31 -> 7635.1907 | AP31: =H31-Y31 -> 54812.517 | AQ31: =I31-Z31 -> 172395 | AR31: =J31-AA31 -> 0 | AS31: =K31-AB31 -> 0 | AT31: =L31-AC31 -> 0 | ... AX31: =P31-AG31 -> 0 | AY31: =SUM(AM31:AX31) -> 248051.46
B32: Rohit Bharti | C32: NHP395 | D32: BDE | E32: =SUMIF('Incentive Report- Output'!$B$4:$B$93,'Incentive Summary Output'!C32,'Incentive Report- Output'!$AF$4:$AF$93) -> 0 | F32: =SUMIF('Incentive Report- Output'!$B$98:$B$188,'Incentive Summary Output'!C32,'Incentive Report- Output'!$AF$98:$AF$188) -> 8665.8686 | G32: =SUMIF('Incentive Report- Output'!$B$193:$B$283,'Incentive Summary Output'!C32,'Incentive Report- Output'!$AF$193:$AF$283) -> 6801.75 | H32: =SUMIF('Incentive Report- Output'!$B$288:$B$382,'Incentive Summary Output'!C32,'Incentive Report- Output'!$AF$288:$AF$382) -> 6382.2712 | I32: =SUMIF('Incentive Report- Output'!$B$387:$B$480,'Incentive Summary Output'!C32,'Incentive Report- Output'!$AF$387:$AF$480) -> 327714.41 | Q32: =SUM(E32:P32) -> 349564.3 | S32: Rohit Bharti | T32: NHP395 | U32: BDE | V32: =IF(E32>200000,E32-200000,0) -> 0 | W32: =IF(F32>200000,F32-200000,0) -> 0 | X32: =IF(G32>200000,G32-200000,0) -> 0 | Y32: =IF(H32>200000,H32-200000,0) -> 0 | Z32: =IF(I32>200000,I32-200000,0) -> 127714.41 | AA32: =IF(J32>200000,J32-200000,0) -> 0 | AB32: =IF(K32>200000,K32-200000,0) -> 0 | AC32: =IF(L32>200000,L32-200000,0) -> 0 | ... AG32: =IF(P32>200000,P32-200000,0) -> 0 | AH32: =SUM(V32:AG32) -> 127714.41 | AJ32: Rohit Bharti | AK32: NHP395 | AL32: BDE | AM32: =E32-V32 -> 0 | AN32: =F32-W32 -> 8665.8686 | AO32: =G32-X32 -> 6801.75 | AP32: =H32-Y32 -> 6382.2712 | AQ32: =I32-Z32 -> 200000 | AR32: =J32-AA32 -> 0 | AS32: =K32-AB32 -> 0 | AT32: =L32-AC32 -> 0 | ... AX32: =P32-AG32 -> 0 | AY32: =SUM(AM32:AX32) -> 221849.89
B33: Sumit Kumar Singh | C33: NHP709 | D33: BDE | E33: =SUMIF('Incentive Report- Output'!$B$4:$B$93,'Incentive Summary Output'!C33,'Incentive Report- Output'!$AF$4:$AF$93) -> 5893.5085 | F33: =SUMIF('Incentive Report- Output'!$B$98:$B$188,'Incentive Summary Output'!C33,'Incentive Report- Output'!$AF$98:$AF$188) -> 6472.4873 | G33: =SUMIF('Incentive Report- Output'!$B$193:$B$283,'Incentive Summary Output'!C33,'Incentive Report- Output'!$AF$193:$AF$283) -> 7379.678 | H33: =SUMIF('Incentive Report- Output'!$B$288:$B$382,'Incentive Summary Output'!C33,'Incentive Report- Output'!$AF$288:$AF$382) -> 14478.898 | I33: =SUMIF('Incentive Report- Output'!$B$387:$B$480,'Incentive Summary Output'!C33,'Incentive Report- Output'!$AF$387:$AF$480) -> 401696.52 | Q33: =SUM(E33:P33) -> 435921.09 | S33: Sumit Kumar Singh | T33: NHP709 | U33: BDE | V33: =IF(E33>200000,E33-200000,0) -> 0 | W33: =IF(F33>200000,F33-200000,0) -> 0 | X33: =IF(G33>200000,G33-200000,0) -> 0 | Y33: =IF(H33>200000,H33-200000,0) -> 0 | Z33: =IF(I33>200000,I33-200000,0) -> 201696.52 | AA33: =IF(J33>200000,J33-200000,0) -> 0 | AB33: =IF(K33>200000,K33-200000,0) -> 0 | AC33: =IF(L33>200000,L33-200000,0) -> 0 | ... AG33: =IF(P33>200000,P33-200000,0) -> 0 | AH33: =SUM(V33:AG33) -> 201696.52 | AJ33: Sumit Kumar Singh | AK33: NHP709 | AL33: BDE | AM33: =E33-V33 -> 5893.5085 | AN33: =F33-W33 -> 6472.4873 | AO33: =G33-X33 -> 7379.678 | AP33: =H33-Y33 -> 14478.898 | AQ33: =I33-Z33 -> 200000 | AR33: =J33-AA33 -> 0 | AS33: =K33-AB33 -> 0 | AT33: =L33-AC33 -> 0 | ... AX33: =P33-AG33 -> 0 | AY33: =SUM(AM33:AX33) -> 234224.57
B34: Anjaney | C34: NHP144 | D34: RM | E34: =SUMIF('Incentive Report- Output'!$B$4:$B$93,'Incentive Summary Output'!C34,'Incentive Report- Output'!$AF$4:$AF$93) -> 0 | F34: =SUMIF('Incentive Report- Output'!$B$98:$B$188,'Incentive Summary Output'!C34,'Incentive Report- Output'!$AF$98:$AF$188) -> 0 | G34: =SUMIF('Incentive Report- Output'!$B$193:$B$283,'Incentive Summary Output'!C34,'Incentive Report- Output'!$AF$193:$AF$283) -> 0 | H34: =SUMIF('Incentive Report- Output'!$B$288:$B$382,'Incentive Summary Output'!C34,'Incentive Report- Output'!$AF$288:$AF$382) -> 0 | I34: =SUMIF('Incentive Report- Output'!$B$387:$B$480,'Incentive Summary Output'!C34,'Incentive Report- Output'!$AF$387:$AF$480) -> 416765.19 | Q34: =SUM(E34:P34) -> 416765.19 | S34: Anjaney | T34: NHP144 | U34: RM | V34: =IF(E34>200000,E34-200000,0) -> 0 | W34: =IF(F34>200000,F34-200000,0) -> 0 | X34: =IF(G34>200000,G34-200000,0) -> 0 | Y34: =IF(H34>200000,H34-200000,0) -> 0 | Z34: =IF(I34>200000,I34-200000,0) -> 216765.19 | AA34: =IF(J34>200000,J34-200000,0) -> 0 | AB34: =IF(K34>200000,K34-200000,0) -> 0 | AC34: =IF(L34>200000,L34-200000,0) -> 0 | ... AG34: =IF(P34>200000,P34-200000,0) -> 0 | AH34: =SUM(V34:AG34) -> 216765.19 | AJ34: Anjaney | AK34: NHP144 | AL34: RM | AM34: =E34-V34 -> 0 | AN34: =F34-W34 -> 0 | AO34: =G34-X34 -> 0 | AP34: =H34-Y34 -> 0 | AQ34: =I34-Z34 -> 200000 | AR34: =J34-AA34 -> 0 | AS34: =K34-AB34 -> 0 | AT34: =L34-AC34 -> 0 | ... AX34: =P34-AG34 -> 0 | AY34: =SUM(AM34:AX34) -> 200000
B35: Abhishek Sinha | C35: NHP815 | D35: BDE | E35: =SUMIF('Incentive Report- Output'!$B$4:$B$93,'Incentive Summary Output'!C35,'Incentive Report- Output'!$AF$4:$AF$93) -> 13950.508 | F35: =SUMIF('Incentive Report- Output'!$B$98:$B$188,'Incentive Summary Output'!C35,'Incentive Report- Output'!$AF$98:$AF$188) -> 78091.017 | G35: =SUMIF('Incentive Report- Output'!$B$193:$B$283,'Incentive Summary Output'!C35,'Incentive Report- Output'!$AF$193:$AF$283) -> 0 | H35: =SUMIF('Incentive Report- Output'!$B$288:$B$382,'Incentive Summary Output'!C35,'Incentive Report- Output'!$AF$288:$AF$382) -> 0 | I35: =SUMIF('Incentive Report- Output'!$B$387:$B$480,'Incentive Summary Output'!C35,'Incentive Report- Output'!$AF$387:$AF$480) -> 427882.55 | Q35: =SUM(E35:P35) -> 519924.08 | S35: Abhishek Sinha | T35: NHP815 | U35: BDE | V35: =IF(E35>200000,E35-200000,0) -> 0 | W35: =IF(F35>200000,F35-200000,0) -> 0 | X35: =IF(G35>200000,G35-200000,0) -> 0 | Y35: =IF(H35>200000,H35-200000,0) -> 0 | Z35: =IF(I35>200000,I35-200000,0) -> 227882.55 | AA35: =IF(J35>200000,J35-200000,0) -> 0 | AB35: =IF(K35>200000,K35-200000,0) -> 0 | AC35: =IF(L35>200000,L35-200000,0) -> 0 | ... AG35: =IF(P35>200000,P35-200000,0) -> 0 | AH35: =SUM(V35:AG35) -> 227882.55 | AJ35: Abhishek Sinha | AK35: NHP815 | AL35: BDE | AM35: =E35-V35 -> 13950.508 | AN35: =F35-W35 -> 78091.017 | AO35: =G35-X35 -> 0 | AP35: =H35-Y35 -> 0 | AQ35: =I35-Z35 -> 200000 | AR35: =J35-AA35 -> 0 | AS35: =K35-AB35 -> 0 | AT35: =L35-AC35 -> 0 | ... AX35: =P35-AG35 -> 0 | AY35: =SUM(AM35:AX35) -> 292041.53
B36: Adnan Akhtar | C36: NHP170 | D36: BDE | E36: =SUMIF('Incentive Report- Output'!$B$4:$B$93,'Incentive Summary Output'!C36,'Incentive Report- Output'!$AF$4:$AF$93) -> 7714.6441 | F36: =SUMIF('Incentive Report- Output'!$B$98:$B$188,'Incentive Summary Output'!C36,'Incentive Report- Output'!$AF$98:$AF$188) -> 60451.093 | G36: =SUMIF('Incentive Report- Output'!$B$193:$B$283,'Incentive Summary Output'!C36,'Incentive Report- Output'!$AF$193:$AF$283) -> 6702.8178 | H36: =SUMIF('Incentive Report- Output'!$B$288:$B$382,'Incentive Summary Output'!C36,'Incentive Report- Output'!$AF$288:$AF$382) -> 16183.992 | I36: =SUMIF('Incentive Report- Output'!$B$387:$B$480,'Incentive Summary Output'!C36,'Incentive Report- Output'!$AF$387:$AF$480) -> 539778.41 | Q36: =SUM(E36:P36) -> 630830.95 | S36: Adnan Akhtar | T36: NHP170 | U36: BDE | V36: =IF(E36>200000,E36-200000,0) -> 0 | W36: =IF(F36>200000,F36-200000,0) -> 0 | X36: =IF(G36>200000,G36-200000,0) -> 0 | Y36: =IF(H36>200000,H36-200000,0) -> 0 | Z36: =IF(I36>200000,I36-200000,0) -> 339778.41 | AA36: =IF(J36>200000,J36-200000,0) -> 0 | AB36: =IF(K36>200000,K36-200000,0) -> 0 | AC36: =IF(L36>200000,L36-200000,0) -> 0 | ... AG36: =IF(P36>200000,P36-200000,0) -> 0 | AH36: =SUM(V36:AG36) -> 339778.41 | AJ36: Adnan Akhtar | AK36: NHP170 | AL36: BDE | AM36: =E36-V36 -> 7714.6441 | AN36: =F36-W36 -> 60451.093 | AO36: =G36-X36 -> 6702.8178 | AP36: =H36-Y36 -> 16183.992 | AQ36: =I36-Z36 -> 200000 | AR36: =J36-AA36 -> 0 | AS36: =K36-AB36 -> 0 | AT36: =L36-AC36 -> 0 | ... AX36: =P36-AG36 -> 0 | AY36: =SUM(AM36:AX36) -> 291052.55
... B103: Nav Nandh Tej | C103: NHP621 | D103: BDE | E103: =SUMIF('Incentive Report- Output'!$B$4:$B$93,'Incentive Summary Output'!C103,'Incentive Report- Output'!$AF$4:$AF$93) -> 5050.3093 | F103: =SUMIF('Incentive Report- Output'!$B$98:$B$188,'Incentive Summary Output'!C103,'Incentive Report- Output'!$AF$98:$AF$188) -> 0 | G103: =SUMIF('Incentive Report- Output'!$B$193:$B$283,'Incentive Summary Output'!C103,'Incentive Report- Output'!$AF$193:$AF$283) -> 0 | H103: =SUMIF('Incentive Report- Output'!$B$288:$B$382,'Incentive Summary Output'!C103,'Incentive Report- Output'!$AF$288:$AF$382) -> 0 | I103: =SUMIF('Incentive Report- Output'!$B$387:$B$480,'Incentive Summary Output'!C103,'Incentive Report- Output'!$AF$387:$AF$480) -> 0 | Q103: =SUM(E103:P103) -> 5050.3093 | S103: Nav Nandh Tej | T103: NHP621 | U103: BDE | V103: =IF(E103>200000,E103-200000,0) -> 0 | W103: =IF(F103>200000,F103-200000,0) -> 0 | X103: =IF(G103>200000,G103-200000,0) -> 0 | Y103: =IF(H103>200000,H103-200000,0) -> 0 | Z103: =IF(I103>200000,I103-200000,0) -> 0 | AA103: =IF(J103>200000,J103-200000,0) -> 0 | AB103: =IF(K103>200000,K103-200000,0) -> 0 | AC103: =IF(L103>200000,L103-200000,0) -> 0 | ... AG103: =IF(P103>200000,P103-200000,0) -> 0 | AH103: =SUM(V103:AG103) -> 0 | AJ103: Nav Nandh Tej | AK103: NHP621 | AL103: BDE | AM103: =E103-V103 -> 5050.3093 | AN103: =F103-W103 -> 0 | AO103: =G103-X103 -> 0 | AP103: =H103-Y103 -> 0 | AQ103: =I103-Z103 -> 0 | AR103: =J103-AA103 -> 0 | AS103: =K103-AB103 -> 0 | AT103: =L103-AC103 -> 0 | ... AX103: =P103-AG103 -> 0 | AY103: =SUM(AM103:AX103) -> 5050.3093
C104: Total | E104: =SUM(E25:E103) -> 1153970.2 | F104: =SUM(F25:F103) -> 1764141.8 | G104: =SUM(G25:G103) -> 1533549.3 | H104: =SUM(H25:H103) -> 1354845.1 | I104: =SUM(I25:I103) -> 22414109 | J104: =SUM(J25:J103) -> 0 | K104: =SUM(K25:K103) -> 0 | L104: =SUM(L25:L103) -> 0 | ... Q104: =SUM(Q25:Q103) -> 28220615 | T104: Total | V104: =SUM(V25:V103) -> 0 | W104: =SUM(W25:W103) -> 0 | X104: =SUM(X25:X103) -> 0 | Y104: =SUM(Y25:Y103) -> 0 | Z104: =SUM(Z25:Z103) -> 10767559 | AA104: =SUM(AA25:AA103) -> 0 | AB104: =SUM(AB25:AB103) -> 0 | AC104: =SUM(AC25:AC103) -> 0 | ... AH104: =SUM(AH25:AH103) -> 10767559 | AK104: Total | AM104: =SUM(AM25:AM103) -> 1153970.2 | AN104: =SUM(AN25:AN103) -> 1764141.8 | AO104: =SUM(AO25:AO103) -> 1533549.3 | AP104: =SUM(AP25:AP103) -> 1354845.1 | AQ104: =SUM(AQ25:AQ103) -> 11646549 | AR104: =SUM(AR25:AR103) -> 0 | AS104: =SUM(AS25:AS103) -> 0 | AT104: =SUM(AT25:AT103) -> 0 | ... AY104: =SUM(AY25:AY103) -> 17453056

Sheet Target Achieved- Input
A1: 46113 | J1: Gross Sales | Q1: Disqualified Sales | X1: Foundation Sales
A2: Field Sales Targets Arpil 2026-27 | J2: Region | K2: Agent Name | L2: Employee ID | M2: Sum of paid_amount | N2: Sum of paid_amount_*_100/118 | O2: Count of payment_id | Q2: Region | R2: Agent Name | S2: Employee ID | T2: Sum of paid_amount | U2: Sum of paid_amount_*_100/118 | V2: Count of payment_id | X2: Region | Y2: Agent Name | Z2: Employee ID | AA2: Sum of paid_amount | AB2: Sum of paid_amount_*_100/118 | AC2: Count of payment_id
A3: Troopers | B3: Employee IDs | C3: Submanagers | D3: Zone | E3: RM | F3: ZM | G3: April Base | H3: April WC | J3: R1-Ajeet | K3: Ajeet Pandey | L3: NHP374 | M3: 1387763 | N3: 1176070.3 | O3: 37 | Q3: R1-Ajeet | R3: Ajeet Pandey | S3: NHP374 | T3: 199995 | U3: 169487.29 | V3: 5 | X3: R1-Ajeet | Y3: Ajeet Pandey | Z3: NHP374 | AA3: 11998 | AB3: 10167.797 | AC3: 2
A4: Ajeet Pandey | B4: NHP374 | D4: R1-Ajeet | E4: Ajeet Pandey | F4: Divyansh Pandey | G4: 60 | H4: 78 | J4: R1-Ajeet | K4: Ankit Madan | L4: NHP291 | M4: 1999998 | N4: 1694913.6 | O4: 52 | Q4: R1-Ajeet | R4: Ankit Madan | S4: NHP291 | T4: 66648 | U4: 56481.356 | V4: 2 | X4: R1-Ajeet | Y4: Ankit Madan | Z4: NHP291 | AA4: 34995 | AB4: 29656.78 | AC4: 5
A5: Ankit Madan | B5: NHP291 | D5: R1-Ajeet | E5: Ajeet Pandey | F5: Divyansh Pandey | G5: 60 | H5: 78 | J5: R1-Ajeet | K5: Sachin Sharma | L5: NHP698 | M5: 982522 | N5: 832645.76 | O5: 28 | Q5: R1-Ajeet | R5: Sachin Sharma | S5: NHP698 | T5: 141996 | U5: 120335.59 | V5: 4 | X5: R1-Ajeet | Y5: Sachin Sharma | Z5: NHP698 | AA5: 46993 | AB5: 39824.576 | AC5: 7
A6: Sachin Sharma | B6: NHP698 | D6: R1-Ajeet | E6: Ajeet Pandey | F6: Divyansh Pandey | G6: 50 | H6: 65 | J6: R1-Ajeet | K6: Shariq Bhat | L6: NHP679 | M6: 1616955 | N6: 1370300.8 | O6: 45 | Q6: R1-Ajeet | R6: Shariq Bhat | S6: NHP679 | T6: 39999 | U6: 33897.458 | V6: 1 | X6: R1-Ajeet | Y6: Shariq Bhat | Z6: NHP679 | AA6: 5999 | AB6: 5083.8983 | AC6: 1
A7: Shariq Bhat | B7: NHP679 | D7: R1-Ajeet | E7: Ajeet Pandey | F7: Divyansh Pandey | G7: 50 | H7: 65 | J7: R1-Ajeet | K7: Zahid Majeeb | L7: NHP479 | M7: 1773949 | N7: 1503346.6 | O7: 51 | Q7: R1-Ajeet | R7: Zahid Majeeb | S7: NHP479 | T7: 39999 | U7: 33897.458 | V7: 1 | X7: R1-Ajeet | Y7: Zahid Majeeb | Z7: NHP479 | AA7: 0
A8: Zahid Majeeb | B8: NHP479 | D8: R1-Ajeet | E8: Ajeet Pandey | F8: Divyansh Pandey | G8: 60 | H8: 78 | J8: R1-Ajeet Total | M8: 7761187 | N8: 6577277.1 | O8: 213 | Q8: R1-Ajeet Total | T8: 488637 | U8: 414099.15 | V8: 13 | X8: R1-Ajeet Total | AA8: 99985 | AB8: 84733.051 | AC8: 15
A9: Akif Hannan | B9: NHP212 | D9: R2-Akif | E9: Akif Hannan | F9: Divyansh Pandey | G9: 50 | H9: 65 | J9: R2-Akif | K9: Akif Hannan | L9: NHP212 | M9: 1156621 | N9: 980187.29 | O9: 29 | Q9: R2-Akif | R9: Akif Hannan | S9: NHP212 | T9: 0 | X9: R2-Akif | Y9: Akif Hannan | Z9: NHP212 | AA9: 0
A10: Ayush Choubey | B10: NHP727 | D10: R2-Akif | E10: Akif Hannan | F10: Divyansh Pandey | G10: 50 | H10: 65 | J10: R2-Akif | K10: Ayush Choubey | L10: NHP727 | M10: 1225766 | N10: 1038784.7 | O10: 34 | Q10: R2-Akif | R10: Ayush Choubey | S10: NHP727 | T10: 53298 | U10: 45167.797 | V10: 2 | X10: R2-Akif | Y10: Ayush Choubey | Z10: NHP727 | AA10: 29995 | AB10: 25419.492 | AC10: 5
A11: Rohit Bharti | B11: NHP395 | D11: R2-Akif | E11: Akif Hannan | F11: Divyansh Pandey | G11: 60 | H11: 78 | J11: R2-Akif | K11: Rohit Bharti | L11: NHP395 | M11: 1102419 | N11: 934253.39 | O11: 31 | Q11: R2-Akif | R11: Rohit Bharti | S11: NHP395 | T11: 261293 | U11: 221434.75 | V11: 7 | X11: R2-Akif | Y11: Rohit Bharti | Z11: NHP395 | AA11: 35994 | AB11: 30503.39 | AC11: 6
A12: Sumit Kumar | B12: NHP709 | D12: R2-Akif | E12: Akif Hannan | F12: Divyansh Pandey | G12: 50 | H12: 65 | J12: R2-Akif | K12: Sumit Kumar Singh | L12: NHP709 | M12: 1390868 | N12: 1178701.7 | O12: 32 | Q12: R2-Akif | R12: Sumit Kumar Singh | S12: NHP709 | T12: 0 | X12: R2-Akif | Y12: Sumit Kumar Singh | Z12: NHP709 | AA12: 11998 | AB12: 10167.797 | AC12: 2
A13: Abhishek Sinha | B13: NHP815 | D13: R3-Anjaney | E13: Anjaney Tripathi | F13: Divyansh Pandey | G13: 50 | H13: 65 | J13: R2-Akif Total | M13: 4875674 | N13: 4131927.1 | O13: 126 | Q13: R2-Akif Total | T13: 314591 | U13: 266602.54 | V13: 9 | X13: R2-Akif Total | AA13: 77987 | AB13: 66090.678 | AC13: 13
A14: Adnan Akhtar | B14: NHP170 | D14: R3-Anjaney | E14: Anjaney Tripathi | F14: Divyansh Pandey | G14: 70 | H14: 91 | J14: R3-Anjaney | K14: Abhishek Sinha | L14: NHP815 | M14: 1646160 | N14: 1395050.8 | O14: 40 | Q14: R3-Anjaney | R14: Abhishek Sinha | S14: NHP815 | T14: 0 | X14: R3-Anjaney | Y14: Abhishek Sinha | Z14: NHP815 | AA14: 0
A15: Anjaney Tripathi | B15: NHP144 | D15: R3-Anjaney | E15: Anjaney Tripathi | F15: Divyansh Pandey | G15: 50 | H15: 65 | J15: R3-Anjaney | K15: Adnan Akhtar | L15: NHP170 | M15: 2078651 | N15: 1761568.6 | O15: 49 | Q15: R3-Anjaney | R15: Adnan Akhtar | S15: NHP170 | T15: 257995 | U15: 218639.83 | V15: 5 | X15: R3-Anjaney | Y15: Adnan Akhtar | Z15: NHP170 | AA15: 11998 | AB15: 10167.797 | AC15: 2
A16: Anurag Bhargava | B16: NHP290 | D16: R3-Anjaney | E16: Anjaney Tripathi | F16: Divyansh Pandey | G16: 70 | H16: 91 | J16: R3-Anjaney | K16: Anjaney | L16: NHP144 | M16: 567639 | N16: 481050 | O16: 11 | Q16: R3-Anjaney | R16: Anjaney | S16: NHP144 | T16: 567639 | U16: 481050 | V16: 11 | X16: R3-Anjaney | Y16: Anjaney | Z16: NHP144 | AA16: 0
A17: Arshad Khan | B17: NHP561 | C17: Anurag Bhargava | D17: R3-Anjaney | E17: Anjaney Tripathi | F17: Divyansh Pandey | G17: 70 | H17: 91 | J17: R3-Anjaney | K17: Anurag Bhargava | L17: NHP290 | M17: 2314593 | N17: 1961519.5 | O17: 57 | Q17: R3-Anjaney | R17: Anurag Bhargava | S17: NHP290 | T17: 0 | X17: R3-Anjaney | Y17: Anurag Bhargava | Z17: NHP290 | AA17: 23996 | AB17: 20335.593 | AC17: 4
A18: Nikhil D | B18: NHP153 | D18: R3-Anjaney | E18: Anjaney Tripathi | F18: Divyansh Pandey | G18: 70 | H18: 91 | J18: R3-Anjaney | K18: Arshad Khan | L18: NHP561 | M18: 1283266 | N18: 1087513.6 | O18: 34 | Q18: R3-Anjaney | R18: Arshad Khan | S18: NHP561 | T18: 0 | X18: R3-Anjaney | Y18: Arshad Khan | Z18: NHP561 | AA18: 11998 | AB18: 10167.797 | AC18: 2
A19: Sangram Singh | B19: NHP620 | D19: R3-Anjaney | E19: Anjaney Tripathi | F19: Divyansh Pandey | G19: 70 | H19: 91 | J19: R3-Anjaney | K19: Nikhil | L19: NHP153 | M19: 2593239 | N19: 2197660.2 | O19: 61 | Q19: R3-Anjaney | R19: Nikhil | S19: NHP153 | T19: 319994 | U19: 271181.36 | V19: 6 | X19: R3-Anjaney | Y19: Nikhil | Z19: NHP153 | AA19: 11998 | AB19: 10167.797 | AC19: 2
A20: Shubham Vyas | B20: NHP466 | D20: R3-Anjaney | E20: Anjaney Tripathi | F20: Divyansh Pandey | G20: 60 | H20: 78 | J20: R3-Anjaney | K20: Shubham Vyas | L20: NHP466 | M20: 832680 | N20: 705661.02 | O20: 20 | Q20: R3-Anjaney | R20: Shubham Vyas | S20: NHP466 | T20: 101797 | U20: 86268.644 | V20: 3 | X20: R3-Anjaney | Y20: Shubham Vyas | Z20: NHP466 | AA20: 5999 | AB20: 5083.8983 | AC20: 1
A21: Adarsh Kumar | B21: NHP670 | D21: R4-Sohaib | E21: Sohaib Ahmed | F21: Divyansh Pandey | G21: 50 | H21: 65 | J21: R3-Anjaney | K21: Sangram Singh | L21: NHP620 | M21: 1826908 | N21: 1548227.1 | O21: 42 | Q21: R3-Anjaney | R21: Sangram Singh | S21: NHP620 | T21: 0 | X21: R3-Anjaney | Y21: Sangram Singh | Z21: NHP620 | AA21: 20997 | AB21: 17794.068 | AC21: 3
A22: Ankit Jha | B22: NHP672 | D22: R4-Sohaib | E22: Sohaib Ahmed | F22: Divyansh Pandey | G22: 50 | H22: 65 | J22: R3-Anjaney Total | M22: 13143136 | N22: 11138251 | O22: 314 | Q22: R3-Anjaney Total | T22: 1247425 | U22: 1057139.8 | V22: 25 | X22: R3-Anjaney Total | AA22: 86986 | AB22: 73716.949 | AC22: 14
A23: Sohaib Ahmed | B23: NHP173 | D23: R4-Sohaib | E23: Sohaib Ahmed | F23: Divyansh Pandey | G23: 60 | H23: 78 | J23: R4-Sohaib | K23: Adarsh Kumar | L23: NHP670 | M23: 1096521 | N23: 929255.08 | O23: 29 | Q23: R4-Sohaib | R23: Adarsh Kumar | S23: NHP670 | T23: 136446 | U23: 115632.2 | V23: 4 | X23: R4-Sohaib | Y23: Adarsh Kumar | Z23: NHP670 | AA23: 30995 | AB23: 26266.949 | AC23: 5
A24: Masud Rana | B24: NHP386 | D24: R5-Susmita | E24: Susmita Paul | F24: Biswadip Sarkar | G24: 65 | H24: 84.5 | J24: R4-Sohaib | K24: Ankit Jha | L24: NHP672 | M24: 815227 | N24: 690870.34 | O24: 23 | Q24: R4-Sohaib | R24: Ankit Jha | S24: NHP672 | T24: 229794 | U24: 194740.68 | V24: 6 | X24: R4-Sohaib | Y24: Ankit Jha | Z24: NHP672 | AA24: 23996 | AB24: 20335.593 | AC24: 4
A25: Nildeep Dasgupta | B25: NHP807 | D25: R5-Susmita | E25: Susmita Paul | F25: Biswadip Sarkar | G25: 30 | H25: 39 | J25: R4-Sohaib | K25: Sohaib Ahmed | L25: NHP173 | M25: 1818156 | N25: 1540810.2 | O25: 44 | Q25: R4-Sohaib | R25: Sohaib Ahmed | S25: NHP173 | T25: 119997 | U25: 101692.37 | V25: 3 | X25: R4-Sohaib | Y25: Sohaib Ahmed | Z25: NHP173 | AA25: 30995 | AB25: 26266.949 | AC25: 5
A26: Nilotpal Sharma | B26: NHP675 | C26: Masud Rana | D26: R5-Susmita | E26: Susmita Paul | F26: Biswadip Sarkar | G26: 50 | H26: 65 | J26: R4-Sohaib Total | M26: 3729904 | N26: 3160935.6 | O26: 96 | Q26: R4-Sohaib Total | T26: 486237 | U26: 412065.25 | V26: 13 | X26: R4-Sohaib Total | AA26: 85986 | AB26: 72869.492 | AC26: 14
A27: Sambit Kumar | B27: NHP717 | C27: Subash Debnath | D27: R5-Susmita | E27: Susmita Paul | F27: Biswadip Sarkar | G27: 60 | H27: 78 | J27: R5-Susmita | K27: Masud Rana | L27: NHP386 | M27: 2390739 | N27: 2026050 | O27: 61 | Q27: R5-Susmita | R27: Masud Rana | S27: NHP386 | T27: 0 | X27: R5-Susmita | Y27: Masud Rana | Z27: NHP386 | AA27: 35994 | AB27: 30503.39 | AC27: 6
A28: Satyaki Acharjee | B28: NHP826 | C28: Masud Rana | D28: R5-Susmita | E28: Susmita Paul | F28: Biswadip Sarkar | G28: 50 | H28: 65 | J28: R5-Susmita | K28: Nildeep Dasgupta | L28: NHP807 | M28: 680078 | N28: 576337.29 | O28: 22 | Q28: R5-Susmita | R28: Nildeep Dasgupta | S28: NHP807 | T28: 125994 | U28: 106774.58 | V28: 6 | X28: R5-Susmita | Y28: Nildeep Dasgupta | Z28: NHP807 | AA28: 41993 | AB28: 35587.288 | AC28: 7
A29: Sriti Jaiswal | B29: NHP553 | D29: R5-Susmita | E29: Susmita Paul | F29: Biswadip Sarkar | G29: 65 | H29: 84.5 | J29: R5-Susmita | K29: Nilotpal Sharma | L29: NHP675 | M29: 1659358 | N29: 1406235.6 | O29: 42 | Q29: R5-Susmita | R29: Nilotpal Sharma | S29: NHP675 | T29: 0 | X29: R5-Susmita | Y29: Nilotpal Sharma | Z29: NHP675 | AA29: 24996 | AB29: 21183.051 | AC29: 4
A30: Subash Debnath | B30: NHP148 | D30: R5-Susmita | E30: Susmita Paul | F30: Biswadip Sarkar | G30: 65 | H30: 84.5 | J30: R5-Susmita | K30: Sambit Kumar | L30: NHP717 | M30: 1854207 | N30: 1571361.9 | O30: 43 | Q30: R5-Susmita | R30: Sambit Kumar | S30: NHP717 | T30: 0 | X30: R5-Susmita | Y30: Sambit Kumar | Z30: NHP717 | AA30: 23996 | AB30: 20335.593 | AC30: 4
A31: Susmita Paul | B31: NHP166 | D31: R5-Susmita | E31: Susmita Paul | F31: Biswadip Sarkar | G31: 70 | H31: 91 | J31: R5-Susmita | K31: Sriti Jaiswal | L31: NHP553 | M31: 3472358 | N31: 2942676.3 | O31: 92 | Q31: R5-Susmita | R31: Sriti Jaiswal | S31: NHP553 | T31: 0 | X31: R5-Susmita | Y31: Sriti Jaiswal | Z31: NHP553 | AA31: 96984 | AB31: 82189.831 | AC31: 16
A32: Akar Srivastava | B32: NHP169 | D32: R6-Independent(Biswadip) | F32: Biswadip Sarkar | G32: 50 | H32: 65 | J32: R5-Susmita | K32: Subash Debnath | L32: NHP148 | M32: 3447765 | N32: 2921834.7 | O32: 85 | Q32: R5-Susmita | R32: Subash Debnath | S32: NHP148 | T32: 0 | X32: R5-Susmita | Y32: Subash Debnath | Z32: NHP148 | AA32: 41993 | AB32: 35587.288 | AC32: 7
A33: Faiq Khan | B33: NHP155 | D33: R6-Independent(Biswadip) | F33: Biswadip Sarkar | G33: 60 | H33: 78 | J33: R5-Susmita | K33: Susmita Paul | L33: NHP166 | M33: 4975016 | N33: 4216115.3 | O33: 134 | Q33: R5-Susmita | R33: Susmita Paul | S33: NHP166 | T33: 0 | X33: R5-Susmita | Y33: Susmita Paul | Z33: NHP166 | AA33: 119980 | AB33: 101677.97 | AC33: 20
A34: Manoj Sharma | B34: NHP470 | D34: R6-Independent(Biswadip) | F34: Biswadip Sarkar | G34: 60 | H34: 78 | J34: R5-Susmita | K34: Satyaki Acharjee | L34: NHP826 | M34: 1043673 | N34: 884468.64 | O34: 27 | Q34: R5-Susmita | R34: Satyaki Acharjee | S34: NHP826 | T34: 0 | X34: R5-Susmita | Y34: Satyaki Acharjee | Z34: NHP826 | AA34: 17997 | AB34: 15251.695 | AC34: 3
A35: Mudit Raj | B35: NHP142 | D35: R6-Independent(Biswadip) | F35: Biswadip Sarkar | G35: 60 | H35: 78 | J35: R5-Susmita Total | M35: 19523194 | N35: 16545080 | O35: 506 | Q35: R5-Susmita Total | T35: 125994 | U35: 106774.58 | V35: 6 | X35: R5-Susmita Total | AA35: 403933 | AB35: 342316.1 | AC35: 67
A36: Prashant Vaibhav | B36: NHP676 | D36: R6-Independent(Biswadip) | F36: Biswadip Sarkar | G36: 70 | H36: 91 | J36: R6-Independent(Biswadip) | K36: Akar Srivastava | L36: NHP169 | M36: 2046854 | N36: 1734622 | O36: 46 | Q36: R6-Independent(Biswadip) | R36: Akar Srivastava | S36: NHP169 | T36: 0 | X36: R6-Independent(Biswadip) | Y36: Akar Srivastava | Z36: NHP169 | AA36: 11998 | AB36: 10167.797 | AC36: 2
A37: Suraj Singh | B37: NHP446 | D37: R6-Independent(Biswadip) | F37: Biswadip Sarkar | G37: 65 | H37: 84.5 | J37: R6-Independent(Biswadip) | K37: Faiq Khan | L37: NHP155 | M37: 1380666 | N37: 1170055.9 | O37: 34 | Q37: R6-Independent(Biswadip) | R37: Faiq Khan | S37: NHP155 | T37: 116998 | U37: 99150.847 | V37: 2 | X37: R6-Independent(Biswadip) | Y37: Faiq Khan | Z37: NHP155 | AA37: 47992 | AB37: 40671.186 | AC37: 8
A38: Vinod Pathania | B38: NHP151 | D38: R6-Independent(Biswadip) | F38: Biswadip Sarkar | G38: 50 | H38: 65 | J38: R6-Independent(Biswadip) | K38: Manoj Sharma | L38: NHP470 | M38: 895175 | N38: 758622.88 | O38: 25 | Q38: R6-Independent(Biswadip) | R38: Manoj Sharma | S38: NHP470 | T38: 0 | X38: R6-Independent(Biswadip) | Y38: Manoj Sharma | Z38: NHP470 | AA38: 35994 | AB38: 30503.39 | AC38: 6
A39: Manasvi D | B39: NHP674 | D39: R7-Sufiyan | E39: Sufiyan Ansari | F39: Rajat Sharma | G39: 60 | H39: 78 | J39: R6-Independent(Biswadip) | K39: Mudit Raj | L39: NHP142 | M39: 2690736 | N39: 2280284.7 | O39: 64 | Q39: R6-Independent(Biswadip) | R39: Mudit Raj | S39: NHP142 | T39: 137997 | U39: 116946.61 | V39: 3 | X39: R6-Independent(Biswadip) | Y39: Mudit Raj | Z39: NHP142 | AA39: 49992 | AB39: 42366.102 | AC39: 8
A40: Paras Doifode | B40: NHP551 | D40: R7-Sufiyan | E40: Sufiyan Ansari | F40: Rajat Sharma | G40: 70 | H40: 91 | J40: R6-Independent(Biswadip) | K40: Prashant Vaibhav | L40: NHP676 | M40: 5457486 | N40: 4624988.1 | O40: 114 | Q40: R6-Independent(Biswadip) | R40: Prashant Vaibhav | S40: NHP676 | T40: 0 | X40: R6-Independent(Biswadip) | Y40: Prashant Vaibhav | Z40: NHP676 | AA40: 47992 | AB40: 40671.186 | AC40: 8
A41: Shivani Chauhan | B41: NHP825 | D41: R7-Sufiyan | E41: Sufiyan Ansari | F41: Rajat Sharma | G41: 35 | H41: 45.5 | J41: R6-Independent(Biswadip) | K41: Suraj Singh | L41: NHP446 | M41: 1057425 | N41: 896122.88 | O41: 25 | Q41: R6-Independent(Biswadip) | R41: Suraj Singh | S41: NHP446 | T41: 50999 | U41: 43219.492 | V41: 1 | X41: R6-Independent(Biswadip) | Y41: Suraj Singh | Z41: NHP446 | AA41: 17997 | AB41: 15251.695 | AC41: 3
A42: Sufiyan Ansari | B42: NHP160 | D42: R7-Sufiyan | E42: Sufiyan Ansari | F42: Rajat Sharma | G42: 60 | H42: 78 | J42: R6-Independent(Biswadip) | K42: Vinod Pathania | L42: NHP151 | M42: 674588 | N42: 571684.75 | O42: 12 | Q42: R6-Independent(Biswadip) | R42: Vinod Pathania | S42: NHP151 | T42: 176596 | U42: 149657.63 | V42: 4 | X42: R6-Independent(Biswadip) | Y42: Vinod Pathania | Z42: NHP151 | AA42: 0
A43: Akshay Grover | B43: NHP818 | D43: R8-Tauseef | E43: Tauseef Ansari | F43: Rajat Sharma | G43: 46 | H43: 59.8 | J43: R6-Independent(Biswadip) Total | M43: 14202930 | N43: 12036381 | O43: 320 | Q43: R6-Independent(Biswadip) Total | T43: 482590 | U43: 408974.58 | V43: 10 | X43: R6-Independent(Biswadip) Total | AA43: 211965 | AB43: 179631.36 | AC43: 35
A44: Prajwal Ghodke | B44: NHP608 | D44: R8-Tauseef | E44: Tauseef Ansari | F44: Rajat Sharma | G44: 70 | H44: 91 | J44: R7-Sufiyan | K44: Manasvi Dhoke | L44: NHP674 | M44: 3667233 | N44: 3107824.6 | O44: 67 | Q44: R7-Sufiyan | R44: Manasvi Dhoke | S44: NHP674 | T44: 0 | X44: R7-Sufiyan | Y44: Manasvi Dhoke | Z44: NHP674 | AA44: 11998 | AB44: 10167.797 | AC44: 2
A45: Tauseef Ansari | B45: NHP581 | D45: R8-Tauseef | E45: Tauseef Ansari | F45: Rajat Sharma | G45: 70 | H45: 91 | J45: R7-Sufiyan | K45: Paras Doifode | L45: NHP551 | M45: 997473 | N45: 845316.1 | O45: 27 | Q45: R7-Sufiyan | R45: Paras Doifode | S45: NHP551 | T45: 0 | X45: R7-Sufiyan | Y45: Paras Doifode | Z45: NHP551 | AA45: 11998 | AB45: 10167.797 | AC45: 2
A46: Wayne Camilo | B46: NHP377 | D46: R8-Tauseef | E46: Tauseef Ansari | F46: Rajat Sharma | G46: 70 | H46: 91 | J46: R7-Sufiyan | K46: Shivani Chauhan | L46: NHP825 | M46: 1667513 | N46: 1413146.6 | O46: 37 | Q46: R7-Sufiyan | R46: Shivani Chauhan | S46: NHP825 | T46: 393992 | U46: 333891.53 | V46: 8 | X46: R7-Sufiyan | Y46: Shivani Chauhan | Z46: NHP825 | AA46: 0
A47: Ajay Kumar | B47: NHP138 | D47: R9-Ajay | E47: Ajay Kumar | F47: Rajat Sharma | G47: 60 | H47: 78 | J47: R7-Sufiyan | K47: Sufiyan Ansari | L47: NHP160 | M47: 1990654 | N47: 1686994.9 | O47: 46 | Q47: R7-Sufiyan | R47: Sufiyan Ansari | S47: NHP160 | T47: 647788 | U47: 548972.88 | V47: 12 | X47: R7-Sufiyan | Y47: Sufiyan Ansari | Z47: NHP160 | AA47: 11998 | AB47: 10167.797 | AC47: 2
A48: Praveen Raj | B48: NHP158 | D48: R9-Ajay | E48: Ajay Kumar | F48: Rajat Sharma | G48: 70 | H48: 91 | J48: R7-Sufiyan Total | M48: 8322873 | N48: 7053282.2 | O48: 177 | Q48: R7-Sufiyan Total | T48: 1041780 | U48: 882864.41 | V48: 20 | X48: R7-Sufiyan Total | AA48: 35994 | AB48: 30503.39 | AC48: 6
A49: Shreekrishna Kulkarni | B49: NHP827 | D49: R9-Ajay | E49: Ajay Kumar | F49: Rajat Sharma | G49: 46 | H49: 59.8 | J49: R8-Tauseef | K49: Tauseef Ansari | L49: NHP581 | M49: 1100626 | N49: 932733.9 | O49: 24 | Q49: R8-Tauseef | R49: Tauseef Ansari | S49: NHP581 | T49: 329243 | U49: 279019.49 | V49: 7 | X49: R8-Tauseef | Y49: Tauseef Ansari | Z49: NHP581 | AA49: 5999 | AB49: 5083.8983 | AC49: 1
A50: Ajmal Shan | B50: NHP683 | D50: R10-Sukanthan | E50: Sukanthan PK | F50: Akshay Yamsanwar | G50: 55 | H50: 71.5 | J50: R8-Tauseef | K50: Wayne Camilo | L50: NHP377 | M50: 929977 | N50: 788116.1 | O50: 23 | Q50: R8-Tauseef | R50: Wayne Camilo | S50: NHP377 | T50: 649984 | U50: 550833.9 | V50: 16 | X50: R8-Tauseef | Y50: Wayne Camilo | Z50: NHP377 | AA50: 12998 | AB50: 11015.254 | AC50: 2
A51: Anoof M | B51: NHP668 | D51: R10-Sukanthan | E51: Sukanthan PK | F51: Akshay Yamsanwar | G51: 40 | H51: 52 | J51: R8-Tauseef | K51: Akshay Grover | L51: NHP818 | M51: 1590718 | N51: 1348066.1 | O51: 32 | Q51: R8-Tauseef | R51: Akshay Grover | S51: NHP818 | T51: 349994 | U51: 296605.08 | V51: 6 | X51: R8-Tauseef | Y51: Akshay Grover | Z51: NHP818 | AA51: 23996 | AB51: 20335.593 | AC51: 4
A52: Arundas Aravind | B52: NHP782 | D52: R10-Sukanthan | E52: Sukanthan PK | F52: Akshay Yamsanwar | G52: 50 | H52: 65 | J52: R8-Tauseef | K52: Prajwal Ghodke | L52: NHP608 | M52: 2056855 | N52: 1743097.5 | O52: 45 | Q52: R8-Tauseef | R52: Prajwal Ghodke | S52: NHP608 | T52: 958929 | U52: 812651.69 | V52: 21 | X52: R8-Tauseef | Y52: Prajwal Ghodke | Z52: NHP608 | AA52: 17997 | AB52: 15251.695 | AC52: 3
A53: Sachin V | B53: NHP159 | D53: R10-Sukanthan | E53: Sukanthan PK | F53: Akshay Yamsanwar | G53: 50 | H53: 65 | J53: R8-Tauseef Total | M53: 5678176 | N53: 4812013.6 | O53: 124 | Q53: R8-Tauseef Total | T53: 2288150 | U53: 1939110.2 | V53: 50 | X53: R8-Tauseef Total | AA53: 60990 | AB53: 51686.441 | AC53: 10
A54: Sudharsan Raja | B54: NHP744 | D54: R10-Sukanthan | E54: Sukanthan PK | F54: Akshay Yamsanwar | G54: 55 | H54: 71.5 | J54: R9-Ajay | K54: Praveen Raj | L54: NHP158 | M54: 2746982 | N54: 2327950.8 | O54: 68 | Q54: R9-Ajay | R54: Praveen Raj | S54: NHP158 | T54: 0 | X54: R9-Ajay | Y54: Praveen Raj | Z54: NHP158 | AA54: 23996 | AB54: 20335.593 | AC54: 4
A55: Sukanthan PK | B55: NHP157 | D55: R10-Sukanthan | E55: Sukanthan PK | F55: Akshay Yamsanwar | G55: 50 | H55: 65 | J55: R9-Ajay | K55: Shreekrishna Kulkarni | L55: NHP827 | M55: 1738769 | N55: 1473533.1 | O55: 31 | Q55: R9-Ajay | R55: Shreekrishna Kulkarni | S55: NHP827 | T55: 298994 | U55: 253384.75 | V55: 6 | X55: R9-Ajay | Y55: Shreekrishna Kulkarni | Z55: NHP827 | AA55: 0
A56: Ushaswini K | B56: NHP681 | D56: R10-Sukanthan | E56: Sukanthan PK | F56: Akshay Yamsanwar | G56: 60 | H56: 78 | J56: R9-Ajay | K56: Ajay Kumar | L56: NHP138 | M56: 1085223 | N56: 919680.51 | O56: 27 | Q56: R9-Ajay | R56: Ajay Kumar | S56: NHP138 | T56: 0 | X56: R9-Ajay | Y56: Ajay Kumar | Z56: NHP138 | AA56: 35994 | AB56: 30503.39 | AC56: 6
A57: Aattreya Ravindran | B57: NHP785 | D57: R11-Srinivasan | E57: Srinivasan G | F57: Akshay Yamsanwar | G57: 50 | H57: 65 | J57: R9-Ajay Total | M57: 5570974 | N57: 4721164.4 | O57: 126 | Q57: R9-Ajay Total | T57: 298994 | U57: 253384.75 | V57: 6 | X57: R9-Ajay Total | AA57: 59990 | AB57: 50838.983 | AC57: 10
A58: Hari Haran | B58: NHP552 | C58: Nirmal Raj | D58: R11-Srinivasan | E58: Srinivasan G | F58: Akshay Yamsanwar | G58: 60 | H58: 78 | J58: R10-Sukanthan | K58: Ajmal Shan | L58: NHP683 | M58: 671434 | N58: 569011.86 | O58: 16 | Q58: R10-Sukanthan | R58: Ajmal Shan | S58: NHP683 | T58: 181445 | U58: 153766.95 | V58: 5 | X58: R10-Sukanthan | Y58: Ajmal Shan | Z58: NHP683 | AA58: 13998 | AB58: 11862.712 | AC58: 2
A59: Jeyaganesh Balaji | B59: NHP545 | D59: R11-Srinivasan | E59: Srinivasan G | F59: Akshay Yamsanwar | G59: 50 | H59: 65 | J59: R10-Sukanthan | K59: Sachin V Nair | L59: NHP159 | M59: 476090 | N59: 403466.1 | O59: 10 | Q59: R10-Sukanthan | R59: Sachin V Nair | S59: NHP159 | T59: 257795 | U59: 218470.34 | V59: 5 | X59: R10-Sukanthan | Y59: Sachin V Nair | Z59: NHP159 | AA59: 0
A60: Nirmal Raj | B60: NHP380 | D60: R11-Srinivasan | E60: Srinivasan G | F60: Akshay Yamsanwar | G60: 60 | H60: 78 | J60: R10-Sukanthan | K60: Sudharsan Raja R | L60: NHP744 | M60: 942982 | N60: 799137.29 | O60: 18 | Q60: R10-Sukanthan | R60: Sudharsan Raja R | S60: NHP744 | T60: 378993 | U60: 321180.51 | V60: 7 | X60: R10-Sukanthan | Y60: Sudharsan Raja R | Z60: NHP744 | AA60: 0
A61: Santhosh G | B61: NHP719 | D61: R11-Srinivasan | E61: Srinivasan G | F61: Akshay Yamsanwar | G61: 55 | H61: 71.5 | J61: R10-Sukanthan | K61: Sukanthan PK | L61: NHP157 | M61: 780080 | N61: 661084.75 | O61: 20 | Q61: R10-Sukanthan | R61: Sukanthan PK | S61: NHP157 | T61: 290994 | U61: 246605.08 | V61: 6 | X61: R10-Sukanthan | Y61: Sukanthan PK | Z61: NHP157 | AA61: 20997 | AB61: 17794.068 | AC61: 3
A62: Srinivasan G | B62: NHP248 | D62: R11-Srinivasan | E62: Srinivasan G | F62: Akshay Yamsanwar | G62: 60 | H62: 78 | J62: R10-Sukanthan | K62: Ushaswini K | L62: NHP681 | M62: 2153357 | N62: 1824878.8 | O62: 43 | Q62: R10-Sukanthan | R62: Ushaswini K | S62: NHP681 | T62: 0 | X62: R10-Sukanthan | Y62: Ushaswini K | Z62: NHP681 | AA62: 6999 | AB62: 5931.3559 | AC62: 1
A63: Abhishek Bhat | B63: NHP444 | D63: R12-Independent(Akshay) | F63: Akshay Yamsanwar | G63: 55 | H63: 71.5 | J63: R10-Sukanthan | K63: Anoof | L63: NHP668 | M63: 446439 | N63: 378338.14 | O63: 11 | Q63: R10-Sukanthan | R63: Anoof | S63: NHP668 | T63: 244645 | U63: 207326.27 | V63: 5 | X63: R10-Sukanthan | Y63: Anoof | Z63: NHP668 | AA63: 13998 | AB63: 11862.712 | AC63: 2
A64: Mohammed Sufian Shareeq | B64: NHP518 | D64: R12-Independent(Akshay) | F64: Akshay Yamsanwar | G64: 60 | H64: 78 | J64: R10-Sukanthan | K64: Arundas Aravind | L64: NHP782 | M64: 885732 | N64: 750620.34 | O64: 18 | Q64: R10-Sukanthan | R64: Arundas Aravind | S64: NHP782 | T64: 203997 | U64: 172878.81 | V64: 3 | X64: R10-Sukanthan | Y64: Arundas Aravind | Z64: NHP782 | AA64: 6999 | AB64: 5931.3559 | AC64: 1
A65: Shrihari Kulkarni | B65: NHP279 | D65: R12-Independent(Akshay) | F65: Akshay Yamsanwar | G65: 50 | H65: 65 | J65: R10-Sukanthan Total | M65: 6356114 | N65: 5386537.3 | O65: 136 | Q65: R10-Sukanthan Total | T65: 1557869 | U65: 1320228 | V65: 31 | X65: R10-Sukanthan Total | AA65: 62991 | AB65: 53382.203 | AC65: 9
A66: Arshad Hussain | B66: NHP364 | D66: R13-Saif | E66: Saif Khan | F66: Independent(APTS) | G66: 60 | H66: 78 | J66: R11-Srinivasan | K66: Aattreya Ravindran | L66: NHP785 | M66: 1017626 | N66: 862394.92 | O66: 24 | Q66: R11-Srinivasan | R66: Aattreya Ravindran | S66: NHP785 | T66: 581987 | U66: 493209.32 | V66: 13 | X66: R11-Srinivasan | Y66: Aattreya Ravindran | Z66: NHP785 | AA66: 23996 | AB66: 20335.593 | AC66: 4
A67: Nenavath Laxman | B67: NHP536 | D67: R13-Saif | E67: Saif Khan | F67: Independent(APTS) | G67: 60 | H67: 78 | J67: R11-Srinivasan | K67: Hari Haran | L67: NHP552 | M67: 1727714 | N67: 1464164.4 | O67: 36 | Q67: R11-Srinivasan | R67: Hari Haran | S67: NHP552 | T67: 0 | X67: R11-Srinivasan | Y67: Hari Haran | Z67: NHP552 | AA67: 11998 | AB67: 10167.797 | AC67: 2
A68: Ranjith D | B68: NHP610 | D68: R13-Saif | E68: Saif Khan | F68: Independent(APTS) | G68: 55 | H68: 71.5 | J68: R11-Srinivasan | K68: Jeyaganesh Balaji | L68: NHP545 | M68: 1541067 | N68: 1305989 | O68: 33 | Q68: R11-Srinivasan | R68: Jeyaganesh Balaji | S68: NHP545 | T68: 243644 | U68: 206477.97 | V68: 6 | X68: R11-Srinivasan | Y68: Jeyaganesh Balaji | Z68: NHP545 | AA68: 11998 | AB68: 10167.797 | AC68: 2
A69: Saif Khan | B69: NHP147 | D69: R13-Saif | E69: Saif Khan | F69: Independent(APTS) | G69: 55 | H69: 71.5 | J69: R11-Srinivasan | K69: Nirmal Raj | L69: NHP380 | M69: 3512535 | N69: 2976724.6 | O69: 65 | Q69: R11-Srinivasan | R69: Nirmal Raj | S69: NHP380 | T69: 461991 | U69: 391517.8 | V69: 9 | X69: R11-Srinivasan | Y69: Nirmal Raj | Z69: NHP380 | AA69: 23996 | AB69: 20335.593 | AC69: 4
A70: Shaktinandan Akhilesh | B70: NHP736 | D70: R13-Saif | E70: Saif Khan | F70: Independent(APTS) | G70: 55 | H70: 71.5 | J70: R11-Srinivasan | K70: Santhosh G | L70: NHP719 | M70: 2123251 | N70: 1799365.3 | O70: 49 | Q70: R11-Srinivasan | R70: Santhosh G | S70: NHP719 | T70: 509989 | U70: 432194.07 | V70: 11 | X70: R11-Srinivasan | Y70: Santhosh G | Z70: NHP719 | AA70: 29995 | AB70: 25419.492 | AC70: 5
A71: Suresh Kumar | B71: NHP211 | D71: R13-Saif | E71: Saif Khan | F71: Independent(APTS) | G71: 60 | H71: 78 | J71: R11-Srinivasan | K71: Srinivasan G | L71: NHP248 | M71: 2000309 | N71: 1695177.1 | O71: 41 | Q71: R11-Srinivasan | R71: Srinivasan G | S71: NHP248 | T71: 641637 | U71: 543760.17 | V71: 13 | X71: R11-Srinivasan | Y71: Srinivasan G | Z71: NHP248 | AA71: 5999 | AB71: 5083.8983 | AC71: 1
A72: Amey jadhav | B72: NHP671 | D72: R14-Rameez | E72: Rameez Arman | F72: Independent(APTS) | G72: 50 | H72: 65 | J72: R11-Srinivasan Total | M72: 11922502 | N72: 10103815 | O72: 248 | Q72: R11-Srinivasan Total | T72: 2439248 | U72: 2067159.3 | V72: 52 | X72: R11-Srinivasan Total | AA72: 107982 | AB72: 91510.169 | AC72: 18
A73: Loka Phanindra | B73: NHP365 | C73: Sai Srikanth | D73: R14-Rameez | E73: Rameez Arman | F73: Independent(APTS) | G73: 60 | H73: 78 | J73: R12-Independent(Akshay) | K73: Abhishek Bhat | L73: NHP444 | M73: 1408170 | N73: 1193364.4 | O73: 30 | Q73: R12-Independent(Akshay) | R73: Abhishek Bhat | S73: NHP444 | T73: 382292 | U73: 323976.27 | V73: 8 | X73: R12-Independent(Akshay) | Y73: Abhishek Bhat | Z73: NHP444 | AA73: 0
A74: Nav Nandh Tej | B74: NHP621 | D74: R14-Rameez | E74: Rameez Arman | F74: Independent(APTS) | G74: 50 | H74: 65 | J74: R12-Independent(Akshay) | K74: Mohammed Sufian Shareeq | L74: NHP518 | M74: 1598612 | N74: 1354755.9 | O74: 38 | Q74: R12-Independent(Akshay) | R74: Mohammed Sufian Shareeq | S74: NHP518 | T74: 5999 | U74: 5083.8983 | V74: 1 | X74: R12-Independent(Akshay) | Y74: Mohammed Sufian Shareeq | Z74: NHP518 | AA74: 41993 | AB74: 35587.288 | AC74: 7
A75: Rameez Arman | B75: NHP218 | D75: R14-Rameez | E75: Rameez Arman | F75: Independent(APTS) | G75: 55 | H75: 71.5 | J75: R12-Independent(Akshay) | K75: Shrihari R Kulkarni | L75: NHP279 | M75: 1307024 | N75: 1107647.5 | O75: 26 | Q75: R12-Independent(Akshay) | R75: Shrihari R Kulkarni | S75: NHP279 | T75: 645437 | U75: 546980.51 | V75: 13 | X75: R12-Independent(Akshay) | Y75: Shrihari R Kulkarni | Z75: NHP279 | AA75: 0
A76: Sai Srikanth | B76: NHP309 | D76: R14-Rameez | E76: Rameez Arman | F76: Independent(APTS) | G76: 60 | H76: 78 | J76: R12-Independent(Akshay) Total | M76: 4313806 | N76: 3655767.8 | O76: 94 | Q76: R12-Independent(Akshay) Total | T76: 1033728 | U76: 876040.68 | V76: 22 | X76: R12-Independent(Akshay) Total | AA76: 41993 | AB76: 35587.288 | AC76: 7
J77: R13-Saif | K77: Arshad Hussain | L77: NHP364 | M77: 1147575 | N77: 972521.19 | O77: 25 | Q77: R13-Saif | R77: Arshad Hussain | S77: NHP364 | T77: 269292 | U77: 228213.56 | V77: 8 | X77: R13-Saif | Y77: Arshad Hussain | Z77: NHP364 | AA77: 23996 | AB77: 20335.593 | AC77: 4
J78: R13-Saif | K78: Nenavath Laxman | L78: NHP536 | M78: 678987 | N78: 575412.71 | O78: 13 | Q78: R13-Saif | R78: Nenavath Laxman | S78: NHP536 | T78: 678987 | U78: 575412.71 | V78: 13 | X78: R13-Saif | Y78: Nenavath Laxman | Z78: NHP536 | AA78: 5999 | AB78: 5083.8983 | AC78: 1
J79: R13-Saif | K79: Shaktinandan Akhilesh | L79: NHP736 | M79: 645737 | N79: 547234.75 | O79: 13 | Q79: R13-Saif | R79: Shaktinandan Akhilesh | S79: NHP736 | T79: 645737 | U79: 547234.75 | V79: 13 | X79: R13-Saif | Y79: Shaktinandan Akhilesh | Z79: NHP736 | AA79: 0
J80: R13-Saif | K80: Suresh Kumar Thakur | L80: NHP211 | M80: 1179175 | N80: 999300.85 | O80: 25 | Q80: R13-Saif | R80: Suresh Kumar Thakur | S80: NHP211 | T80: 116998 | U80: 99150.847 | V80: 2 | X80: R13-Saif | Y80: Suresh Kumar Thakur | Z80: NHP211 | AA80: 0
J81: R13-Saif | K81: Ranjith D | L81: NHP610 | M81: 1358469 | N81: 1151244.9 | O81: 31 | Q81: R13-Saif | R81: Ranjith D | S81: NHP610 | T81: 282644 | U81: 239528.81 | V81: 6 | X81: R13-Saif | Y81: Ranjith D | Z81: NHP610 | AA81: 5999 | AB81: 5083.8983 | AC81: 1
J82: R13-Saif | K82: Saif Khan | L82: NHP147 | M82: 1087630 | N82: 921720.34 | O82: 20 | Q82: R13-Saif | R82: Saif Khan | S82: NHP147 | T82: 1087630 | U82: 921720.34 | V82: 20 | X82: R13-Saif | Y82: Saif Khan | Z82: NHP147 | AA82: 0
J83: R13-Saif Total | M83: 6097573 | N83: 5167434.7 | O83: 127 | Q83: R13-Saif Total | T83: 3081288 | U83: 2611261 | V83: 62 | X83: R13-Saif Total | AA83: 35994 | AB83: 30503.39 | AC83: 6
J84: R14-Rameez | K84: Rameez Arman | L84: NHP218 | M84: 1272624 | N84: 1078494.9 | O84: 26 | Q84: R14-Rameez | R84: Rameez Arman | S84: NHP218 | T84: 26649 | U84: 22583.898 | V84: 1 | X84: R14-Rameez | Y84: Rameez Arman | Z84: NHP218 | AA84: 5999 | AB84: 5083.8983 | AC84: 1
J85: R14-Rameez | K85: Amey Jadhav | L85: NHP671 | M85: 1722069 | N85: 1459380.5 | O85: 31 | Q85: R14-Rameez | R85: Amey Jadhav | S85: NHP671 | T85: 0 | X85: R14-Rameez | Y85: Amey Jadhav | Z85: NHP671 | AA85: 0
J86: R14-Rameez | K86: Loka Phanindra | L86: NHP365 | M86: 3088833 | N86: 2617655.1 | O86: 67 | Q86: R14-Rameez | R86: Loka Phanindra | S86: NHP365 | T86: 0 | X86: R14-Rameez | Y86: Loka Phanindra | Z86: NHP365 | AA86: 11998 | AB86: 10167.797 | AC86: 2
J87: R14-Rameez | K87: Sai Srikanth | L87: NHP309 | M87: 2087712 | N87: 1769247.5 | O87: 38 | Q87: R14-Rameez | R87: Sai Srikanth | S87: NHP309 | T87: 0 | X87: R14-Rameez | Y87: Sai Srikanth | Z87: NHP309 | AA87: 0
J88: R14-Rameez | K88: Nav Nandh Tej | L88: NHP621 | M88: 1191873 | N88: 1010061.9 | O88: 27 | Q88: R14-Rameez | R88: Nav Nandh Tej | S88: NHP621 | T88: 0 | X88: R14-Rameez | Y88: Nav Nandh Tej | Z88: NHP621 | AA88: 23996 | AB88: 20335.593 | AC88: 4
J89: R14-Rameez Total | M89: 9363111 | N89: 7934839.8 | O89: 189 | Q89: R14-Rameez Total | T89: 26649 | U89: 22583.898 | V89: 1 | X89: R14-Rameez Total | AA89: 41993 | AB89: 35587.288 | AC89: 7
J90: Grand Total | M90: =+M8+M13+M22+M26+M35+M43+M48+M53+M57+M65+M72+M76+M83+M89 -> 120861154 | N90: =+N8+N13+N22+N26+N35+N43+N48+N53+N57+N65+N72+N76+N83+N89 -> 1.0242471e+08 | O90: =+O8+O13+O22+O26+O35+O43+O48+O53+O57+O65+O72+O76+O83+O89 -> 2796 | Q90: Grand Total | T90: =+T8+T13+T22+T26+T35+T43+T48+T53+T57+T65+T72+T76+T83+T89 -> 14913180 | U90: =+U8+U13+U22+U26+U35+U43+U48+U53+U57+U65+U72+U76+U83+U89 -> 12638288 | V90: =+V8+V13+V22+V26+V35+V43+V48+V53+V57+V65+V72+V76+V83+V89 -> 320 | X90: Grand Total | AA90: =+AA8+AA13+AA22+AA26+AA35+AA43+AA48+AA53+AA57+AA65+AA72+AA76+AA83+AA89 -> 1414769 | AB90: =+AB8+AB13+AB22+AB26+AB35+AB43+AB48+AB53+AB57+AB65+AB72+AB76+AB83+AB89 -> 1198956.8 | AC90: =+AC8+AC13+AC22+AC26+AC35+AC43+AC48+AC53+AC57+AC65+AC72+AC76+AC83+AC89 -> 231
A92: 46143 | J92: Gross Sales | Q92: Disqualified Sales | X92: Foundation Sales
A93: Field Sales Targets May 2026-27 | J93: Region | K93: Agent Name | L93: Employee ID | M93: Sum of paid_amount | N93: Sum of paid_amount_*_100/118 | O93: Count of payment_id | Q93: Region | R93: Agent Name | S93: Employee ID | T93: Sum of paid_amount | U93: Sum of paid_amount_*_100/118 | V93: Count of payment_id | X93: Region | Y93: Agent Name | Z93: Employee ID | AA93: Sum of paid_amount | AB93: Sum of paid_amount_*_100/118 | AC93: Count of payment_id
A94: Troopers | B94: Employee IDs | C94: Submanagers | D94: Zone | E94: RM | F94: ZM | G94: May Base | H94: May WC | J94: R1-Ajeet | K94: Ajeet Pandey | L94: NHP374 | M94: 2887078 | N94: 2446676.3 | O94: 72 | Q94: R1-Ajeet | R94: Ajeet Pandey | S94: NHP374 | T94: 487788 | U94: 413379.66 | V94: 12 | X94: R1-Ajeet | Y94: Ajeet Pandey | Z94: NHP374 | AA94: 20997 | AB94: 17794.068 | AC94: 3
A95: Ajeet Pandey | B95: NHP374 | D95: R1-Ajeet | E95: Ajeet Pandey | F95: Divyansh Pandey | G95: 80 | H95: 104 | J95: R1-Ajeet | K95: Ankit Madan | L95: NHP291 | M95: 2333544 | N95: 1977579.7 | O95: 56 | Q95: R1-Ajeet | R95: Ankit Madan | S95: NHP291 | T95: 0 | X95: R1-Ajeet | Y95: Ankit Madan | Z95: NHP291 | AA95: 0
A96: Ankit Madan | B96: NHP291 | D96: R1-Ajeet | E96: Ajeet Pandey | F96: Divyansh Pandey | G96: 80 | H96: 104 | J96: R1-Ajeet | K96: Sachin Sharma | L96: NHP698 | M96: 3456868 | N96: 2929549.2 | O96: 82 | Q96: R1-Ajeet | R96: Sachin Sharma | S96: NHP698 | T96: 42999 | U96: 36439.831 | V96: 1 | X96: R1-Ajeet | Y96: Sachin Sharma | Z96: NHP698 | AA96: 13998 | AB96: 11862.712 | AC96: 2
A97: Sachin Sharma | B97: NHP698 | D97: R1-Ajeet | E97: Ajeet Pandey | F97: Divyansh Pandey | G97: 70 | H97: 91 | J97: R1-Ajeet | K97: Shariq Bhat | L97: NHP679 | M97: 1894498 | N97: 1605506.8 | O97: 52 | Q97: R1-Ajeet | R97: Shariq Bhat | S97: NHP679 | T97: 125297 | U97: 106183.9 | V97: 3 | X97: R1-Ajeet | Y97: Shariq Bhat | Z97: NHP679 | AA97: 13998 | AB97: 11862.712 | AC97: 2
A98: Shariq Bhat | B98: NHP679 | D98: R1-Ajeet | E98: Ajeet Pandey | F98: Divyansh Pandey | G98: 70 | H98: 91 | J98: R1-Ajeet | K98: Zahid Majeeb | L98: NHP479 | M98: 2013644 | N98: 1706478 | O98: 56 | Q98: R1-Ajeet | R98: Zahid Majeeb | S98: NHP479 | T98: 33299 | U98: 28219.492 | V98: 1 | X98: R1-Ajeet | Y98: Zahid Majeeb | Z98: NHP479 | AA98: 27996 | AB98: 23725.424 | AC98: 4
A99: Zahid Majeeb | B99: NHP479 | D99: R1-Ajeet | E99: Ajeet Pandey | F99: Divyansh Pandey | G99: 80 | H99: 104 | J99: R1-Ajeet Total | M99: 12585632 | N99: 10665790 | O99: 318 | Q99: R1-Ajeet Total | T99: 689383 | U99: 584222.88 | V99: 17 | X99: R1-Ajeet Total | AA99: 76989 | AB99: 65244.915 | AC99: 11
A100: Akif Hannan | B100: NHP212 | D100: R2-Akif | E100: Akif Hannan | F100: Divyansh Pandey | G100: 60 | H100: 78 | J100: R2-Akif | K100: Akif Hannan | L100: NHP212 | M100: 3606312 | N100: 3056196.6 | O100: 88 | Q100: R2-Akif | R100: Akif Hannan | S100: NHP212 | T100: 25649 | U100: 21736.441 | V100: 1 | X100: R2-Akif | Y100: Akif Hannan | Z100: NHP212 | AA100: 43993 | AB100: 37282.203 | AC100: 7
A101: Ayush Choubey | B101: NHP727 | D101: R2-Akif | E101: Akif Hannan | F101: Divyansh Pandey | G101: 70 | H101: 91 | J101: R2-Akif | K101: Ayush Choubey | L101: NHP727 | M101: 2050994 | N101: 1738130.5 | O101: 56 | Q101: R2-Akif | R101: Ayush Choubey | S101: NHP727 | T101: 106197 | U101: 89997.458 | V101: 3 | X101: R2-Akif | Y101: Ayush Choubey | Z101: NHP727 | AA101: 11998 | AB101: 10167.797 | AC101: 2
...

Sheet Incentive Report- Output
J1: =SUMIF(D:D,"R10",O:O) -> 1.1373777e+08
A2: 46113
A3: PARTICULARS | E3: BDE | T3: TM/SR BDE | X3: ZONE - RM | AB3: Other Incenitves/Penalty | AC3: Final Incentives Apr 2026 | AH3: PENALTY FOR UNDERUTILIZING THE SALES COUPONS ( LESS THAN 80% ) | AI3: PARTICULARS | AL3: Penalty Per Employee
A4: Name | B4: Employee ID | C4: Designation | D4: Zone | E4: BDE Target Units | F4: Winner Units | G4: Gross Sales Count | H4: Disqaulified Sales Count | I4: Foundation Sales Count | J4: Achieved Units RM & TM | K4: Achieved units % BDE | L4: Target Revenue - NET | M4: Achieved Revenue (Including GST)- GROSS | N4: Achieved Revenue (W/o GST) - NET Disqualified Sales | O4: Achieved Revenue (W/o GST)- NET BDE | P4: Achieved Revenue % | Q4: Highest of units and Revenue % | R4: Incremental slab % | S4: BDE Incentive | T4: TM/SR BDE Target (Revenue) | U4: TM/SR BDE Achieved (Revenue) | V4: TM/SR BDE Achieved % | W4: TM/SR BDE Incentive | X4: Zone target (units) | Y4: Zone Achieved (units) | Z4: Zone Achieved % | AA4: RM Incentive - Quaterly Payout | AB4: Spot Incenitve / Half Yearly Performance Incentive/Penalty/Best RM Reward | AC4: Prior Period Adjustments | AD4: Accumulation Above 2lacs Payable at Year end | AE4: Net Payable this month | AF4: Incentive of the Month | AI4: Name | AJ4: =B4 -> Employee ID | AK4: Zone | AL4: Gross Incentive | AM4: Net Incentive ( after penalty ) | AN4: Penalty
A5: Ajeet Pandey | B5: NHP374 | C5: RM | D5: R1 | E5: =ROUND(SUMIF('Target Achieved- Input'!$B$2:$B$90,'Incentive Report- Output'!B5,'Target Achieved- Input'!$G$2:$G$90),0) -> 60 | F5: =ROUND(SUMIF('Target Achieved- Input'!$B$2:$B$90,'Incentive Report- Output'!B5,'Target Achieved- Input'!$H$2:$H$90),0) -> 78 | G5: =SUMIF('Target Achieved- Input'!$L$2:$L$90,'Incentive Report- Output'!B5,'Target Achieved- Input'!$O$2:$O$90) -> 37 | H5: =SUMIF('Target Achieved- Input'!$S$2:$S$90,'Incentive Report- Output'!B5,'Target Achieved- Input'!$V$2:$V$90) -> 5 | I5: =SUMIF('Target Achieved- Input'!$L$2:$L$90,'Incentive Report- Output'!B5,'Target Achieved- Input'!$AC$2:$AC$90) -> 2 | J5: =G5-H5 -> 32 | K5: =IFERROR(J5/E5,0) -> 0.53333333 | L5: =E5*33000 -> 1980000 | M5: =SUMIF('Target Achieved- Input'!$L$2:$L$90,'Incentive Report- Output'!B5,'Target Achieved- Input'!$M$2:$M$90) -> 1387763 | N5: =SUMIF('Target Achieved- Input'!$S$2:$S$90,'Incentive Report- Output'!B5,'Target Achieved- Input'!$U$2:$U$90) -> 169487.29 | O5: =SUMIF('Target Achieved- Input'!$L$2:$L$90,'Incentive Report- Output'!B5,'Target Achieved- Input'!$N$2:$N$90)-N5 -> 1006583.1 | P5: =IFERROR(O5/L5,0) -> 0.50837528 | Q5: =P5 -> 0.50837528 | R5: 0 | S5: =(LOOKUP(Q5,Policy!$L$12:$M$16)+R5)*O5 -> 5032.9153 | X5: =E10 -> 280 | Y5: =J10 -> 200 | Z5: =Y5/X5 -> 0.71428571 | AA5: 0 | AB5: 0 | AC5: 0 | AD5: =IF(AF5>200000,AF5-200000,0) -> 0 | AE5: =AF5-AD5 -> 5032.9153 | AF5: =S5+W5+AB5+AC5 -> 5032.9153 | AI5: Ajeet Pandey | AJ5: NHP374 | AK5: R1 | AL5: 5880.3517 | AM5: =AF5 -> 5032.9153 | AN5: =AL5-AM5 -> 847.43644
A6: Ankit Madan | B6: NHP291 | C6: BDE | D6: R1 | E6: =ROUND(SUMIF('Target Achieved- Input'!$B$2:$B$90,'Incentive Report- Output'!B6,'Target Achieved- Input'!$G$2:$G$90),0) -> 60 | F6: =ROUND(SUMIF('Target Achieved- Input'!$B$2:$B$90,'Incentive Report- Output'!B6,'Target Achieved- Input'!$H$2:$H$90),0) -> 78 | G6: =SUMIF('Target Achieved- Input'!$L$2:$L$90,'Incentive Report- Output'!B6,'Target Achieved- Input'!$O$2:$O$90) -> 52 | H6: =SUMIF('Target Achieved- Input'!$S$2:$S$90,'Incentive Report- Output'!B6,'Target Achieved- Input'!$V$2:$V$90) -> 2 | I6: =SUMIF('Target Achieved- Input'!$L$2:$L$90,'Incentive Report- Output'!B6,'Target Achieved- Input'!$AC$2:$AC$90) -> 5 | J6: =G6-H6 -> 50 | K6: =IFERROR(J6/E6,0) -> 0.83333333 | L6: =E6*33000 -> 1980000 | M6: =SUMIF('Target Achieved- Input'!$L$2:$L$90,'Incentive Report- Output'!B6,'Target Achieved- Input'!$M$2:$M$90) -> 1999998 | N6: =SUMIF('Target Achieved- Input'!$S$2:$S$90,'Incentive Report- Output'!B6,'Target Achieved- Input'!$U$2:$U$90) -> 56481.356 | O6: =SUMIF('Target Achieved- Input'!$L$2:$L$90,'Incentive Report- Output'!B6,'Target Achieved- Input'!$N$2:$N$90)-N6 -> 1638432.2 | P6: =IFERROR(O6/L6,0) -> 0.82749101 | Q6: =P6 -> 0.82749101 | R6: 0 | S6: =(LOOKUP(Q6,Policy!$L$12:$M$16)+R6)*O6 -> 16384.322 | AA6: 0 | AB6: 0 | AC6: 0 | AD6: =IF(AF6>200000,AF6-200000,0) -> 0 | AE6: =AF6-AD6 -> 16384.322 | AF6: =S6+W6+AB6+AC6 -> 16384.322 | AI6: Ankit Madan | AJ6: NHP291 | AK6: R1 | AL6: 16949.136 | AM6: =AF6 -> 16384.322 | AN6: =AL6-AM6 -> 564.81356
A7: Sachin Sharma | B7: NHP698 | C7: BDE | D7: R1 | E7: =ROUND(SUMIF('Target Achieved- Input'!$B$2:$B$90,'Incentive Report- Output'!B7,'Target Achieved- Input'!$G$2:$G$90),0) -> 50 | F7: =ROUND(SUMIF('Target Achieved- Input'!$B$2:$B$90,'Incentive Report- Output'!B7,'Target Achieved- Input'!$H$2:$H$90),0) -> 65 | G7: =SUMIF('Target Achieved- Input'!$L$2:$L$90,'Incentive Report- Output'!B7,'Target Achieved- Input'!$O$2:$O$90) -> 28 | H7: =SUMIF('Target Achieved- Input'!$S$2:$S$90,'Incentive Report- Output'!B7,'Target Achieved- Input'!$V$2:$V$90) -> 4 | I7: =SUMIF('Target Achieved- Input'!$L$2:$L$90,'Incentive Report- Output'!B7,'Target Achieved- Input'!$AC$2:$AC$90) -> 7 | J7: =G7-H7 -> 24 | K7: =IFERROR(J7/E7,0) -> 0.48 | L7: =E7*33000 -> 1650000 | M7: =SUMIF('Target Achieved- Input'!$L$2:$L$90,'Incentive Report- Output'!B7,'Target Achieved- Input'!$M$2:$M$90) -> 982522 | N7: =SUMIF('Target Achieved- Input'!$S$2:$S$90,'Incentive Report- Output'!B7,'Target Achieved- Input'!$U$2:$U$90) -> 120335.59 | O7: =SUMIF('Target Achieved- Input'!$L$2:$L$90,'Incentive Report- Output'!B7,'Target Achieved- Input'!$N$2:$N$90)-N7 -> 712310.17 | P7: =IFERROR(O7/L7,0) -> 0.43170313 | Q7: =P7 -> 0.43170313 | R7: 0 | S7: =(LOOKUP(Q7,Policy!$L$12:$M$16)+R7)*O7 -> 0 | AA7: 0 | AB7: 0 | AC7: 0 | AD7: =IF(AF7>200000,AF7-200000,0) -> 0 | AE7: =AF7-AD7 -> 0 | AF7: =S7+W7+AB7+AC7 -> 0 | AI7: Sachin Sharma | AJ7: NHP698 | AK7: R1 | AL7: 4163.2288 | AM7: =AF7 -> 0 | AN7: =AL7-AM7 -> 4163.2288
A8: Shariq Bhat | B8: NHP679 | C8: BDE | D8: R1 | E8: =ROUND(SUMIF('Target Achieved- Input'!$B$2:$B$90,'Incentive Report- Output'!B8,'Target Achieved- Input'!$G$2:$G$90),0) -> 50 | F8: =ROUND(SUMIF('Target Achieved- Input'!$B$2:$B$90,'Incentive Report- Output'!B8,'Target Achieved- Input'!$H$2:$H$90),0) -> 65 | G8: =SUMIF('Target Achieved- Input'!$L$2:$L$90,'Incentive Report- Output'!B8,'Target Achieved- Input'!$O$2:$O$90) -> 45 | H8: =SUMIF('Target Achieved- Input'!$S$2:$S$90,'Incentive Report- Output'!B8,'Target Achieved- Input'!$V$2:$V$90) -> 1 | I8: =SUMIF('Target Achieved- Input'!$L$2:$L$90,'Incentive Report- Output'!B8,'Target Achieved- Input'!$AC$2:$AC$90) -> 1 | J8: =G8-H8 -> 44 | K8: =IFERROR(J8/E8,0) -> 0.88 | L8: =E8*33000 -> 1650000 | M8: =SUMIF('Target Achieved- Input'!$L$2:$L$90,'Incentive Report- Output'!B8,'Target Achieved- Input'!$M$2:$M$90) -> 1616955 | N8: =SUMIF('Target Achieved- Input'!$S$2:$S$90,'Incentive Report- Output'!B8,'Target Achieved- Input'!$U$2:$U$90) -> 33897.458 | O8: =SUMIF('Target Achieved- Input'!$L$2:$L$90,'Incentive Report- Output'!B8,'Target Achieved- Input'!$N$2:$N$90)-N8 -> 1336403.4 | P8: =IFERROR(O8/L8,0) -> 0.80994145 | Q8: =P8 -> 0.80994145 | R8: 0 | S8: =(LOOKUP(Q8,Policy!$L$12:$M$16)+R8)*O8 -> 13364.034 | AA8: 0 | AB8: 0 | AC8: 0 | AD8: =IF(AF8>200000,AF8-200000,0) -> 0 | AE8: =AF8-AD8 -> 13364.034 | AF8: =S8+W8+AB8+AC8 -> 13364.034 | AI8: Shariq Bhat | AJ8: NHP679 | AK8: R1 | AL8: 13703.008 | AM8: =AF8 -> 13364.034 | AN8: =AL8-AM8 -> 338.97458
A9: Zahid Majeeb | B9: NHP479 | C9: BDE | D9: R1 | E9: =ROUND(SUMIF('Target Achieved- Input'!$B$2:$B$90,'Incentive Report- Output'!B9,'Target Achieved- Input'!$G$2:$G$90),0) -> 60 | F9: =ROUND(SUMIF('Target Achieved- Input'!$B$2:$B$90,'Incentive Report- Output'!B9,'Target Achieved- Input'!$H$2:$H$90),0) -> 78 | G9: =SUMIF('Target Achieved- Input'!$L$2:$L$90,'Incentive Report- Output'!B9,'Target Achieved- Input'!$O$2:$O$90) -> 51 | H9: =SUMIF('Target Achieved- Input'!$S$2:$S$90,'Incentive Report- Output'!B9,'Target Achieved- Input'!$V$2:$V$90) -> 1 | I9: =SUMIF('Target Achieved- Input'!$L$2:$L$90,'Incentive Report- Output'!B9,'Target Achieved- Input'!$AC$2:$AC$90) -> 0 | J9: =G9-H9 -> 50 | K9: =IFERROR(J9/E9,0) -> 0.83333333 | L9: =E9*33000 -> 1980000 | M9: =SUMIF('Target Achieved- Input'!$L$2:$L$90,'Incentive Report- Output'!B9,'Target Achieved- Input'!$M$2:$M$90) -> 1773949 | N9: =SUMIF('Target Achieved- Input'!$S$2:$S$90,'Incentive Report- Output'!B9,'Target Achieved- Input'!$U$2:$U$90) -> 33897.458 | O9: =SUMIF('Target Achieved- Input'!$L$2:$L$90,'Incentive Report- Output'!B9,'Target Achieved- Input'!$N$2:$N$90)-N9 -> 1469449.2 | P9: =IFERROR(O9/L9,0) -> 0.74214604 | Q9: =P9 -> 0.74214604 | R9: 0 | S9: =(LOOKUP(Q9,Policy!$L$12:$M$16)+R9)*O9 -> 7347.2458 | AA9: 0 | AB9: 0 | AC9: 0 | AD9: =IF(AF9>200000,AF9-200000,0) -> 0 | AE9: =AF9-AD9 -> 7347.2458 | AF9: =S9+W9+AB9+AC9 -> 7347.2458 | AI9: Zahid Majeeb | AJ9: NHP479 | AK9: R1 | AL9: 7516.7331 | AM9: =AF9 -> 7347.2458 | AN9: =AL9-AM9 -> 169.48729
A10: TOTAL | D10: R1 | E10: =SUM(E5:E9) -> 280 | F10: =SUM(F5:F9) -> 364 | G10: =SUM(G5:G9) -> 213 | H10: =SUM(H5:H9) -> 13 | I10: =SUM(I5:I9) -> 15 | J10: =SUM(J5:J9) -> 200 | L10: =SUM(L5:L9) -> 9240000 | M10: =SUM(M5:M9) -> 7761187 | N10: =SUM(N5:N9) -> 414099.15 | O10: =SUM(O5:O9) -> 6163178 | S10: =SUM(S5:S9) -> 42128.517 | T10: =SUM(T5:T9) -> 0 | U10: =SUM(U5:U9) -> 0 | V10: =SUM(V5:V9) -> 0 | W10: =SUM(W5:W9) -> 0 | X10: =SUM(X5:X9) -> 280 | Y10: =SUM(Y5:Y9) -> 200 | Z10: =SUM(Z5:Z9) -> 0.71428571 | ... AF10: =SUM(AF5:AF9) -> 42128.517 | AI10: TOTAL | AK10: R1 | AL10: 48212.458 | AM10: =SUM(AM5:AM9) -> 42128.517 | AN10: =SUM(AN5:AN9) -> 6083.9407
A11: Akif Hannan | B11: NHP212 | C11: RM | D11: R2 | E11: =ROUND(SUMIF('Target Achieved- Input'!$B$2:$B$90,'Incentive Report- Output'!B11,'Target Achieved- Input'!$G$2:$G$90),0) -> 50 | F11: =ROUND(SUMIF('Target Achieved- Input'!$B$2:$B$90,'Incentive Report- Output'!B11,'Target Achieved- Input'!$H$2:$H$90),0) -> 65 | G11: =SUMIF('Target Achieved- Input'!$L$2:$L$90,'Incentive Report- Output'!B11,'Target Achieved- Input'!$O$2:$O$90) -> 29 | H11: =SUMIF('Target Achieved- Input'!$S$2:$S$90,'Incentive Report- Output'!B11,'Target Achieved- Input'!$V$2:$V$90) -> 0 | I11: =SUMIF('Target Achieved- Input'!$L$2:$L$90,'Incentive Report- Output'!B11,'Target Achieved- Input'!$AC$2:$AC$90) -> 0 | J11: =G11-H11 -> 29 | K11: =IFERROR(J11/E11,0) -> 0.58 | L11: =E11*33000 -> 1650000 | M11: =SUMIF('Target Achieved- Input'!$L$2:$L$90,'Incentive Report- Output'!B11,'Target Achieved- Input'!$M$2:$M$90) -> 1156621 | N11: =SUMIF('Target Achieved- Input'!$S$2:$S$90,'Incentive Report- Output'!B11,'Target Achieved- Input'!$U$2:$U$90) -> 0 | O11: =SUMIF('Target Achieved- Input'!$L$2:$L$90,'Incentive Report- Output'!B11,'Target Achieved- Input'!$N$2:$N$90)-N11 -> 980187.29 | P11: =IFERROR(O11/L11,0) -> 0.5940529 | Q11: =MAX(P11,K11) -> 0.5940529 | R11: 0 | S11: =(LOOKUP(Q11,Policy!$L$12:$M$16)+R11)*O11 -> 4900.9364 | X11: =E15 -> 210 | Y11: =J15 -> 117 | Z11: =Y11/X11 -> 0.55714286 | AA11: 0 | AB11: 0 | AC11: 0 | AD11: =IF(AF11>200000,AF11-200000,0) -> 0 | AE11: =AF11-AD11 -> 4900.9364 | AF11: =S11+W11+AB11+AC11 -> 4900.9364 | AI11: Akif Hannan | AJ11: NHP212 | AK11: R2 | AL11: 4900.9364 | AM11: =AF11 -> 4900.9364 | AN11: =AL11-AM11 -> 0
A12: Ayush Choubey | B12: NHP727 | C12: BDE | D12: R2 | E12: =ROUND(SUMIF('Target Achieved- Input'!$B$2:$B$90,'Incentive Report- Output'!B12,'Target Achieved- Input'!$G$2:$G$90),0) -> 50 | F12: =ROUND(SUMIF('Target Achieved- Input'!$B$2:$B$90,'Incentive Report- Output'!B12,'Target Achieved- Input'!$H$2:$H$90),0) -> 65 | G12: =SUMIF('Target Achieved- Input'!$L$2:$L$90,'Incentive Report- Output'!B12,'Target Achieved- Input'!$O$2:$O$90) -> 34 | H12: =SUMIF('Target Achieved- Input'!$S$2:$S$90,'Incentive Report- Output'!B12,'Target Achieved- Input'!$V$2:$V$90) -> 2 | I12: =SUMIF('Target Achieved- Input'!$L$2:$L$90,'Incentive Report- Output'!B12,'Target Achieved- Input'!$AC$2:$AC$90) -> 5 | J12: =G12-H12 -> 32 | K12: =IFERROR(J12/E12,0) -> 0.64 | L12: =E12*33000 -> 1650000 | M12: =SUMIF('Target Achieved- Input'!$L$2:$L$90,'Incentive Report- Output'!B12,'Target Achieved- Input'!$M$2:$M$90) -> 1225766 | N12: =SUMIF('Target Achieved- Input'!$S$2:$S$90,'Incentive Report- Output'!B12,'Target Achieved- Input'!$U$2:$U$90) -> 45167.797 | O12: =SUMIF('Target Achieved- Input'!$L$2:$L$90,'Incentive Report- Output'!B12,'Target Achieved- Input'!$N$2:$N$90)-N12 -> 993616.95 | P12: =IFERROR(O12/L12,0) -> 0.60219209 | Q12: =P12 -> 0.60219209 | R12: 0 | S12: =(LOOKUP(Q12,Policy!$L$12:$M$16)+R12)*O12 -> 4968.0847 | AA12: 0 | AB12: 0 | AC12: 0 | AD12: =IF(AF12>200000,AF12-200000,0) -> 0 | AE12: =AF12-AD12 -> 4968.0847 | AF12: =S12+W12+AB12+AC12 -> 4968.0847 | AI12: Ayush Choubey | AJ12: NHP727 | AK12: R2 | AL12: 5193.9237 | AM12: =AF12 -> 4968.0847 | AN12: =AL12-AM12 -> 225.83898
A13: Rohit Bharti | B13: NHP395 | C13: BDE | D13: R2 | E13: =ROUND(SUMIF('Target Achieved- Input'!$B$2:$B$90,'Incentive Report- Output'!B13,'Target Achieved- Input'!$G$2:$G$90),0) -> 60 | F13: =ROUND(SUMIF('Target Achieved- Input'!$B$2:$B$90,'Incentive Report- Output'!B13,'Target Achieved- Input'!$H$2:$H$90),0) -> 78 | G13: =SUMIF('Target Achieved- Input'!$L$2:$L$90,'Incentive Report- Output'!B13,'Target Achieved- Input'!$O$2:$O$90) -> 31 | H13: =SUMIF('Target Achieved- Input'!$S$2:$S$90,'Incentive Report- Output'!B13,'Target Achieved- Input'!$V$2:$V$90) -> 7 | I13: =SUMIF('Target Achieved- Input'!$L$2:$L$90,'Incentive Report- Output'!B13,'Target Achieved- Input'!$AC$2:$AC$90) -> 6 | J13: =G13-H13 -> 24 | K13: =IFERROR(J13/E13,0) -> 0.4 | L13: =E13*33000 -> 1980000 | M13: =SUMIF('Target Achieved- Input'!$L$2:$L$90,'Incentive Report- Output'!B13,'Target Achieved- Input'!$M$2:$M$90) -> 1102419 | N13: =SUMIF('Target Achieved- Input'!$S$2:$S$90,'Incentive Report- Output'!B13,'Target Achieved- Input'!$U$2:$U$90) -> 221434.75 | O13: =SUMIF('Target Achieved- Input'!$L$2:$L$90,'Incentive Report- Output'!B13,'Target Achieved- Input'!$N$2:$N$90)-N13 -> 712818.64 | P13: =IFERROR(O13/L13,0) -> 0.36000942 | Q13: =P13 -> 0.36000942 | R13: 0 | S13: =(LOOKUP(Q13,Policy!$L$12:$M$16)+R13)*O13 -> 0 | AA13: 0 | AB13: 0 | AC13: 0 | AD13: =IF(AF13>200000,AF13-200000,0) -> 0 | AE13: =AF13-AD13 -> 0 | AF13: =S13+W13+AB13+AC13 -> 0 | AI13: Rohit Bharti | AJ13: NHP395 | AK13: R2 | AL13: 0 | AM13: =AF13 -> 0 | AN13: =AL13-AM13 -> 0
A14: Sumit Kumar Singh | B14: NHP709 | C14: BDE | D14: R2 | E14: =ROUND(SUMIF('Target Achieved- Input'!$B$2:$B$90,'Incentive Report- Output'!B14,'Target Achieved- Input'!$G$2:$G$90),0) -> 50 | F14: =ROUND(SUMIF('Target Achieved- Input'!$B$2:$B$90,'Incentive Report- Output'!B14,'Target Achieved- Input'!$H$2:$H$90),0) -> 65 | G14: =SUMIF('Target Achieved- Input'!$L$2:$L$90,'Incentive Report- Output'!B14,'Target Achieved- Input'!$O$2:$O$90) -> 32 | H14: =SUMIF('Target Achieved- Input'!$S$2:$S$90,'Incentive Report- Output'!B14,'Target Achieved- Input'!$V$2:$V$90) -> 0 | I14: =SUMIF('Target Achieved- Input'!$L$2:$L$90,'Incentive Report- Output'!B14,'Target Achieved- Input'!$AC$2:$AC$90) -> 2 | J14: =G14-H14 -> 32 | K14: =IFERROR(J14/E14,0) -> 0.64 | L14: =E14*33000 -> 1650000 | M14: =SUMIF('Target Achieved- Input'!$L$2:$L$90,'Incentive Report- Output'!B14,'Target Achieved- Input'!$M$2:$M$90) -> 1390868 | N14: =SUMIF('Target Achieved- Input'!$S$2:$S$90,'Incentive Report- Output'!B14,'Target Achieved- Input'!$U$2:$U$90) -> 0 | O14: =SUMIF('Target Achieved- Input'!$L$2:$L$90,'Incentive Report- Output'!B14,'Target Achieved- Input'!$N$2:$N$90)-N14 -> 1178701.7 | P14: =IFERROR(O14/L14,0) -> 0.71436466 | Q14: =MAX(P14,K14) -> 0.71436466 | R14: 0 | S14: =(LOOKUP(Q14,Policy!$L$12:$M$16)+R14)*O14 -> 5893.5085 | AA14: 0 | AB14: 0 | AC14: 0 | AD14: =IF(AF14>200000,AF14-200000,0) -> 0 | AE14: =AF14-AD14 -> 5893.5085 | AF14: =S14+W14+AB14+AC14 -> 5893.5085 | AI14: Sumit Kumar Singh | AJ14: NHP709 | AK14: R2 | AL14: 5893.5085 | AM14: =AF14 -> 5893.5085 | AN14: =AL14-AM14 -> 0
A15: TOTAL | D15: R2 | E15: =SUM(E11:E14) -> 210 | F15: =SUM(F11:F14) -> 273 | G15: =SUM(G11:G14) -> 126 | H15: =SUM(H11:H14) -> 9 | I15: =SUM(I11:I14) -> 13 | J15: =SUM(J11:J14) -> 117 | L15: =SUM(L11:L14) -> 6930000 | M15: =SUM(M11:M14) -> 4875674 | N15: =SUM(N11:N14) -> 266602.54 | O15: =SUM(O11:O14) -> 3865324.6 | S15: =SUM(S11:S14) -> 15762.53 | T15: =SUM(T11:T14) -> 0 | U15: =SUM(U11:U14) -> 0 | V15: =SUM(V11:V14) -> 0 | W15: =SUM(W11:W14) -> 0 | X15: =SUM(X11:X14) -> 210 | Y15: =SUM(Y11:Y14) -> 117 | Z15: =SUM(Z11:Z14) -> 0.55714286 | ... AF15: =SUM(AF11:AF14) -> 15762.53 | AI15: TOTAL | AK15: R2 | AL15: 15988.369 | AM15: =SUM(AM11:AM14) -> 15762.53 | AN15: =SUM(AN11:AN14) -> 225.83898
A16: Anjaney | B16: NHP144 | C16: RM | D16: R3 | E16: =ROUND(SUMIF('Target Achieved- Input'!$B$2:$B$90,'Incentive Report- Output'!B16,'Target Achieved- Input'!$G$2:$G$90),0) -> 50 | F16: =ROUND(SUMIF('Target Achieved- Input'!$B$2:$B$90,'Incentive Report- Output'!B16,'Target Achieved- Input'!$H$2:$H$90),0) -> 65 | G16: =SUMIF('Target Achieved- Input'!$L$2:$L$90,'Incentive Report- Output'!B16,'Target Achieved- Input'!$O$2:$O$90) -> 11 | H16: =SUMIF('Target Achieved- Input'!$S$2:$S$90,'Incentive Report- Output'!B16,'Target Achieved- Input'!$V$2:$V$90) -> 11 | I16: =SUMIF('Target Achieved- Input'!$L$2:$L$90,'Incentive Report- Output'!B16,'Target Achieved- Input'!$AC$2:$AC$90) -> 0 | J16: =G16-H16 -> 0 | K16: =IFERROR(J16/E16,0) -> 0 | L16: =E16*33000 -> 1650000 | M16: =SUMIF('Target Achieved- Input'!$L$2:$L$90,'Incentive Report- Output'!B16,'Target Achieved- Input'!$M$2:$M$90) -> 567639 | N16: =SUMIF('Target Achieved- Input'!$S$2:$S$90,'Incentive Report- Output'!B16,'Target Achieved- Input'!$U$2:$U$90) -> 481050 | O16: =SUMIF('Target Achieved- Input'!$L$2:$L$90,'Incentive Report- Output'!B16,'Target Achieved- Input'!$N$2:$N$90)-N16 -> 0 | P16: =IFERROR(O16/L16,0) -> 0 | Q16: =MAX(P16,K16) -> 0 | R16: 0 | S16: =(LOOKUP(Q16,Policy!$L$12:$M$16)+R16)*O16 -> 0 | X16: =E24 -> 510 | Y16: =J24 -> 289 | Z16: =Y16/X16 -> 0.56666667 | AA16: 0 | AB16: 0 | AC16: 0 | AD16: =IF(AF16>200000,AF16-200000,0) -> 0 | AE16: =AF16-AD16 -> 0 | AF16: =S16+W16+AB16+AC16 -> 0 | AI16: Anjaney | AJ16: NHP144 | AK16: R3 | AL16: 0 | AM16: =AF16 -> 0 | AN16: =AL16-AM16 -> 0
A17: Abhishek Sinha | B17: NHP815 | C17: BDE | D17: R3 | E17: =ROUND(SUMIF('Target Achieved- Input'!$B$2:$B$90,'Incentive Report- Output'!B17,'Target Achieved- Input'!$G$2:$G$90),0) -> 50 | F17: =ROUND(SUMIF('Target Achieved- Input'!$B$2:$B$90,'Incentive Report- Output'!B17,'Target Achieved- Input'!$H$2:$H$90),0) -> 65 | G17: =SUMIF('Target Achieved- Input'!$L$2:$L$90,'Incentive Report- Output'!B17,'Target Achieved- Input'!$O$2:$O$90) -> 40 | H17: =SUMIF('Target Achieved- Input'!$S$2:$S$90,'Incentive Report- Output'!B17,'Target Achieved- Input'!$V$2:$V$90) -> 0 | I17: =SUMIF('Target Achieved- Input'!$L$2:$L$90,'Incentive Report- Output'!B17,'Target Achieved- Input'!$AC$2:$AC$90) -> 0 | J17: =G17-H17 -> 40 | K17: =IFERROR(J17/E17,0) -> 0.8 | L17: =E17*33000 -> 1650000 | M17: =SUMIF('Target Achieved- Input'!$L$2:$L$90,'Incentive Report- Output'!B17,'Target Achieved- Input'!$M$2:$M$90) -> 1646160 | N17: =SUMIF('Target Achieved- Input'!$S$2:$S$90,'Incentive Report- Output'!B17,'Target Achieved- Input'!$U$2:$U$90) -> 0 | O17: =SUMIF('Target Achieved- Input'!$L$2:$L$90,'Incentive Report- Output'!B17,'Target Achieved- Input'!$N$2:$N$90)-N17 -> 1395050.8 | P17: =IFERROR(O17/L17,0) -> 0.84548536 | Q17: =MAX(P17,K17) -> 0.84548536 | R17: 0 | S17: =(LOOKUP(Q17,Policy!$L$12:$M$16)+R17)*O17 -> 13950.508 | AA17: 0 | AB17: 0 | AC17: 0 | AD17: =IF(AF17>200000,AF17-200000,0) -> 0 | AE17: =AF17-AD17 -> 13950.508 | AF17: =S17+W17+AB17+AC17 -> 13950.508 | AI17: Abhishek Sinha | AJ17: NHP815 | AK17: R3 | AL17: 13950.508 | AM17: =AF17 -> 13950.508 | AN17: =AL17-AM17 -> 0
A18: Adnan Akhtar | B18: NHP170 | C18: BDE | D18: R3 | E18: =ROUND(SUMIF('Target Achieved- Input'!$B$2:$B$90,'Incentive Report- Output'!B18,'Target Achieved- Input'!$G$2:$G$90),0) -> 70 | F18: =ROUND(SUMIF('Target Achieved- Input'!$B$2:$B$90,'Incentive Report- Output'!B18,'Target Achieved- Input'!$H$2:$H$90),0) -> 91 | G18: =SUMIF('Target Achieved- Input'!$L$2:$L$90,'Incentive Report- Output'!B18,'Target Achieved- Input'!$O$2:$O$90) -> 49 | H18: =SUMIF('Target Achieved- Input'!$S$2:$S$90,'Incentive Report- Output'!B18,'Target Achieved- Input'!$V$2:$V$90) -> 5 | I18: =SUMIF('Target Achieved- Input'!$L$2:$L$90,'Incentive Report- Output'!B18,'Target Achieved- Input'!$AC$2:$AC$90) -> 2 | J18: =G18-H18 -> 44 | K18: =IFERROR(J18/E18,0) -> 0.62857143 | L18: =E18*33000 -> 2310000 | M18: =SUMIF('Target Achieved- Input'!$L$2:$L$90,'Incentive Report- Output'!B18,'Target Achieved- Input'!$M$2:$M$90) -> 2078651 | N18: =SUMIF('Target Achieved- Input'!$S$2:$S$90,'Incentive Report- Output'!B18,'Target Achieved- Input'!$U$2:$U$90) -> 218639.83 | O18: =SUMIF('Target Achieved- Input'!$L$2:$L$90,'Incentive Report- Output'!B18,'Target Achieved- Input'!$N$2:$N$90)-N18 -> 1542928.8 | P18: =IFERROR(O18/L18,0) -> 0.66793455 | Q18: =MAX(P18,K18) -> 0.66793455 | R18: 0 | S18: =(LOOKUP(Q18,Policy!$L$12:$M$16)+R18)*O18 -> 7714.6441 | AA18: 0 | AB18: 0 | AC18: 0 | AD18: =IF(AF18>200000,AF18-200000,0) -> 0 | AE18: =AF18-AD18 -> 7714.6441 | AF18: =S18+W18+AB18+AC18 -> 7714.6441 | AI18: Adnan Akhtar | AJ18: NHP170 | AK18: R3 | AL18: 8807.8432 | AM18: =AF18 -> 7714.6441 | AN18: =AL18-AM18 -> 1093.1992
A19: Anurag Bhargava | B19: NHP290 | C19: SBM | D19: R3 | E19: =ROUND(SUMIF('Target Achieved- Input'!$B$2:$B$90,'Incentive Report- Output'!B19,'Target Achieved- Input'!$G$2:$G$90),0) -> 70 | F19: =ROUND(SUMIF('Target Achieved- Input'!$B$2:$B$90,'Incentive Report- Output'!B19,'Target Achieved- Input'!$H$2:$H$90),0) -> 91 | G19: =SUMIF('Target Achieved- Input'!$L$2:$L$90,'Incentive Report- Output'!B19,'Target Achieved- Input'!$O$2:$O$90) -> 57 | H19: =SUMIF('Target Achieved- Input'!$S$2:$S$90,'Incentive Report- Output'!B19,'Target Achieved- Input'!$V$2:$V$90) -> 0 | I19: =SUMIF('Target Achieved- Input'!$L$2:$L$90,'Incentive Report- Output'!B19,'Target Achieved- Input'!$AC$2:$AC$90) -> 4 | J19: =G19-H19 -> 57 | K19: =IFERROR(J19/E19,0) -> 0.81428571 | L19: =E19*33000 -> 2310000 | M19: =SUMIF('Target Achieved- Input'!$L$2:$L$90,'Incentive Report- Output'!B19,'Target Achieved- Input'!$M$2:$M$90) -> 2314593 | N19: =SUMIF('Target Achieved- Input'!$S$2:$S$90,'Incentive Report- Output'!B19,'Target Achieved- Input'!$U$2:$U$90) -> 0 | O19: =SUMIF('Target Achieved- Input'!$L$2:$L$90,'Incentive Report- Output'!B19,'Target Achieved- Input'!$N$2:$N$90)-N19 -> 1961519.5 | P19: =IFERROR(O19/L19,0) -> 0.84914264 | Q19: =MAX(P19,K19) -> 0.84914264 | R19: 0 | S19: =(LOOKUP(Q19,Policy!$L$12:$M$16)+R19)*O19 -> 19615.195 | T19: =L20 -> 2310000 | U19: =O20 -> 1087513.6 | V19: =IFERROR(U19/T19,0) -> 0.47078509 | W19: =LOOKUP(V19,Policy!$L$18:$M$21)*U19 -> 0 | AA19: 0 | AB19: 0 | AC19: 0 | AD19: =IF(AF19>200000,AF19-200000,0) -> 0 | AE19: =AF19-AD19 -> 19615.195 | AF19: =S19+W19+AB19+AC19 -> 19615.195 | AI19: Anurag Bhargava | AJ19: NHP290 | AK19: R3 | AL19: 19615.195 | AM19: =AF19 -> 19615.195 | AN19: =AL19-AM19 -> 0
A20: Arshad Khan | B20: NHP561 | C20: BDE | D20: R3 | E20: =ROUND(SUMIF('Target Achieved- Input'!$B$2:$B$90,'Incentive Report- Output'!B20,'Target Achieved- Input'!$G$2:$G$90),0) -> 70 | F20: =ROUND(SUMIF('Target Achieved- Input'!$B$2:$B$90,'Incentive Report- Output'!B20,'Target Achieved- Input'!$H$2:$H$90),0) -> 91 | G20: =SUMIF('Target Achieved- Input'!$L$2:$L$90,'Incentive Report- Output'!B20,'Target Achieved- Input'!$O$2:$O$90) -> 34 | H20: =SUMIF('Target Achieved- Input'!$S$2:$S$90,'Incentive Report- Output'!B20,'Target Achieved- Input'!$V$2:$V$90) -> 0 | I20: =SUMIF('Target Achieved- Input'!$L$2:$L$90,'Incentive Report- Output'!B20,'Target Achieved- Input'!$AC$2:$AC$90) -> 2 | J20: =G20-H20 -> 34 | K20: =IFERROR(J20/E20,0) -> 0.48571429 | L20: =E20*33000 -> 2310000 | M20: =SUMIF('Target Achieved- Input'!$L$2:$L$90,'Incentive Report- Output'!B20,'Target Achieved- Input'!$M$2:$M$90) -> 1283266 | N20: =SUMIF('Target Achieved- Input'!$S$2:$S$90,'Incentive Report- Output'!B20,'Target Achieved- Input'!$U$2:$U$90) -> 0 | O20: =SUMIF('Target Achieved- Input'!$L$2:$L$90,'Incentive Report- Output'!B20,'Target Achieved- Input'!$N$2:$N$90)-N20 -> 1087513.6 | P20: =IFERROR(O20/L20,0) -> 0.47078509 | Q20: =P20 -> 0.47078509 | R20: 0 | S20: =(LOOKUP(Q20,Policy!$L$12:$M$16)+R20)*O20 -> 0 | AA20: 0 | AB20: 0 | AC20: 0 | AD20: =IF(AF20>200000,AF20-200000,0) -> 0 | AE20: =AF20-AD20 -> 0 | AF20: =S20+W20+AB20+AC20 -> 0 | AI20: Arshad Khan | AJ20: NHP561 | AK20: R3 | AL20: 0 | AM20: =AF20 -> 0 | AN20: =AL20-AM20 -> 0
A21: Nikhil | B21: NHP153 | C21: BDE | D21: R3 | E21: =ROUND(SUMIF('Target Achieved- Input'!$B$2:$B$90,'Incentive Report- Output'!B21,'Target Achieved- Input'!$G$2:$G$90),0) -> 70 | F21: =ROUND(SUMIF('Target Achieved- Input'!$B$2:$B$90,'Incentive Report- Output'!B21,'Target Achieved- Input'!$H$2:$H$90),0) -> 91 | G21: =SUMIF('Target Achieved- Input'!$L$2:$L$90,'Incentive Report- Output'!B21,'Target Achieved- Input'!$O$2:$O$90) -> 61 | H21: =SUMIF('Target Achieved- Input'!$S$2:$S$90,'Incentive Report- Output'!B21,'Target Achieved- Input'!$V$2:$V$90) -> 6 | I21: =SUMIF('Target Achieved- Input'!$L$2:$L$90,'Incentive Report- Output'!B21,'Target Achieved- Input'!$AC$2:$AC$90) -> 2 | J21: =G21-H21 -> 55 | K21: =IFERROR(J21/E21,0) -> 0.78571429 | L21: =E21*33000 -> 2310000 | M21: =SUMIF('Target Achieved- Input'!$L$2:$L$90,'Incentive Report- Output'!B21,'Target Achieved- Input'!$M$2:$M$90) -> 2593239 | N21: =SUMIF('Target Achieved- Input'!$S$2:$S$90,'Incentive Report- Output'!B21,'Target Achieved- Input'!$U$2:$U$90) -> 271181.36 | O21: =SUMIF('Target Achieved- Input'!$L$2:$L$90,'Incentive Report- Output'!B21,'Target Achieved- Input'!$N$2:$N$90)-N21 -> 1926478.8 | P21: =IFERROR(O21/L21,0) -> 0.83397351 | Q21: =MAX(P21,K21) -> 0.83397351 | R21: 0 | S21: =(LOOKUP(Q21,Policy!$L$12:$M$16)+R21)*O21 -> 19264.788 | AA21: 0 | AB21: 0 | AC21: 0 | AD21: =IF(AF21>200000,AF21-200000,0) -> 0 | AE21: =AF21-AD21 -> 19264.788 | AF21: =S21+W21+AB21+AC21 -> 19264.788 | AI21: Nikhil | AJ21: NHP153 | AK21: R3 | AL21: 21976.602 | AM21: =AF21 -> 19264.788 | AN21: =AL21-AM21 -> 2711.8136
A22: Shubham Vyas | B22: NHP466 | C22: BDE | D22: R3 | E22: =ROUND(SUMIF('Target Achieved- Input'!$B$2:$B$90,'Incentive Report- Output'!B22,'Target Achieved- Input'!$G$2:$G$90),0) -> 60 | F22: =ROUND(SUMIF('Target Achieved- Input'!$B$2:$B$90,'Incentive Report- Output'!B22,'Target Achieved- Input'!$H$2:$H$90),0) -> 78 | G22: =SUMIF('Target Achieved- Input'!$L$2:$L$90,'Incentive Report- Output'!B22,'Target Achieved- Input'!$O$2:$O$90) -> 20 | H22: =SUMIF('Target Achieved- Input'!$S$2:$S$90,'Incentive Report- Output'!B22,'Target Achieved- Input'!$V$2:$V$90) -> 3 | I22: =SUMIF('Target Achieved- Input'!$L$2:$L$90,'Incentive Report- Output'!B22,'Target Achieved- Input'!$AC$2:$AC$90) -> 1 | J22: =G22-H22 -> 17 | K22: =IFERROR(J22/E22,0) -> 0.28333333 | L22: =E22*33000 -> 1980000 | M22: =SUMIF('Target Achieved- Input'!$L$2:$L$90,'Incentive Report- Output'!B22,'Target Achieved- Input'!$M$2:$M$90) -> 832680 | N22: =SUMIF('Target Achieved- Input'!$S$2:$S$90,'Incentive Report- Output'!B22,'Target Achieved- Input'!$U$2:$U$90) -> 86268.644 | O22: =SUMIF('Target Achieved- Input'!$L$2:$L$90,'Incentive Report- Output'!B22,'Target Achieved- Input'!$N$2:$N$90)-N22 -> 619392.37 | P22: =IFERROR(O22/L22,0) -> 0.31282443 | Q22: =MAX(P22,K22) -> 0.31282443 | R22: 0 | S22: =(LOOKUP(Q22,Policy!$L$12:$M$16)+R22)*O22 -> 0 | AA22: 0 | AB22: 0 | AC22: 0 | AD22: =IF(AF22>200000,AF22-200000,0) -> 0 | AE22: =AF22-AD22 -> 0 | AF22: =S22+W22+AB22+AC22 -> 0 | AI22: Shubham Vyas | AJ22: NHP466 | AK22: R3 | AL22: 0 | AM22: =AF22 -> 0 | AN22: =AL22-AM22 -> 0
A23: Sangram Singh | B23: NHP620 | C23: BDE | D23: R3 | E23: =ROUND(SUMIF('Target Achieved- Input'!$B$2:$B$90,'Incentive Report- Output'!B23,'Target Achieved- Input'!$G$2:$G$90),0) -> 70 | F23: =ROUND(SUMIF('Target Achieved- Input'!$B$2:$B$90,'Incentive Report- Output'!B23,'Target Achieved- Input'!$H$2:$H$90),0) -> 91 | G23: =SUMIF('Target Achieved- Input'!$L$2:$L$90,'Incentive Report- Output'!B23,'Target Achieved- Input'!$O$2:$O$90) -> 42 | H23: =SUMIF('Target Achieved- Input'!$S$2:$S$90,'Incentive Report- Output'!B23,'Target Achieved- Input'!$V$2:$V$90) -> 0 | I23: =SUMIF('Target Achieved- Input'!$L$2:$L$90,'Incentive Report- Output'!B23,'Target Achieved- Input'!$AC$2:$AC$90) -> 3 | J23: =G23-H23 -> 42 | K23: =IFERROR(J23/E23,0) -> 0.6 | L23: =E23*33000 -> 2310000 | M23: =SUMIF('Target Achieved- Input'!$L$2:$L$90,'Incentive Report- Output'!B23,'Target Achieved- Input'!$M$2:$M$90) -> 1826908 | N23: =SUMIF('Target Achieved- Input'!$S$2:$S$90,'Incentive Report- Output'!B23,'Target Achieved- Input'!$U$2:$U$90) -> 0 | O23: =SUMIF('Target Achieved- Input'!$L$2:$L$90,'Incentive Report- Output'!B23,'Target Achieved- Input'!$N$2:$N$90)-N23 -> 1548227.1 | P23: =IFERROR(O23/L23,0) -> 0.67022819 | Q23: =MAX(P23,K23) -> 0.67022819 | R23: 0 | S23: =(LOOKUP(Q23,Policy!$L$12:$M$16)+R23)*O23 -> 7741.1356 | AA23: 0 | AB23: 0 | AC23: 0 | AD23: =IF(AF23>200000,AF23-200000,0) -> 0 | AE23: =AF23-AD23 -> 7741.1356 | AF23: =S23+W23+AB23+AC23 -> 7741.1356 | AI23: Sangram Singh | AJ23: NHP620 | AK23: R3 | AL23: 7741.1356 | AM23: =AF23 -> 7741.1356 | AN23: =AL23-AM23 -> 0
A24: TOTAL | D24: R3 | E24: =SUM(E16:E23) -> 510 | F24: =SUM(F16:F23) -> 663 | G24: =SUM(G16:G23) -> 314 | H24: =SUM(H16:H23) -> 25 | I24: =SUM(I16:I23) -> 14 | J24: =SUM(J16:J23) -> 289 | L24: =SUM(L16:L23) -> 16830000 | M24: =SUM(M16:M23) -> 13143136 | N24: =SUM(N16:N23) -> 1057139.8 | O24: =SUM(O16:O23) -> 10081111 | S24: =SUM(S16:S23) -> 68286.271 | T24: =SUM(T16:T23) -> 2310000 | U24: =SUM(U16:U23) -> 1087513.6 | V24: =SUM(V16:V23) -> 0.47078509 | W24: =SUM(W16:W23) -> 0 | X24: =SUM(X16:X23) -> 510 | Y24: =SUM(Y16:Y23) -> 289 | Z24: =SUM(Z16:Z23) -> 0.56666667 | ... AF24: =SUM(AF16:AF23) -> 68286.271 | AI24: TOTAL | AK24: R3 | AL24: 72091.284 | AM24: =SUM(AM16:AM23) -> 68286.271 | AN24: =SUM(AN16:AN23) -> 3805.0127
A25: Sohaib Ahmed | B25: NHP173 | C25: RM | D25: R4 | E25: =ROUND(SUMIF('Target Achieved- Input'!$B$2:$B$90,'Incentive Report- Output'!B25,'Target Achieved- Input'!$G$2:$G$90),0) -> 60 | F25: =ROUND(SUMIF('Target Achieved- Input'!$B$2:$B$90,'Incentive Report- Output'!B25,'Target Achieved- Input'!$H$2:$H$90),0) -> 78 | G25: =SUMIF('Target Achieved- Input'!$L$2:$L$90,'Incentive Report- Output'!B25,'Target Achieved- Input'!$O$2:$O$90) -> 44 | H25: =SUMIF('Target Achieved- Input'!$S$2:$S$90,'Incentive Report- Output'!B25,'Target Achieved- Input'!$V$2:$V$90) -> 3 | I25: =SUMIF('Target Achieved- Input'!$L$2:$L$90,'Incentive Report- Output'!B25,'Target Achieved- Input'!$AC$2:$AC$90) -> 5 | J25: =G25-H25 -> 41 | K25: =IFERROR(J25/E25,0) -> 0.68333333 | L25: =E25*33000 -> 1980000 | M25: =SUMIF('Target Achieved- Input'!$L$2:$L$90,'Incentive Report- Output'!B25,'Target Achieved- Input'!$M$2:$M$90) -> 1818156 | N25: =SUMIF('Target Achieved- Input'!$S$2:$S$90,'Incentive Report- Output'!B25,'Target Achieved- Input'!$U$2:$U$90) -> 101692.37 | O25: =SUMIF('Target Achieved- Input'!$L$2:$L$90,'Incentive Report- Output'!B25,'Target Achieved- Input'!$N$2:$N$90)-N25 -> 1439117.8 | P25: =IFERROR(O25/L25,0) -> 0.72682717 | Q25: =MAX(P25,K25) -> 0.72682717 | R25: 0 | S25: =(LOOKUP(Q25,Policy!$L$12:$M$16)+R25)*O25 -> 7195.589 | X25: =E28 -> 160 | Y25: =J28 -> 83 | Z25: =Y25/X25 -> 0.51875 | AA25: 0 | AB25: 0 | AC25: 0 | AD25: =IF(AF25>200000,AF25-200000,0) -> 0 | AE25: =AF25-AD25+AC25 -> 7195.589 | AF25: =S25+W25+AB25+AC25 -> 7195.589 | AI25: Sohaib Ahmed | AJ25: NHP173 | AK25: R4 | AL25: 7704.0508 | AM25: =AF25 -> 7195.589 | AN25: =AL25-AM25 -> 508.46186
A26: Adarsh Kumar | B26: NHP670 | C26: BDE | D26: R4 | E26: =ROUND(SUMIF('Target Achieved- Input'!$B$2:$B$90,'Incentive Report- Output'!B26,'Target Achieved- Input'!$G$2:$G$90),0) -> 50 | F26: =ROUND(SUMIF('Target Achieved- Input'!$B$2:$B$90,'Incentive Report- Output'!B26,'Target Achieved- Input'!$H$2:$H$90),0) -> 65 | G26: =SUMIF('Target Achieved- Input'!$L$2:$L$90,'Incentive Report- Output'!B26,'Target Achieved- Input'!$O$2:$O$90) -> 29 | H26: =SUMIF('Target Achieved- Input'!$S$2:$S$90,'Incentive Report- Output'!B26,'Target Achieved- Input'!$V$2:$V$90) -> 4 | I26: =SUMIF('Target Achieved- Input'!$L$2:$L$90,'Incentive Report- Output'!B26,'Target Achieved- Input'!$AC$2:$AC$90) -> 5 | J26: =G26-H26 -> 25 | K26: =IFERROR(J26/E26,0) -> 0.5 | L26: =E26*33000 -> 1650000 | M26: =SUMIF('Target Achieved- Input'!$L$2:$L$90,'Incentive Report- Output'!B26,'Target Achieved- Input'!$M$2:$M$90) -> 1096521 | N26: =SUMIF('Target Achieved- Input'!$S$2:$S$90,'Incentive Report- Output'!B26,'Target Achieved- Input'!$U$2:$U$90) -> 115632.2 | O26: =SUMIF('Target Achieved- Input'!$L$2:$L$90,'Incentive Report- Output'!B26,'Target Achieved- Input'!$N$2:$N$90)-N26 -> 813622.88 | P26: =IFERROR(O26/L26,0) -> 0.49310478 | Q26: =P26 -> 0.49310478 | R26: 0 | S26: =(LOOKUP(Q26,Policy!$L$12:$M$16)+R26)*O26 -> 0 | AA26: 0 | AB26: 0 | AC26: 0 | AD26: =IF(AF26>200000,AF26-200000,0) -> 0 | AE26: =AF26-AD26+AC26 -> 0 | AF26: =S26+W26+AB26+AC26 -> 0 | AI26: Adarsh Kumar | AJ26: NHP670 | AK26: R4 | AL26: 4646.2754 | AM26: =AF26 -> 0 | AN26: =AL26-AM26 -> 4646.2754
A27: Ankit Jha | B27: NHP672 | C27: BDE | D27: R4 | E27: =ROUND(SUMIF('Target Achieved- Input'!$B$2:$B$90,'Incentive Report- Output'!B27,'Target Achieved- Input'!$G$2:$G$90),0) -> 50 | F27: =ROUND(SUMIF('Target Achieved- Input'!$B$2:$B$90,'Incentive Report- Output'!B27,'Target Achieved- Input'!$H$2:$H$90),0) -> 65 | G27: =SUMIF('Target Achieved- Input'!$L$2:$L$90,'Incentive Report- Output'!B27,'Target Achieved- Input'!$O$2:$O$90) -> 23 | H27: =SUMIF('Target Achieved- Input'!$S$2:$S$90,'Incentive Report- Output'!B27,'Target Achieved- Input'!$V$2:$V$90) -> 6 | I27: =SUMIF('Target Achieved- Input'!$L$2:$L$90,'Incentive Report- Output'!B27,'Target Achieved- Input'!$AC$2:$AC$90) -> 4 | J27: =G27-H27 -> 17 | K27: =IFERROR(J27/E27,0) -> 0.34 | L27: =E27*33000 -> 1650000 | M27: =SUMIF('Target Achieved- Input'!$L$2:$L$90,'Incentive Report- Output'!B27,'Target Achieved- Input'!$M$2:$M$90) -> 815227 | N27: =SUMIF('Target Achieved- Input'!$S$2:$S$90,'Incentive Report- Output'!B27,'Target Achieved- Input'!$U$2:$U$90) -> 194740.68 | O27: =SUMIF('Target Achieved- Input'!$L$2:$L$90,'Incentive Report- Output'!B27,'Target Achieved- Input'!$N$2:$N$90)-N27 -> 496129.66 | P27: =IFERROR(O27/L27,0) -> 0.30068464 | Q27: =P27 -> 0.30068464 | R27: 0 | S27: =(LOOKUP(Q27,Policy!$L$12:$M$16)+R27)*O27 -> 0 | AA27: 0 | AB27: 0 | AC27: 0 | AD27: =IF(AF27>200000,AF27-200000,0) -> 0 | AE27: =AF27-AD27+AC27 -> 0 | AF27: =S27+W27+AB27+AC27 -> 0 | AI27: Ankit Jha | AJ27: NHP672 | AK27: R4 | AL27: 0 | AM27: =AF27 -> 0 | AN27: =AL27-AM27 -> 0
A28: TOTAL | D28: R4 | E28: =SUM(E25:E27) -> 160 | F28: =SUM(F25:F27) -> 208 | G28: =SUM(G25:G27) -> 96 | H28: =SUM(H25:H27) -> 13 | I28: =SUM(I25:I27) -> 14 | J28: =SUM(J25:J27) -> 83 | L28: =SUM(L25:L27) -> 5280000 | M28: =SUM(M25:M27) -> 3729904 | N28: =SUM(N25:N27) -> 412065.25 | O28: =SUM(O25:O27) -> 2748870.3 | S28: =SUM(S25:S27) -> 7195.589 | T28: =SUM(T25:T27) -> 0 | U28: =SUM(U25:U27) -> 0 | V28: =SUM(V25:V27) -> 0 | W28: =SUM(W25:W27) -> 0 | X28: =SUM(X25:X27) -> 160 | Y28: =SUM(Y25:Y27) -> 83 | Z28: =SUM(Z25:Z27) -> 0.51875 | ... AF28: =SUM(AF25:AF27) -> 7195.589 | AI28: TOTAL | AK28: R4 | AL28: 12350.326 | AM28: =SUM(AM25:AM27) -> 7195.589 | AN28: =SUM(AN25:AN27) -> 5154.7373
A29: Susmita Paul | B29: NHP166 | C29: RM | D29: R5 | E29: =ROUND(SUMIF('Target Achieved- Input'!$B$2:$B$90,'Incentive Report- Output'!B29,'Target Achieved- Input'!$G$2:$G$90),0) -> 70 | F29: =ROUND(SUMIF('Target Achieved- Input'!$B$2:$B$90,'Incentive Report- Output'!B29,'Target Achieved- Input'!$H$2:$H$90),0) -> 91 | G29: =SUMIF('Target Achieved- Input'!$L$2:$L$90,'Incentive Report- Output'!B29,'Target Achieved- Input'!$O$2:$O$90) -> 134 | H29: =SUMIF('Target Achieved- Input'!$S$2:$S$90,'Incentive Report- Output'!B29,'Target Achieved- Input'!$V$2:$V$90) -> 0 | I29: =SUMIF('Target Achieved- Input'!$L$2:$L$90,'Incentive Report- Output'!B29,'Target Achieved- Input'!$AC$2:$AC$90) -> 20 | J29: =G29-H29 -> 134 | K29: =IFERROR(J29/E29,0) -> 1.9142857 | L29: =E29*33000 -> 2310000 | M29: =SUMIF('Target Achieved- Input'!$L$2:$L$90,'Incentive Report- Output'!B29,'Target Achieved- Input'!$M$2:$M$90) -> 4975016 | N29: =SUMIF('Target Achieved- Input'!$S$2:$S$90,'Incentive Report- Output'!B29,'Target Achieved- Input'!$U$2:$U$90) -> 0 | O29: =SUMIF('Target Achieved- Input'!$L$2:$L$90,'Incentive Report- Output'!B29,'Target Achieved- Input'!$N$2:$N$90)-N29 -> 4216115.3 | P29: =IFERROR(O29/L29,0) -> 1.8251581 | Q29: =P29 -> 1.8251581 | R29: 0 | S29: =(LOOKUP(Q29,Policy!$L$12:$M$16)+R29)*O29 -> 126483.46 | X29: =E37 -> 455 | Y29: =J37 -> 500 | Z29: =Y29/X29 -> 1.0989011 | AA29: 0 | AB29: 0 | AC29: 0 | AD29: =IF(AF29>200000,AF29-200000,0) -> 0 | AE29: =AF29-AD29 -> 126483.46 | AF29: =S29+W29+AB29+AC29 -> 126483.46 | AI29: Susmita Paul | AJ29: NHP166 | AK29: R5 | AL29: 126483.46 | AM29: =AF29 -> 126483.46 | AN29: =AL29-AM29 -> 0
A30: Masud Rana | B30: NHP386 | C30: SBM | D30: R5 | E30: =ROUND(SUMIF('Target Achieved- Input'!$B$2:$B$90,'Incentive Report- Output'!B30,'Target Achieved- Input'!$G$2:$G$90),0) -> 65 | F30: =ROUND(SUMIF('Target Achieved- Input'!$B$2:$B$90,'Incentive Report- Output'!B30,'Target Achieved- Input'!$H$2:$H$90),0) -> 85 | G30: =SUMIF('Target Achieved- Input'!$L$2:$L$90,'Incentive Report- Output'!B30,'Target Achieved- Input'!$O$2:$O$90) -> 61 | H30: =SUMIF('Target Achieved- Input'!$S$2:$S$90,'Incentive Report- Output'!B30,'Target Achieved- Input'!$V$2:$V$90) -> 0 | I30: =SUMIF('Target Achieved- Input'!$L$2:$L$90,'Incentive Report- Output'!B30,'Target Achieved- Input'!$AC$2:$AC$90) -> 6 | J30: =G30-H30 -> 61 | K30: =IFERROR(J30/E30,0) -> 0.93846154 | L30: =E30*33000 -> 2145000 | M30: =SUMIF('Target Achieved- Input'!$L$2:$L$90,'Incentive Report- Output'!B30,'Target Achieved- Input'!$M$2:$M$90) -> 2390739 | N30: =SUMIF('Target Achieved- Input'!$S$2:$S$90,'Incentive Report- Output'!B30,'Target Achieved- Input'!$U$2:$U$90) -> 0 | O30: =SUMIF('Target Achieved- Input'!$L$2:$L$90,'Incentive Report- Output'!B30,'Target Achieved- Input'!$N$2:$N$90)-N30 -> 2026050 | P30: =IFERROR(O30/L30,0) -> 0.94454545 | Q30: =MAX(P30,K30) -> 0.94454545 | R30: 0 | S30: =(LOOKUP(Q30,Policy!$L$12:$M$16)+R30)*O30 -> 20260.5 | T30: =L32+L36 -> 3300000 | U30: =O32+O36 -> 2290704.2 | V30: =IFERROR(U30/T30,0) -> 0.6941528 | W30: =LOOKUP(V30,Policy!$L$18:$M$21)*U30 -> 0 | AA30: 0 | AB30: 0 | AC30: 0 | AD30: =IF(AF30>200000,AF30-200000,0) -> 0 | AE30: =AF30-AD30 -> 20260.5 | AF30: =S30+W30+AB30+AC30 -> 20260.5 | AI30: Masud Rana | AJ30: NHP386 | AK30: R5 | AL30: 20260.5 | AM30: =AF30 -> 20260.5 | AN30: =AL30-AM30 -> 0
A31: Nildeep Dasgupta | B31: NHP807 | C31: BDE | D31: R5 | E31: =ROUND(SUMIF('Target Achieved- Input'!$B$2:$B$90,'Incentive Report- Output'!B31,'Target Achieved- Input'!$G$2:$G$90),0) -> 30 | F31: =ROUND(SUMIF('Target Achieved- Input'!$B$2:$B$90,'Incentive Report- Output'!B31,'Target Achieved- Input'!$H$2:$H$90),0) -> 39 | G31: =SUMIF('Target Achieved- Input'!$L$2:$L$90,'Incentive Report- Output'!B31,'Target Achieved- Input'!$O$2:$O$90) -> 22 | H31: =SUMIF('Target Achieved- Input'!$S$2:$S$90,'Incentive Report- Output'!B31,'Target Achieved- Input'!$V$2:$V$90) -> 6 | I31: =SUMIF('Target Achieved- Input'!$L$2:$L$90,'Incentive Report- Output'!B31,'Target Achieved- Input'!$AC$2:$AC$90) -> 7 | J31: =G31-H31 -> 16 | K31: =IFERROR(J31/E31,0) -> 0.53333333 | L31: =E31*33000 -> 990000 | M31: =SUMIF('Target Achieved- Input'!$L$2:$L$90,'Incentive Report- Output'!B31,'Target Achieved- Input'!$M$2:$M$90) -> 680078 | N31: =SUMIF('Target Achieved- Input'!$S$2:$S$90,'Incentive Report- Output'!B31,'Target Achieved- Input'!$U$2:$U$90) -> 106774.58 | O31: =SUMIF('Target Achieved- Input'!$L$2:$L$90,'Incentive Report- Output'!B31,'Target Achieved- Input'!$N$2:$N$90)-N31 -> 469562.71 | P31: =IFERROR(O31/L31,0) -> 0.47430577 | Q31: =P31 -> 0.47430577 | R31: 0 | S31: =(LOOKUP(Q31,Policy!$L$12:$M$16)+R31)*O31 -> 0 | AA31: 0 | AB31: 0 | AC31: 0 | AD31: =IF(AF31>200000,AF31-200000,0) -> 0 | AE31: =AF31-AD31 -> 0 | AF31: =S31+W31+AB31+AC31 -> 0 | AI31: Nildeep Dasgupta | AJ31: NHP807 | AK31: R5 | AL31: 2881.6864 | AM31: =AF31 -> 0 | AN31: =AL31-AM31 -> 2881.6864
A32: Nilotpal Sharma | B32: NHP675 | C32: BDE | D32: R5 | E32: =ROUND(SUMIF('Target Achieved- Input'!$B$2:$B$90,'Incentive Report- Output'!B32,'Target Achieved- Input'!$G$2:$G$90),0) -> 50 | F32: =ROUND(SUMIF('Target Achieved- Input'!$B$2:$B$90,'Incentive Report- Output'!B32,'Target Achieved- Input'!$H$2:$H$90),0) -> 65 | G32: =SUMIF('Target Achieved- Input'!$L$2:$L$90,'Incentive Report- Output'!B32,'Target Achieved- Input'!$O$2:$O$90) -> 42 | H32: =SUMIF('Target Achieved- Input'!$S$2:$S$90,'Incentive Report- Output'!B32,'Target Achieved- Input'!$V$2:$V$90) -> 0 | I32: =SUMIF('Target Achieved- Input'!$L$2:$L$90,'Incentive Report- Output'!B32,'Target Achieved- Input'!$AC$2:$AC$90) -> 4 | J32: =G32-H32 -> 42 | K32: =IFERROR(J32/E32,0) -> 0.84 | L32: =E32*33000 -> 1650000 | M32: =SUMIF('Target Achieved- Input'!$L$2:$L$90,'Incentive Report- Output'!B32,'Target Achieved- Input'!$M$2:$M$90) -> 1659358 | N32: =SUMIF('Target Achieved- Input'!$S$2:$S$90,'Incentive Report- Output'!B32,'Target Achieved- Input'!$U$2:$U$90) -> 0 | O32: =SUMIF('Target Achieved- Input'!$L$2:$L$90,'Incentive Report- Output'!B32,'Target Achieved- Input'!$N$2:$N$90)-N32 -> 1406235.6 | P32: =IFERROR(O32/L32,0) -> 0.852264 | Q32: =MAX(P32,K32) -> 0.852264 | R32: 0 | S32: =(LOOKUP(Q32,Policy!$L$12:$M$16)+R32)*O32 -> 14062.356 | AA32: 0 | AB32: 0 | AC32: 0 | AD32: =IF(AF32>200000,AF32-200000,0) -> 0 | AE32: =AF32-AD32 -> 14062.356 | AF32: =S32+W32+AB32+AC32 -> 14062.356 | AI32: Nilotpal Sharma | AJ32: NHP675 | AK32: R5 | AL32: 14062.356 | AM32: =AF32 -> 14062.356 | AN32: =AL32-AM32 -> 0
A33: Sambit Kumar | B33: NHP717 | C33: BDE | D33: R5 | E33: =ROUND(SUMIF('Target Achieved- Input'!$B$2:$B$90,'Incentive Report- Output'!B33,'Target Achieved- Input'!$G$2:$G$90),0) -> 60 | F33: =ROUND(SUMIF('Target Achieved- Input'!$B$2:$B$90,'Incentive Report- Output'!B33,'Target Achieved- Input'!$H$2:$H$90),0) -> 78 | G33: =SUMIF('Target Achieved- Input'!$L$2:$L$90,'Incentive Report- Output'!B33,'Target Achieved- Input'!$O$2:$O$90) -> 43 | H33: =SUMIF('Target Achieved- Input'!$S$2:$S$90,'Incentive Report- Output'!B33,'Target Achieved- Input'!$V$2:$V$90) -> 0 | I33: =SUMIF('Target Achieved- Input'!$L$2:$L$90,'Incentive Report- Output'!B33,'Target Achieved- Input'!$AC$2:$AC$90) -> 4 | J33: =G33-H33 -> 43 | K33: =IFERROR(J33/E33,0) -> 0.71666667 | L33: =E33*33000 -> 1980000 | M33: =SUMIF('Target Achieved- Input'!$L$2:$L$90,'Incentive Report- Output'!B33,'Target Achieved- Input'!$M$2:$M$90) -> 1854207 | N33: =SUMIF('Target Achieved- Input'!$S$2:$S$90,'Incentive Report- Output'!B33,'Target Achieved- Input'!$U$2:$U$90) -> 0 | O33: =SUMIF('Target Achieved- Input'!$L$2:$L$90,'Incentive Report- Output'!B33,'Target Achieved- Input'!$N$2:$N$90)-N33 -> 1571361.9 | P33: =IFERROR(O33/L33,0) -> 0.7936171 | Q33: =MAX(P33,K33) -> 0.7936171 | R33: 0 | S33: =(LOOKUP(Q33,Policy!$L$12:$M$16)+R33)*O33 -> 7856.8093 | AA33: 0 | AB33: 0 | AC33: 0 | AD33: =IF(AF33>200000,AF33-200000,0) -> 0 | AE33: =AF33-AD33 -> 7856.8093 | AF33: =S33+W33+AB33+AC33 -> 7856.8093 | AI33: Sambit Kumar | AJ33: NHP717 | AK33: R5 | AL33: 7856.8093 | AM33: =AF33 -> 7856.8093 | AN33: =AL33-AM33 -> 0
A34: Sriti Jaiswal | B34: NHP553 | C34: BDE | D34: R5 | E34: =ROUND(SUMIF('Target Achieved- Input'!$B$2:$B$90,'Incentive Report- Output'!B34,'Target Achieved- Input'!$G$2:$G$90),0) -> 65 | F34: =ROUND(SUMIF('Target Achieved- Input'!$B$2:$B$90,'Incentive Report- Output'!B34,'Target Achieved- Input'!$H$2:$H$90),0) -> 85 | G34: =SUMIF('Target Achieved- Input'!$L$2:$L$90,'Incentive Report- Output'!B34,'Target Achieved- Input'!$O$2:$O$90) -> 92 | H34: =SUMIF('Target Achieved- Input'!$S$2:$S$90,'Incentive Report- Output'!B34,'Target Achieved- Input'!$V$2:$V$90) -> 0 | I34: =SUMIF('Target Achieved- Input'!$L$2:$L$90,'Incentive Report- Output'!B34,'Target Achieved- Input'!$AC$2:$AC$90) -> 16 | J34: =G34-H34 -> 92 | K34: =IFERROR(J34/E34,0) -> 1.4153846 | L34: =E34*33000 -> 2145000 | M34: =SUMIF('Target Achieved- Input'!$L$2:$L$90,'Incentive Report- Output'!B34,'Target Achieved- Input'!$M$2:$M$90) -> 3472358 | N34: =SUMIF('Target Achieved- Input'!$S$2:$S$90,'Incentive Report- Output'!B34,'Target Achieved- Input'!$U$2:$U$90) -> 0 | O34: =SUMIF('Target Achieved- Input'!$L$2:$L$90,'Incentive Report- Output'!B34,'Target Achieved- Input'!$N$2:$N$90)-N34 -> 2942676.3 | P34: =IFERROR(O34/L34,0) -> 1.371877 | Q34: =P34 -> 1.371877 | R34: 0 | S34: =(LOOKUP(Q34,Policy!$L$12:$M$16)+R34)*O34 -> 88280.288 | AA34: 0 | AB34: 0 | AC34: 0 | AD34: =IF(AF34>200000,AF34-200000,0) -> 0 | AE34: =AF34-AD34 -> 88280.288 | AF34: =S34+W34+AB34+AC34 -> 88280.288 | AI34: Sriti Jaiswal | AJ34: NHP553 | AK34: R5 | AL34: 88280.288 | AM34: =AF34 -> 88280.288 | AN34: =AL34-AM34 -> 0
A35: Subash Debnath | B35: NHP148 | C35: SBM | D35: R5 | E35: =ROUND(SUMIF('Target Achieved- Input'!$B$2:$B$90,'Incentive Report- Output'!B35,'Target Achieved- Input'!$G$2:$G$90),0) -> 65 | F35: =ROUND(SUMIF('Target Achieved- Input'!$B$2:$B$90,'Incentive Report- Output'!B35,'Target Achieved- Input'!$H$2:$H$90),0) -> 85 | G35: =SUMIF('Target Achieved- Input'!$L$2:$L$90,'Incentive Report- Output'!B35,'Target Achieved- Input'!$O$2:$O$90) -> 85 | H35: =SUMIF('Target Achieved- Input'!$S$2:$S$90,'Incentive Report- Output'!B35,'Target Achieved- Input'!$V$2:$V$90) -> 0 | I35: =SUMIF('Target Achieved- Input'!$L$2:$L$90,'Incentive Report- Output'!B35,'Target Achieved- Input'!$AC$2:$AC$90) -> 7 | J35: =G35-H35 -> 85 | K35: =IFERROR(J35/E35,0) -> 1.3076923 | L35: =E35*33000 -> 2145000 | M35: =SUMIF('Target Achieved- Input'!$L$2:$L$90,'Incentive Report- Output'!B35,'Target Achieved- Input'!$M$2:$M$90) -> 3447765 | N35: =SUMIF('Target Achieved- Input'!$S$2:$S$90,'Incentive Report- Output'!B35,'Target Achieved- Input'!$U$2:$U$90) -> 0 | O35: =SUMIF('Target Achieved- Input'!$L$2:$L$90,'Incentive Report- Output'!B35,'Target Achieved- Input'!$N$2:$N$90)-N35 -> 2921834.7 | P35: =IFERROR(O35/L35,0) -> 1.3621607 | Q35: =MAX(P35,K35) -> 1.3621607 | R35: 0 | S35: =(LOOKUP(Q35,Policy!$L$12:$M$16)+R35)*O35 -> 87655.042 | T35: =L33 -> 1980000 | U35: =O33 -> 1571361.9 | V35: =IFERROR(U35/T35,0) -> 0.7936171 | W35: =LOOKUP(V35,Policy!$L$18:$M$21)*U35 -> 0 | AA35: 0 | AB35: 0 | AC35: 0 | AD35: =IF(AF35>200000,AF35-200000,0) -> 0 | AE35: =AF35-AD35 -> 87655.042 | AF35: =S35+W35+AB35+AC35 -> 87655.042 | AI35: Subash Debnath | AJ35: NHP148 | AK35: R5 | AL35: 87655.042 | AM35: =AF35 -> 87655.042 | AN35: =AL35-AM35 -> 0
A36: Satyaki Acharjee | B36: NHP826 | C36: BDE | D36: R5 | E36: =ROUND(SUMIF('Target Achieved- Input'!$B$2:$B$90,'Incentive Report- Output'!B36,'Target Achieved- Input'!$G$2:$G$90),0) -> 50 | F36: =ROUND(SUMIF('Target Achieved- Input'!$B$2:$B$90,'Incentive Report- Output'!B36,'Target Achieved- Input'!$H$2:$H$90),0) -> 65 | G36: =SUMIF('Target Achieved- Input'!$L$2:$L$90,'Incentive Report- Output'!B36,'Target Achieved- Input'!$O$2:$O$90) -> 27 | H36: =SUMIF('Target Achieved- Input'!$S$2:$S$90,'Incentive Report- Output'!B36,'Target Achieved- Input'!$V$2:$V$90) -> 0 | I36: =SUMIF('Target Achieved- Input'!$L$2:$L$90,'Incentive Report- Output'!B36,'Target Achieved- Input'!$AC$2:$AC$90) -> 3 | J36: =G36-H36 -> 27 | K36: =IFERROR(J36/E36,0) -> 0.54 | L36: =E36*33000 -> 1650000 | M36: =SUMIF('Target Achieved- Input'!$L$2:$L$90,'Incentive Report- Output'!B36,'Target Achieved- Input'!$M$2:$M$90) -> 1043673 | N36: =SUMIF('Target Achieved- Input'!$S$2:$S$90,'Incentive Report- Output'!B36,'Target Achieved- Input'!$U$2:$U$90) -> 0 | O36: =SUMIF('Target Achieved- Input'!$L$2:$L$90,'Incentive Report- Output'!B36,'Target Achieved- Input'!$N$2:$N$90)-N36 -> 884468.64 | P36: =IFERROR(O36/L36,0) -> 0.5360416 | Q36: =P36 -> 0.5360416 | R36: 0 | S36: =(LOOKUP(Q36,Policy!$L$12:$M$16)+R36)*O36 -> 4422.3432 | AA36: 0 | AB36: 0 | AC36: 0 | AD36: =IF(AF36>200000,AF36-200000,0) -> 0 | AE36: =AF36-AD36 -> 4422.3432 | AF36: =S36+W36+AB36+AC36 -> 4422.3432 | AI36: Satyaki Acharjee | AJ36: NHP826 | AK36: R5 | AL36: 4422.3432 | AM36: =AF36 -> 4422.3432 | AN36: =AL36-AM36 -> 0
A37: TOTAL | D37: R5 | E37: =SUM(E29:E36) -> 455 | F37: =SUM(F29:F36) -> 593 | G37: =SUM(G29:G36) -> 506 | H37: =SUM(H29:H36) -> 6 | I37: =SUM(I29:I36) -> 67 | J37: =SUM(J29:J36) -> 500 | L37: =SUM(L29:L36) -> 15015000 | M37: =SUM(M29:M36) -> 19523194 | N37: =SUM(N29:N36) -> 106774.58 | O37: =SUM(O29:O36) -> 16438305 | S37: =SUM(S29:S36) -> 349020.8 | T37: =SUM(T29:T36) -> 5280000 | U37: =SUM(U29:U36) -> 3862066.1 | V37: =SUM(V29:V36) -> 1.4877699 | W37: =SUM(W29:W36) -> 0 | X37: =SUM(X29:X36) -> 455 | Y37: =SUM(Y29:Y36) -> 500 | Z37: =SUM(Z29:Z36) -> 1.0989011 | ... AF37: =SUM(AF29:AF36) -> 349020.8 | AI37: TOTAL | AK37: R5 | AL37: 351902.48 | AM37: =SUM(AM29:AM36) -> 349020.8 | AN37: =SUM(AN29:AN36) -> 2881.6864
A38: Akar Srivastava | B38: NHP169 | C38: BDE | D38: R6 | E38: =ROUND(SUMIF('Target Achieved- Input'!$B$2:$B$90,'Incentive Report- Output'!B38,'Target Achieved- Input'!$G$2:$G$90),0) -> 50 | F38: =ROUND(SUMIF('Target Achieved- Input'!$B$2:$B$90,'Incentive Report- Output'!B38,'Target Achieved- Input'!$H$2:$H$90),0) -> 65 | G38: =SUMIF('Target Achieved- Input'!$L$2:$L$90,'Incentive Report- Output'!B38,'Target Achieved- Input'!$O$2:$O$90) -> 46 | H38: =SUMIF('Target Achieved- Input'!$S$2:$S$90,'Incentive Report- Output'!B38,'Target Achieved- Input'!$V$2:$V$90) -> 0 | I38: =SUMIF('Target Achieved- Input'!$L$2:$L$90,'Incentive Report- Output'!B38,'Target Achieved- Input'!$AC$2:$AC$90) -> 2 | J38: =G38-H38 -> 46 | K38: =IFERROR(J38/E38,0) -> 0.92 | L38: =E38*33000 -> 1650000 | M38: =SUMIF('Target Achieved- Input'!$L$2:$L$90,'Incentive Report- Output'!B38,'Target Achieved- Input'!$M$2:$M$90) -> 2046854 | N38: =SUMIF('Target Achieved- Input'!$S$2:$S$90,'Incentive Report- Output'!B38,'Target Achieved- Input'!$U$2:$U$90) -> 0 | O38: =SUMIF('Target Achieved- Input'!$L$2:$L$90,'Incentive Report- Output'!B38,'Target Achieved- Input'!$N$2:$N$90)-N38 -> 1734622 | P38: =IFERROR(O38/L38,0) -> 1.0512861 | Q38: =MAX(P38,K38) -> 1.0512861 | R38: 0 | S38: =(LOOKUP(Q38,Policy!$L$12:$M$16)+R38)*O38 -> 39028.996 | AA38: 0 | AB38: 0 | AC38: 0 | AD38: =IF(AF38>200000,AF38-200000,0) -> 0 | AE38: =AF38-AD38 -> 39028.996 | AF38: =S38+W38+AB38+AC38 -> 39028.996 | AI38: Akar Srivastava | AJ38: NHP169 | AK38: R6 | AL38: 39028.996 | AM38: =AF38 -> 39028.996 | AN38: =AL38-AM38 -> 0
A39: Faiq Khan | B39: NHP155 | C39: BDE | D39: R6 | E39: =ROUND(SUMIF('Target Achieved- Input'!$B$2:$B$90,'Incentive Report- Output'!B39,'Target Achieved- Input'!$G$2:$G$90),0) -> 60 | F39: =ROUND(SUMIF('Target Achieved- Input'!$B$2:$B$90,'Incentive Report- Output'!B39,'Target Achieved- Input'!$H$2:$H$90),0) -> 78 | G39: =SUMIF('Target Achieved- Input'!$L$2:$L$90,'Incentive Report- Output'!B39,'Target Achieved- Input'!$O$2:$O$90) -> 34 | H39: =SUMIF('Target Achieved- Input'!$S$2:$S$90,'Incentive Report- Output'!B39,'Target Achieved- Input'!$V$2:$V$90) -> 2 | I39: =SUMIF('Target Achieved- Input'!$L$2:$L$90,'Incentive Report- Output'!B39,'Target Achieved- Input'!$AC$2:$AC$90) -> 8 | J39: =G39-H39 -> 32 | K39: =IFERROR(J39/E39,0) -> 0.53333333 | L39: =E39*33000 -> 1980000 | M39: =SUMIF('Target Achieved- Input'!$L$2:$L$90,'Incentive Report- Output'!B39,'Target Achieved- Input'!$M$2:$M$90) -> 1380666 | N39: =SUMIF('Target Achieved- Input'!$S$2:$S$90,'Incentive Report- Output'!B39,'Target Achieved- Input'!$U$2:$U$90) -> 99150.847 | O39: =SUMIF('Target Achieved- Input'!$L$2:$L$90,'Incentive Report- Output'!B39,'Target Achieved- Input'!$N$2:$N$90)-N39 -> 1070905.1 | P39: =IFERROR(O39/L39,0) -> 0.54086115 | Q39: =MAX(P39,K39) -> 0.54086115 | R39: 0 | S39: =(LOOKUP(Q39,Policy!$L$12:$M$16)+R39)*O39 -> 5354.5254 | AA39: 0 | AB39: 0 | AC39: 0 | AD39: =IF(AF39>200000,AF39-200000,0) -> 0 | AE39: =AF39-AD39 -> 5354.5254 | AF39: =S39+W39+AB39+AC39 -> 5354.5254 | AI39: Faiq Khan | AJ39: NHP155 | AK39: R6 | AL39: 5850.2797 | AM39: =AF39 -> 5354.5254 | AN39: =AL39-AM39 -> 495.75424
A40: Manoj Sharma | B40: NHP470 | C40: BDE | D40: R6 | E40: =ROUND(SUMIF('Target Achieved- Input'!$B$2:$B$90,'Incentive Report- Output'!B40,'Target Achieved- Input'!$G$2:$G$90),0) -> 60 | F40: =ROUND(SUMIF('Target Achieved- Input'!$B$2:$B$90,'Incentive Report- Output'!B40,'Target Achieved- Input'!$H$2:$H$90),0) -> 78 | G40: =SUMIF('Target Achieved- Input'!$L$2:$L$90,'Incentive Report- Output'!B40,'Target Achieved- Input'!$O$2:$O$90) -> 25 | H40: =SUMIF('Target Achieved- Input'!$S$2:$S$90,'Incentive Report- Output'!B40,'Target Achieved- Input'!$V$2:$V$90) -> 0 | I40: =SUMIF('Target Achieved- Input'!$L$2:$L$90,'Incentive Report- Output'!B40,'Target Achieved- Input'!$AC$2:$AC$90) -> 6 | J40: =G40-H40 -> 25 | K40: =IFERROR(J40/E40,0) -> 0.41666667 | L40: =E40*33000 -> 1980000 | M40: =SUMIF('Target Achieved- Input'!$L$2:$L$90,'Incentive Report- Output'!B40,'Target Achieved- Input'!$M$2:$M$90) -> 895175 | N40: =SUMIF('Target Achieved- Input'!$S$2:$S$90,'Incentive Report- Output'!B40,'Target Achieved- Input'!$U$2:$U$90) -> 0 | O40: =SUMIF('Target Achieved- Input'!$L$2:$L$90,'Incentive Report- Output'!B40,'Target Achieved- Input'!$N$2:$N$90)-N40 -> 758622.88 | P40: =IFERROR(O40/L40,0) -> 0.38314287 | Q40: =P40 -> 0.38314287 | R40: 0 | S40: =(LOOKUP(Q40,Policy!$L$12:$M$16)+R40)*O40 -> 0 | AA40: 0 | AB40: 0 | AC40: 0 | AD40: =IF(AF40>200000,AF40-200000,0) -> 0 | AE40: =AF40-AD40 -> 0 | AF40: =S40+W40+AB40+AC40 -> 0 | AI40: Manoj Sharma | AJ40: NHP470 | AK40: R6 | AL40: 0 | AM40: =AF40 -> 0 | AN40: =AL40-AM40 -> 0
A41: Mudit Raj | B41: NHP142 | C41: BDE | D41: R6 | E41: =ROUND(SUMIF('Target Achieved- Input'!$B$2:$B$90,'Incentive Report- Output'!B41,'Target Achieved- Input'!$G$2:$G$90),0) -> 60 | F41: =ROUND(SUMIF('Target Achieved- Input'!$B$2:$B$90,'Incentive Report- Output'!B41,'Target Achieved- Input'!$H$2:$H$90),0) -> 78 | G41: =SUMIF('Target Achieved- Input'!$L$2:$L$90,'Incentive Report- Output'!B41,'Target Achieved- Input'!$O$2:$O$90) -> 64 | H41: =SUMIF('Target Achieved- Input'!$S$2:$S$90,'Incentive Report- Output'!B41,'Target Achieved- Input'!$V$2:$V$90) -> 3 | I41: =SUMIF('Target Achieved- Input'!$L$2:$L$90,'Incentive Report- Output'!B41,'Target Achieved- Input'!$AC$2:$AC$90) -> 8 | J41: =G41-H41 -> 61 | K41: =IFERROR(J41/E41,0) -> 1.0166667 | L41: =E41*33000 -> 1980000 | M41: =SUMIF('Target Achieved- Input'!$L$2:$L$90,'Incentive Report- Output'!B41,'Target Achieved- Input'!$M$2:$M$90) -> 2690736 | N41: =SUMIF('Target Achieved- Input'!$S$2:$S$90,'Incentive Report- Output'!B41,'Target Achieved- Input'!$U$2:$U$90) -> 116946.61 | O41: =SUMIF('Target Achieved- Input'!$L$2:$L$90,'Incentive Report- Output'!B41,'Target Achieved- Input'!$N$2:$N$90)-N41 -> 2163338.1 | P41: =IFERROR(O41/L41,0) -> 1.092595 | Q41: =MAX(P41,K41) -> 1.092595 | R41: 0 | S41: =(LOOKUP(Q41,Policy!$L$12:$M$16)+R41)*O41 -> 48675.108 | AA41: 0 | AB41: 0 | AC41: 0 | AD41: =IF(AF41>200000,AF41-200000,0) -> 0 | AE41: =AF41-AD41 -> 48675.108 | AF41: =S41+W41+AB41+AC41 -> 48675.108 | AI41: Mudit Raj | AJ41: NHP142 | AK41: R6 | AL41: 51306.407 | AM41: =AF41 -> 48675.108 | AN41: =AL41-AM41 -> 2631.2987
A42: Prashant Vaibhav | B42: NHP676 | C42: BDE | D42: R6 | E42: =ROUND(SUMIF('Target Achieved- Input'!$B$2:$B$90,'Incentive Report- Output'!B42,'Target Achieved- Input'!$G$2:$G$90),0) -> 70 | F42: =ROUND(SUMIF('Target Achieved- Input'!$B$2:$B$90,'Incentive Report- Output'!B42,'Target Achieved- Input'!$H$2:$H$90),0) -> 91 | G42: =SUMIF('Target Achieved- Input'!$L$2:$L$90,'Incentive Report- Output'!B42,'Target Achieved- Input'!$O$2:$O$90) -> 114 | H42: =SUMIF('Target Achieved- Input'!$S$2:$S$90,'Incentive Report- Output'!B42,'Target Achieved- Input'!$V$2:$V$90) -> 0 | I42: =SUMIF('Target Achieved- Input'!$L$2:$L$90,'Incentive Report- Output'!B42,'Target Achieved- Input'!$AC$2:$AC$90) -> 8 | J42: =G42-H42 -> 114 | K42: =IFERROR(J42/E42,0) -> 1.6285714 | L42: =E42*33000 -> 2310000 | M42: =SUMIF('Target Achieved- Input'!$L$2:$L$90,'Incentive Report- Output'!B42,'Target Achieved- Input'!$M$2:$M$90) -> 5457486 | N42: =SUMIF('Target Achieved- Input'!$S$2:$S$90,'Incentive Report- Output'!B42,'Target Achieved- Input'!$U$2:$U$90) -> 0 | O42: =SUMIF('Target Achieved- Input'!$L$2:$L$90,'Incentive Report- Output'!B42,'Target Achieved- Input'!$N$2:$N$90)-N42 -> 4624988.1 | P42: =IFERROR(O42/L42,0) -> 2.0021594 | Q42: =MAX(P42,K42) -> 2.0021594 | R42: 0 | S42: =(LOOKUP(Q42,Policy!$L$12:$M$16)+R42)*O42 -> 138749.64 | AA42: 0 | AB42: 0 | AC42: 0 | AD42: =IF(AF42>200000,AF42-200000,0) -> 0 | AE42: =AF42-AD42 -> 138749.64 | AF42: =S42+W42+AB42+AC42 -> 138749.64 | AI42: Prashant Vaibhav | AJ42: NHP676 | AK42: R6 | AL42: 138749.64 | AM42: =AF42 -> 138749.64 | AN42: =AL42-AM42 -> 0
A43: Suraj Singh | B43: NHP446 | C43: BDE | D43: R6 | E43: =ROUND(SUMIF('Target Achieved- Input'!$B$2:$B$90,'Incentive Report- Output'!B43,'Target Achieved- Input'!$G$2:$G$90),0) -> 65 | F43: =ROUND(SUMIF('Target Achieved- Input'!$B$2:$B$90,'Incentive Report- Output'!B43,'Target Achieved- Input'!$H$2:$H$90),0) -> 85 | G43: =SUMIF('Target Achieved- Input'!$L$2:$L$90,'Incentive Report- Output'!B43,'Target Achieved- Input'!$O$2:$O$90) -> 25 | H43: =SUMIF('Target Achieved- Input'!$S$2:$S$90,'Incentive Report- Output'!B43,'Target Achieved- Input'!$V$2:$V$90) -> 1 | I43: =SUMIF('Target Achieved- Input'!$L$2:$L$90,'Incentive Report- Output'!B43,'Target Achieved- Input'!$AC$2:$AC$90) -> 3 | J43: =G43-H43 -> 24 | K43: =IFERROR(J43/E43,0) -> 0.36923077 | L43: =E43*33000 -> 2145000 | M43: =SUMIF('Target Achieved- Input'!$L$2:$L$90,'Incentive Report- Output'!B43,'Target Achieved- Input'!$M$2:$M$90) -> 1057425 | N43: =SUMIF('Target Achieved- Input'!$S$2:$S$90,'Incentive Report- Output'!B43,'Target Achieved- Input'!$U$2:$U$90) -> 43219.492 | O43: =SUMIF('Target Achieved- Input'!$L$2:$L$90,'Incentive Report- Output'!B43,'Target Achieved- Input'!$N$2:$N$90)-N43 -> 852903.39 | P43: =IFERROR(O43/L43,0) -> 0.39762396 | Q43: =MAX(P43,K43) -> 0.39762396 | R43: 0 | S43: =(LOOKUP(Q43,Policy!$L$12:$M$16)+R43)*O43 -> 0 | AA43: 0 | AB43: 0 | AC43: 0 | AD43: =IF(AF43>200000,AF43-200000,0) -> 0 | AE43: =AF43-AD43 -> 0 | AF43: =S43+W43+AB43+AC43 -> 0 | AI43: Suraj Singh | AJ43: NHP446 | AK43: R6 | AL43: 0 | AM43: =AF43 -> 0 | AN43: =AL43-AM43 -> 0
A44: Vinod Pathania | B44: NHP151 | C44: BDE | D44: R6 | E44: =ROUND(SUMIF('Target Achieved- Input'!$B$2:$B$90,'Incentive Report- Output'!B44,'Target Achieved- Input'!$G$2:$G$90),0) -> 50 | F44: =ROUND(SUMIF('Target Achieved- Input'!$B$2:$B$90,'Incentive Report- Output'!B44,'Target Achieved- Input'!$H$2:$H$90),0) -> 65 | G44: =SUMIF('Target Achieved- Input'!$L$2:$L$90,'Incentive Report- Output'!B44,'Target Achieved- Input'!$O$2:$O$90) -> 12 | H44: =SUMIF('Target Achieved- Input'!$S$2:$S$90,'Incentive Report- Output'!B44,'Target Achieved- Input'!$V$2:$V$90) -> 4 | I44: =SUMIF('Target Achieved- Input'!$L$2:$L$90,'Incentive Report- Output'!B44,'Target Achieved- Input'!$AC$2:$AC$90) -> 0 | J44: =G44-H44 -> 8 | K44: =IFERROR(J44/E44,0) -> 0.16 | L44: =E44*33000 -> 1650000 | M44: =SUMIF('Target Achieved- Input'!$L$2:$L$90,'Incentive Report- Output'!B44,'Target Achieved- Input'!$M$2:$M$90) -> 674588 | N44: =SUMIF('Target Achieved- Input'!$S$2:$S$90,'Incentive Report- Output'!B44,'Target Achieved- Input'!$U$2:$U$90) -> 149657.63 | O44: =SUMIF('Target Achieved- Input'!$L$2:$L$90,'Incentive Report- Output'!B44,'Target Achieved- Input'!$N$2:$N$90)-N44 -> 422027.12 | P44: =IFERROR(O44/L44,0) -> 0.25577401 | Q44: =MAX(P44,K44) -> 0.25577401 | R44: 0 | S44: =(LOOKUP(Q44,Policy!$L$12:$M$16)+R44)*O44 -> 0 | AA44: 0 | AB44: 0 | AC44: 0 | AD44: =IF(AF44>200000,AF44-200000,0) -> 0 | AE44: =AF44-AD44 -> 0 | AF44: =S44+W44+AB44+AC44 -> 0 | AI44: Vinod Pathania | AJ44: NHP151 | AK44: R6 | AL44: 0 | AM44: =AF44 -> 0 | AN44: =AL44-AM44 -> 0
A45: TOTAL | D45: R6 | E45: =SUM(E38:E44) -> 415 | F45: =SUM(F38:F44) -> 540 | G45: =SUM(G38:G44) -> 320 | H45: =SUM(H38:H44) -> 10 | I45: =SUM(I38:I44) -> 35 | J45: =SUM(J38:J44) -> 310 | L45: =SUM(L38:L44) -> 13695000 | M45: =SUM(M38:M44) -> 14202930 | N45: =SUM(N38:N44) -> 408974.58 | O45: =SUM(O38:O44) -> 11627407 | S45: =SUM(S38:S44) -> 231808.27 | T45: =SUM(T38:T44) -> 0 | U45: =SUM(U38:U44) -> 0 | V45: =SUM(V38:V44) -> 0 | W45: =SUM(W38:W44) -> 0 | X45: =SUM(X38:X44) -> 0 | Y45: =SUM(Y38:Y44) -> 0 | Z45: =SUM(Z38:Z44) -> 0 | ... AF45: =SUM(AF38:AF44) -> 231808.27 | AI45: TOTAL | AK45: R6 | AL45: 234935.33 | AM45: =SUM(AM38:AM44) -> 231808.27 | AN45: =SUM(AN38:AN44) -> 3127.053
A46: Sufiyan Ansari | B46: NHP160 | C46: RM | D46: R7 | E46: =ROUND(SUMIF('Target Achieved- Input'!$B$2:$B$90,'Incentive Report- Output'!B46,'Target Achieved- Input'!$G$2:$G$90),0) -> 60 | F46: =ROUND(SUMIF('Target Achieved- Input'!$B$2:$B$90,'Incentive Report- Output'!B46,'Target Achieved- Input'!$H$2:$H$90),0) -> 78 | G46: =SUMIF('Target Achieved- Input'!$L$2:$L$90,'Incentive Report- Output'!B46,'Target Achieved- Input'!$O$2:$O$90) -> 46 | H46: =SUMIF('Target Achieved- Input'!$S$2:$S$90,'Incentive Report- Output'!B46,'Target Achieved- Input'!$V$2:$V$90) -> 12 | I46: =SUMIF('Target Achieved- Input'!$L$2:$L$90,'Incentive Report- Output'!B46,'Target Achieved- Input'!$AC$2:$AC$90) -> 2 | J46: =G46-H46 -> 34 | K46: =IFERROR(J46/E46,0) -> 0.56666667 | L46: =E46*33000 -> 1980000 | M46: =SUMIF('Target Achieved- Input'!$L$2:$L$90,'Incentive Report- Output'!B46,'Target Achieved- Input'!$M$2:$M$90) -> 1990654 | N46: =SUMIF('Target Achieved- Input'!$S$2:$S$90,'Incentive Report- Output'!B46,'Target Achieved- Input'!$U$2:$U$90) -> 548972.88 | O46: =SUMIF('Target Achieved- Input'!$L$2:$L$90,'Incentive Report- Output'!B46,'Target Achieved- Input'!$N$2:$N$90)-N46 -> 1138022 | P46: =IFERROR(O46/L46,0) -> 0.5747586 | Q46: =MAX(P46,K46) -> 0.5747586 | R46: 0 | S46: =(LOOKUP(Q46,Policy!$L$12:$M$16)+R46)*O46 -> 5690.1102 | X46: =E50 -> 225 | Y46: =J50 -> 157 | Z46: =Y46/X46 -> 0.69777778 | AA46: 0 | AB46: 0 | AC46: 0 | AD46: =IF(AF46>200000,AF46-200000,0) -> 0 | AE46: =AF46-AD46 -> 5690.1102 | AF46: =S46+W46+AB46+AC46 -> 5690.1102 | AI46: Sufiyan Ansari | AJ46: NHP160 | AK46: R7 | AL46: 16869.949 | AM46: =AF46 -> 5690.1102 | AN46: =AL46-AM46 -> 11179.839
A47: Manasvi Dhoke | B47: NHP674 | C47: BDE | D47: R7 | E47: =ROUND(SUMIF('Target Achieved- Input'!$B$2:$B$90,'Incentive Report- Output'!B47,'Target Achieved- Input'!$G$2:$G$90),0) -> 60 | F47: =ROUND(SUMIF('Target Achieved- Input'!$B$2:$B$90,'Incentive Report- Output'!B47,'Target Achieved- Input'!$H$2:$H$90),0) -> 78 | G47: =SUMIF('Target Achieved- Input'!$L$2:$L$90,'Incentive Report- Output'!B47,'Target Achieved- Input'!$O$2:$O$90) -> 67 | H47: =SUMIF('Target Achieved- Input'!$S$2:$S$90,'Incentive Report- Output'!B47,'Target Achieved- Input'!$V$2:$V$90) -> 0 | I47: =SUMIF('Target Achieved- Input'!$L$2:$L$90,'Incentive Report- Output'!B47,'Target Achieved- Input'!$AC$2:$AC$90) -> 2 | J47: =G47-H47 -> 67 | K47: =IFERROR(J47/E47,0) -> 1.1166667 | L47: =E47*33000 -> 1980000 | M47: =SUMIF('Target Achieved- Input'!$L$2:$L$90,'Incentive Report- Output'!B47,'Target Achieved- Input'!$M$2:$M$90) -> 3667233 | N47: =SUMIF('Target Achieved- Input'!$S$2:$S$90,'Incentive Report- Output'!B47,'Target Achieved- Input'!$U$2:$U$90) -> 0 | O47: =SUMIF('Target Achieved- Input'!$L$2:$L$90,'Incentive Report- Output'!B47,'Target Achieved- Input'!$N$2:$N$90)-N47 -> 3107824.6 | P47: =IFERROR(O47/L47,0) -> 1.5696084 | Q47: =MAX(P47,K47) -> 1.5696084 | R47: 0 | S47: =(LOOKUP(Q47,Policy!$L$12:$M$16)+R47)*O47 -> 93234.737 | AA47: 0 | AB47: 0 | AC47: 0 | AD47: =IF(AF47>200000,AF47-200000,0) -> 0 | AE47: =AF47-AD47 -> 93234.737 | AF47: =S47+W47+AB47+AC47 -> 93234.737 | AI47: Manasvi Dhoke | AJ47: NHP674 | AK47: R7 | AL47: 93234.737 | AM47: =AF47 -> 93234.737 | AN47: =AL47-AM47 -> 0
A48: Paras Doifode | B48: NHP551 | C48: BDE | D48: R7 | E48: =ROUND(SUMIF('Target Achieved- Input'!$B$2:$B$90,'Incentive Report- Output'!B48,'Target Achieved- Input'!$G$2:$G$90),0) -> 70 | F48: =ROUND(SUMIF('Target Achieved- Input'!$B$2:$B$90,'Incentive Report- Output'!B48,'Target Achieved- Input'!$H$2:$H$90),0) -> 91 | G48: =SUMIF('Target Achieved- Input'!$L$2:$L$90,'Incentive Report- Output'!B48,'Target Achieved- Input'!$O$2:$O$90) -> 27 | H48: =SUMIF('Target Achieved- Input'!$S$2:$S$90,'Incentive Report- Output'!B48,'Target Achieved- Input'!$V$2:$V$90) -> 0 | I48: =SUMIF('Target Achieved- Input'!$L$2:$L$90,'Incentive Report- Output'!B48,'Target Achieved- Input'!$AC$2:$AC$90) -> 2 | J48: =G48-H48 -> 27 | K48: =IFERROR(J48/E48,0) -> 0.38571429 | L48: =E48*33000 -> 2310000 | M48: =SUMIF('Target Achieved- Input'!$L$2:$L$90,'Incentive Report- Output'!B48,'Target Achieved- Input'!$M$2:$M$90) -> 997473 | N48: =SUMIF('Target Achieved- Input'!$S$2:$S$90,'Incentive Report- Output'!B48,'Target Achieved- Input'!$U$2:$U$90) -> 0 | O48: =SUMIF('Target Achieved- Input'!$L$2:$L$90,'Incentive Report- Output'!B48,'Target Achieved- Input'!$N$2:$N$90)-N48 -> 845316.1 | P48: =IFERROR(O48/L48,0) -> 0.36593771 | Q48: =P48 -> 0.36593771 | R48: 0 | S48: =(LOOKUP(Q48,Policy!$L$12:$M$16)+R48)*O48 -> 0 | AA48: 0 | AB48: 0 | AC48: 0 | AD48: =IF(AF48>200000,AF48-200000,0) -> 0 | AE48: =AF48-AD48 -> 0 | AF48: =S48+W48+AB48+AC48 -> 0 | AI48: Paras Doifode | AJ48: NHP551 | AK48: R7 | AL48: 0 | AM48: =AF48 -> 0 | AN48: =AL48-AM48 -> 0
A49: Shivani Chauhan | B49: NHP825 | C49: BDE | D49: R7 | E49: =ROUND(SUMIF('Target Achieved- Input'!$B$2:$B$90,'Incentive Report- Output'!B49,'Target Achieved- Input'!$G$2:$G$90),0) -> 35 | F49: =ROUND(SUMIF('Target Achieved- Input'!$B$2:$B$90,'Incentive Report- Output'!B49,'Target Achieved- Input'!$H$2:$H$90),0) -> 46 | G49: =SUMIF('Target Achieved- Input'!$L$2:$L$90,'Incentive Report- Output'!B49,'Target Achieved- Input'!$O$2:$O$90) -> 37 | H49: =SUMIF('Target Achieved- Input'!$S$2:$S$90,'Incentive Report- Output'!B49,'Target Achieved- Input'!$V$2:$V$90) -> 8 | I49: =SUMIF('Target Achieved- Input'!$L$2:$L$90,'Incentive Report- Output'!B49,'Target Achieved- Input'!$AC$2:$AC$90) -> 0 | J49: =G49-H49 -> 29 | K49: =IFERROR(J49/E49,0) -> 0.82857143 | L49: =E49*33000 -> 1155000 | M49: =SUMIF('Target Achieved- Input'!$L$2:$L$90,'Incentive Report- Output'!B49,'Target Achieved- Input'!$M$2:$M$90) -> 1667513 | N49: =SUMIF('Target Achieved- Input'!$S$2:$S$90,'Incentive Report- Output'!B49,'Target Achieved- Input'!$U$2:$U$90) -> 333891.53 | O49: =SUMIF('Target Achieved- Input'!$L$2:$L$90,'Incentive Report- Output'!B49,'Target Achieved- Input'!$N$2:$N$90)-N49 -> 1079255.1 | P49: =IFERROR(O49/L49,0) -> 0.93441999 | Q49: =MAX(P49,K49) -> 0.93441999 | R49: 0 | S49: =(LOOKUP(Q49,Policy!$L$12:$M$16)+R49)*O49 -> 10792.551 | AA49: 0 | AB49: 0 | AC49: 0 | AD49: =IF(AF49>200000,AF49-200000,0) -> 0 | AE49: =AF49-AD49 -> 10792.551 | AF49: =S49+W49+AB49+AC49 -> 10792.551 | AI49: Shivani Chauhan | AJ49: NHP825 | AK49: R7 | AL49: 31795.799 | AM49: =AF49 -> 10792.551 | AN49: =AL49-AM49 -> 21003.248
A50: TOTAL | D50: R7 | E50: =SUM(E46:E49) -> 225 | F50: =SUM(F46:F49) -> 293 | G50: =SUM(G46:G49) -> 177 | H50: =SUM(H46:H49) -> 20 | I50: =SUM(I46:I49) -> 6 | J50: =SUM(J46:J49) -> 157 | L50: =SUM(L46:L49) -> 7425000 | M50: =SUM(M46:M49) -> 8322873 | N50: =SUM(N46:N49) -> 882864.41 | O50: =SUM(O46:O49) -> 6170417.8 | S50: =SUM(S46:S49) -> 109717.4 | T50: =SUM(T46:T49) -> 0 | U50: =SUM(U46:U49) -> 0 | V50: =SUM(V46:V49) -> 0 | W50: =SUM(W46:W49) -> 0 | X50: =SUM(X46:X49) -> 225 | Y50: =SUM(Y46:Y49) -> 157 | Z50: =SUM(Z46:Z49) -> 0.69777778 | ... AF50: =SUM(AF46:AF49) -> 109717.4 | AI50: TOTAL | AK50: R7 | AL50: 141900.49 | AM50: =SUM(AM46:AM49) -> 109717.4 | AN50: =SUM(AN46:AN49) -> 32183.087
A51: Tauseef Ansari | B51: NHP581 | C51: RM | D51: R8 | E51: =ROUND(SUMIF('Target Achieved- Input'!$B$2:$B$90,'Incentive Report- Output'!B51,'Target Achieved- Input'!$G$2:$G$90),0) -> 70 | F51: =ROUND(SUMIF('Target Achieved- Input'!$B$2:$B$90,'Incentive Report- Output'!B51,'Target Achieved- Input'!$H$2:$H$90),0) -> 91 | G51: =SUMIF('Target Achieved- Input'!$L$2:$L$90,'Incentive Report- Output'!B51,'Target Achieved- Input'!$O$2:$O$90) -> 24 | H51: =SUMIF('Target Achieved- Input'!$S$2:$S$90,'Incentive Report- Output'!B51,'Target Achieved- Input'!$V$2:$V$90) -> 7 | I51: =SUMIF('Target Achieved- Input'!$L$2:$L$90,'Incentive Report- Output'!B51,'Target Achieved- Input'!$AC$2:$AC$90) -> 1 | J51: =G51-H51 -> 17 | K51: =IFERROR(J51/E51,0) -> 0.24285714 | L51: =E51*33000 -> 2310000 | M51: =SUMIF('Target Achieved- Input'!$L$2:$L$90,'Incentive Report- Output'!B51,'Target Achieved- Input'!$M$2:$M$90) -> 1100626 | N51: =SUMIF('Target Achieved- Input'!$S$2:$S$90,'Incentive Report- Output'!B51,'Target Achieved- Input'!$U$2:$U$90) -> 279019.49 | O51: =SUMIF('Target Achieved- Input'!$L$2:$L$90,'Incentive Report- Output'!B51,'Target Achieved- Input'!$N$2:$N$90)-N51 -> 653714.41 | P51: =IFERROR(O51/L51,0) -> 0.28299325 | Q51: =MAX(P51,K51) -> 0.28299325 | R51: 0 | S51: =(LOOKUP(Q51,Policy!$L$12:$M$16)+R51)*O51 -> 0 | AA51: 0 | AB51: 0 | AC51: 0 | AD51: =IF(AF51>200000,AF51-200000,0) -> 0 | AE51: =AF51-AD51 -> 0 | AF51: =S51+W51+AB51+AC51 -> 0 | AI51: Tauseef Ansari | AJ51: NHP581 | AK51: R8 | AL51: 0 | AM51: =AF51 -> 0 | AN51: =AL51-AM51 -> 0
A52: Wayne Camilo | B52: NHP377 | C52: BDE | D52: R8 | E52: =ROUND(SUMIF('Target Achieved- Input'!$B$2:$B$90,'Incentive Report- Output'!B52,'Target Achieved- Input'!$G$2:$G$90),0) -> 70 | F52: =ROUND(SUMIF('Target Achieved- Input'!$B$2:$B$90,'Incentive Report- Output'!B52,'Target Achieved- Input'!$H$2:$H$90),0) -> 91 | G52: =SUMIF('Target Achieved- Input'!$L$2:$L$90,'Incentive Report- Output'!B52,'Target Achieved- Input'!$O$2:$O$90) -> 23 | H52: =SUMIF('Target Achieved- Input'!$S$2:$S$90,'Incentive Report- Output'!B52,'Target Achieved- Input'!$V$2:$V$90) -> 16 | I52: =SUMIF('Target Achieved- Input'!$L$2:$L$90,'Incentive Report- Output'!B52,'Target Achieved- Input'!$AC$2:$AC$90) -> 2 | J52: =G52-H52 -> 7 | K52: =IFERROR(J52/E52,0) -> 0.1 | L52: =E52*33000 -> 2310000 | M52: =SUMIF('Target Achieved- Input'!$L$2:$L$90,'Incentive Report- Output'!B52,'Target Achieved- Input'!$M$2:$M$90) -> 929977 | N52: =SUMIF('Target Achieved- Input'!$S$2:$S$90,'Incentive Report- Output'!B52,'Target Achieved- Input'!$U$2:$U$90) -> 550833.9 | O52: =SUMIF('Target Achieved- Input'!$L$2:$L$90,'Incentive Report- Output'!B52,'Target Achieved- Input'!$N$2:$N$90)-N52 -> 237282.2 | P52: =IFERROR(O52/L52,0) -> 0.10271957 | Q52: =MAX(P52,K52) -> 0.10271957 | R52: 0 | S52: =(LOOKUP(Q52,Policy!$L$12:$M$16)+R52)*O52 -> 0 | AA52: 0 | AB52: 0 | AC52: 0 | AD52: =IF(AF52>200000,AF52-200000,0) -> 0 | AE52: =AF52-AD52 -> 0 | AF52: =S52+W52+AB52+AC52 -> 0 | AI52: Wayne Camilo | AJ52: NHP377 | AK52: R8 | AL52: 0 | AM52: =AF52 -> 0 | AN52: =AL52-AM52 -> 0
A53: Akshay Grover | B53: NHP818 | C53: BDE | D53: R8 | E53: =ROUND(SUMIF('Target Achieved- Input'!$B$2:$B$90,'Incentive Report- Output'!B53,'Target Achieved- Input'!$G$2:$G$90),0) -> 46 | F53: =ROUND(SUMIF('Target Achieved- Input'!$B$2:$B$90,'Incentive Report- Output'!B53,'Target Achieved- Input'!$H$2:$H$90),0) -> 60 | G53: =SUMIF('Target Achieved- Input'!$L$2:$L$90,'Incentive Report- Output'!B53,'Target Achieved- Input'!$O$2:$O$90) -> 32 | H53: =SUMIF('Target Achieved- Input'!$S$2:$S$90,'Incentive Report- Output'!B53,'Target Achieved- Input'!$V$2:$V$90) -> 6 | I53: =SUMIF('Target Achieved- Input'!$L$2:$L$90,'Incentive Report- Output'!B53,'Target Achieved- Input'!$AC$2:$AC$90) -> 4 | J53: =G53-H53 -> 26 | K53: =IFERROR(J53/E53,0) -> 0.56521739 | L53: =E53*33000 -> 1518000 | M53: =SUMIF('Target Achieved- Input'!$L$2:$L$90,'Incentive Report- Output'!B53,'Target Achieved- Input'!$M$2:$M$90) -> 1590718 | N53: =SUMIF('Target Achieved- Input'!$S$2:$S$90,'Incentive Report- Output'!B53,'Target Achieved- Input'!$U$2:$U$90) -> 296605.08 | O53: =SUMIF('Target Achieved- Input'!$L$2:$L$90,'Incentive Report- Output'!B53,'Target Achieved- Input'!$N$2:$N$90)-N53 -> 1051461 | P53: =IFERROR(O53/L53,0) -> 0.69266207 | Q53: =MAX(P53,K53) -> 0.69266207 | R53: 0 | S53: =(LOOKUP(Q53,Policy!$L$12:$M$16)+R53)*O53 -> 5257.3051 | AA53: 0 | AB53: 0 | AC53: 0 | AD53: =IF(AF53>200000,AF53-200000,0) -> 0 | AE53: =AF53-AD53 -> 5257.3051 | AF53: =S53+W53+AB53+AC53 -> 5257.3051 | AI53: Akshay Grover | AJ53: NHP818 | AK53: R8 | AL53: 13480.661 | AM53: =AF53 -> 5257.3051 | AN53: =AL53-AM53 -> 8223.3559
A54: Prajwal Ghodke | B54: NHP608 | C54: BDE | D54: R8 | E54: =ROUND(SUMIF('Target Achieved- Input'!$B$2:$B$90,'Incentive Report- Output'!B54,'Target Achieved- Input'!$G$2:$G$90),0) -> 70 | F54: =ROUND(SUMIF('Target Achieved- Input'!$B$2:$B$90,'Incentive Report- Output'!B54,'Target Achieved- Input'!$H$2:$H$90),0) -> 91 | G54: =SUMIF('Target Achieved- Input'!$L$2:$L$90,'Incentive Report- Output'!B54,'Target Achieved- Input'!$O$2:$O$90) -> 45 | H54: =SUMIF('Target Achieved- Input'!$S$2:$S$90,'Incentive Report- Output'!B54,'Target Achieved- Input'!$V$2:$V$90) -> 21 | I54: =SUMIF('Target Achieved- Input'!$L$2:$L$90,'Incentive Report- Output'!B54,'Target Achieved- Input'!$AC$2:$AC$90) -> 3 | J54: =G54-H54 -> 24 | K54: =IFERROR(J54/E54,0) -> 0.34285714 | L54: =E54*33000 -> 2310000 | M54: =SUMIF('Target Achieved- Input'!$L$2:$L$90,'Incentive Report- Output'!B54,'Target Achieved- Input'!$M$2:$M$90) -> 2056855 | N54: =SUMIF('Target Achieved- Input'!$S$2:$S$90,'Incentive Report- Output'!B54,'Target Achieved- Input'!$U$2:$U$90) -> 812651.69 | O54: =SUMIF('Target Achieved- Input'!$L$2:$L$90,'Incentive Report- Output'!B54,'Target Achieved- Input'!$N$2:$N$90)-N54 -> 930445.76 | P54: =IFERROR(O54/L54,0) -> 0.40279037 | Q54: =MAX(P54,K54) -> 0.40279037 | R54: 0 | S54: =(LOOKUP(Q54,Policy!$L$12:$M$16)+R54)*O54 -> 0 | AA54: 0 | AB54: 0 | AC54: 0 | AD54: =IF(AF54>200000,AF54-200000,0) -> 0 | AE54: =AF54-AD54 -> 0 | AF54: =S54+W54+AB54+AC54 -> 0 | AI54: Prajwal Ghodke | AJ54: NHP608 | AK54: R8 | AL54: 8715.4873 | AM54: =AF54 -> 0 | AN54: =AL54-AM54 -> 8715.4873
A55: TOTAL | D55: R8 | E55: =SUM(E51:E54) -> 256 | F55: =SUM(F51:F54) -> 333 | G55: =SUM(G51:G54) -> 124 | H55: =SUM(H51:H54) -> 50 | I55: =SUM(I51:I54) -> 10 | J55: =SUM(J51:J54) -> 74 | L55: =SUM(L51:L54) -> 8448000 | M55: =SUM(M51:M54) -> 5678176 | N55: =SUM(N51:N54) -> 1939110.2 | O55: =SUM(O51:O54) -> 2872903.4 | S55: =SUM(S51:S54) -> 5257.3051 | T55: =SUM(T51:T54) -> 0 | U55: =SUM(U51:U54) -> 0 | V55: =SUM(V51:V54) -> 0 | W55: =SUM(W51:W54) -> 0 | X55: =SUM(X51:X54) -> 0 | Y55: =SUM(Y51:Y54) -> 0 | Z55: =SUM(Z51:Z54) -> 0 | ... AF55: =SUM(AF51:AF54) -> 5257.3051 | AI55: TOTAL | AK55: R8 | AL55: 22196.148 | AM55: =SUM(AM51:AM54) -> 5257.3051 | AN55: =SUM(AN51:AN54) -> 16938.843
A56: Ajay Kumar | B56: NHP138 | C56: RM | D56: R9 | E56: =ROUND(SUMIF('Target Achieved- Input'!$B$2:$B$90,'Incentive Report- Output'!B56,'Target Achieved- Input'!$G$2:$G$90),0) -> 60 | F56: =ROUND(SUMIF('Target Achieved- Input'!$B$2:$B$90,'Incentive Report- Output'!B56,'Target Achieved- Input'!$H$2:$H$90),0) -> 78 | G56: =SUMIF('Target Achieved- Input'!$L$2:$L$90,'Incentive Report- Output'!B56,'Target Achieved- Input'!$O$2:$O$90) -> 27 | H56: =SUMIF('Target Achieved- Input'!$S$2:$S$90,'Incentive Report- Output'!B56,'Target Achieved- Input'!$V$2:$V$90) -> 0 | I56: =SUMIF('Target Achieved- Input'!$L$2:$L$90,'Incentive Report- Output'!B56,'Target Achieved- Input'!$AC$2:$AC$90) -> 6 | J56: =G56-H56 -> 27 | K56: =IFERROR(J56/E56,0) -> 0.45 | L56: =E56*33000 -> 1980000 | M56: =SUMIF('Target Achieved- Input'!$L$2:$L$90,'Incentive Report- Output'!B56,'Target Achieved- Input'!$M$2:$M$90) -> 1085223 | N56: =SUMIF('Target Achieved- Input'!$S$2:$S$90,'Incentive Report- Output'!B56,'Target Achieved- Input'!$U$2:$U$90) -> 0 | O56: =SUMIF('Target Achieved- Input'!$L$2:$L$90,'Incentive Report- Output'!B56,'Target Achieved- Input'!$N$2:$N$90)-N56 -> 919680.51 | P56: =IFERROR(O56/L56,0) -> 0.46448511 | Q56: =MAX(P56,K56) -> 0.46448511 | R56: 0 | S56: =(LOOKUP(Q56,Policy!$L$12:$M$16)+R56)*O56 -> 0 | X56: =E59 -> 176 | Y56: =J59 -> 120 | Z56: =Y56/X56 -> 0.68181818 | AA56: 0 | AB56: 0 | AC56: 0 | AD56: =IF(AF56>200000,AF56-200000,0) -> 0 | AE56: =AF56-AD56 -> 0 | AF56: =S56+W56+AB56+AC56 -> 0 | AI56: Ajay Kumar | AJ56: NHP138 | AK56: R9 | AL56: 0 | AM56: =AF56 -> 0 | AN56: =AL56-AM56 -> 0
A57: Praveen Raj | B57: NHP158 | C57: BDE | D57: R9 | E57: =ROUND(SUMIF('Target Achieved- Input'!$B$2:$B$90,'Incentive Report- Output'!B57,'Target Achieved- Input'!$G$2:$G$90),0) -> 70 | F57: =ROUND(SUMIF('Target Achieved- Input'!$B$2:$B$90,'Incentive Report- Output'!B57,'Target Achieved- Input'!$H$2:$H$90),0) -> 91 | G57: =SUMIF('Target Achieved- Input'!$L$2:$L$90,'Incentive Report- Output'!B57,'Target Achieved- Input'!$O$2:$O$90) -> 68 | H57: =SUMIF('Target Achieved- Input'!$S$2:$S$90,'Incentive Report- Output'!B57,'Target Achieved- Input'!$V$2:$V$90) -> 0 | I57: =SUMIF('Target Achieved- Input'!$L$2:$L$90,'Incentive Report- Output'!B57,'Target Achieved- Input'!$AC$2:$AC$90) -> 4 | J57: =G57-H57 -> 68 | K57: =IFERROR(J57/E57,0) -> 0.97142857 | L57: =E57*33000 -> 2310000 | M57: =SUMIF('Target Achieved- Input'!$L$2:$L$90,'Incentive Report- Output'!B57,'Target Achieved- Input'!$M$2:$M$90) -> 2746982 | N57: =SUMIF('Target Achieved- Input'!$S$2:$S$90,'Incentive Report- Output'!B57,'Target Achieved- Input'!$U$2:$U$90) -> 0 | O57: =SUMIF('Target Achieved- Input'!$L$2:$L$90,'Incentive Report- Output'!B57,'Target Achieved- Input'!$N$2:$N$90)-N57 -> 2327950.8 | P57: =IFERROR(O57/L57,0) -> 1.0077709 | Q57: =MAX(P57,K57) -> 1.0077709 | R57: 0 | S57: =(LOOKUP(Q57,Policy!$L$12:$M$16)+R57)*O57 -> 52378.894 | AA57: 0 | AB57: 0 | AC57: 0 | AD57: =IF(AF57>200000,AF57-200000,0) -> 0 | AE57: =AF57-AD57 -> 52378.894 | AF57: =S57+W57+AB57+AC57 -> 52378.894 | AI57: Praveen Raj | AJ57: NHP158 | AK57: R9 | AL57: 52378.894 | AM57: =AF57 -> 52378.894 | AN57: =AL57-AM57 -> 0
A58: Shreekrishna Kulkarni | B58: NHP827 | C58: BDE | D58: R9 | E58: =ROUND(SUMIF('Target Achieved- Input'!$B$2:$B$90,'Incentive Report- Output'!B58,'Target Achieved- Input'!$G$2:$G$90),0) -> 46 | F58: =ROUND(SUMIF('Target Achieved- Input'!$B$2:$B$90,'Incentive Report- Output'!B58,'Target Achieved- Input'!$H$2:$H$90),0) -> 60 | G58: =SUMIF('Target Achieved- Input'!$L$2:$L$90,'Incentive Report- Output'!B58,'Target Achieved- Input'!$O$2:$O$90) -> 31 | H58: =SUMIF('Target Achieved- Input'!$S$2:$S$90,'Incentive Report- Output'!B58,'Target Achieved- Input'!$V$2:$V$90) -> 6 | I58: =SUMIF('Target Achieved- Input'!$L$2:$L$90,'Incentive Report- Output'!B58,'Target Achieved- Input'!$AC$2:$AC$90) -> 0 | J58: =G58-H58 -> 25 | K58: =IFERROR(J58/E58,0) -> 0.54347826 | L58: =E58*33000 -> 1518000 | M58: =SUMIF('Target Achieved- Input'!$L$2:$L$90,'Incentive Report- Output'!B58,'Target Achieved- Input'!$M$2:$M$90) -> 1738769 | N58: =SUMIF('Target Achieved- Input'!$S$2:$S$90,'Incentive Report- Output'!B58,'Target Achieved- Input'!$U$2:$U$90) -> 253384.75 | O58: =SUMIF('Target Achieved- Input'!$L$2:$L$90,'Incentive Report- Output'!B58,'Target Achieved- Input'!$N$2:$N$90)-N58 -> 1220148.3 | P58: =IFERROR(O58/L58,0) -> 0.80378676 | Q58: =MAX(P58,K58) -> 0.80378676 | R58: 0 | S58: =(LOOKUP(Q58,Policy!$L$12:$M$16)+R58)*O58 -> 12201.483 | AA58: 0 | AB58: 0 | AC58: 0 | AD58: =IF(AF58>200000,AF58-200000,0) -> 0 | AE58: =AF58-AD58 -> 12201.483 | AF58: =S58+W58+AB58+AC58 -> 12201.483 | AI58: Shreekrishna Kulkarni | AJ58: NHP827 | AK58: R9 | AL58: 14735.331 | AM58: =AF58 -> 12201.483 | AN58: =AL58-AM58 -> 2533.8475
A59: TOTAL | D59: R9 | E59: =SUM(E56:E58) -> 176 | F59: =SUM(F56:F58) -> 229 | G59: =SUM(G56:G58) -> 126 | H59: =SUM(H56:H58) -> 6 | I59: =SUM(I56:I58) -> 10 | J59: =SUM(J56:J58) -> 120 | L59: =SUM(L56:L58) -> 5808000 | M59: =SUM(M56:M58) -> 5570974 | N59: =SUM(N56:N58) -> 253384.75 | O59: =SUM(O56:O58) -> 4467779.7 | S59: =SUM(S56:S58) -> 64580.377 | T59: =SUM(T56:T58) -> 0 | U59: =SUM(U56:U58) -> 0 | V59: =SUM(V56:V58) -> 0 | W59: =SUM(W56:W58) -> 0 | X59: =SUM(X56:X58) -> 176 | Y59: =SUM(Y56:Y58) -> 120 | Z59: =SUM(Z56:Z58) -> 0.68181818 | ... AF59: =SUM(AF56:AF58) -> 64580.377 | AI59: TOTAL | AK59: R9 | AL59: 67114.225 | AM59: =SUM(AM56:AM58) -> 64580.377 | AN59: =SUM(AN56:AN58) -> 2533.8475
A60: Sukanthan PK | B60: NHP157 | C60: RM | D60: R10 | E60: =ROUND(SUMIF('Target Achieved- Input'!$B$2:$B$90,'Incentive Report- Output'!B60,'Target Achieved- Input'!$G$2:$G$90),0) -> 50 | F60: =ROUND(SUMIF('Target Achieved- Input'!$B$2:$B$90,'Incentive Report- Output'!B60,'Target Achieved- Input'!$H$2:$H$90),0) -> 65 | G60: =SUMIF('Target Achieved- Input'!$L$2:$L$90,'Incentive Report- Output'!B60,'Target Achieved- Input'!$O$2:$O$90) -> 20 | H60: =SUMIF('Target Achieved- Input'!$S$2:$S$90,'Incentive Report- Output'!B60,'Target Achieved- Input'!$V$2:$V$90) -> 6 | I60: =SUMIF('Target Achieved- Input'!$L$2:$L$90,'Incentive Report- Output'!B60,'Target Achieved- Input'!$AC$2:$AC$90) -> 3 | J60: =G60-H60 -> 14 | K60: =IFERROR(J60/E60,0) -> 0.28 | L60: =E60*33000 -> 1650000 | M60: =SUMIF('Target Achieved- Input'!$L$2:$L$90,'Incentive Report- Output'!B60,'Target Achieved- Input'!$M$2:$M$90) -> 780080 | N60: =SUMIF('Target Achieved- Input'!$S$2:$S$90,'Incentive Report- Output'!B60,'Target Achieved- Input'!$U$2:$U$90) -> 246605.08 | O60: =SUMIF('Target Achieved- Input'!$L$2:$L$90,'Incentive Report- Output'!B60,'Target Achieved- Input'!$N$2:$N$90)-N60 -> 414479.66 | P60: =IFERROR(O60/L60,0) -> 0.25119979 | Q60: =MAX(P60,K60) -> 0.28 | R60: 0 | S60: =(LOOKUP(Q60,Policy!$L$12:$M$16)+R60)*O60 -> 0 | X60: =E67 -> 360 | Y60: =J67 -> 105 | Z60: =Y60/X60 -> 0.29166667 | AA60: 0 | AB60: 0 | AC60: 0 | AD60: =IF(AF60>200000,AF60-200000,0) -> 0 | AE60: =AF60-AD60 -> 0 | AF60: =S60+W60+AB60+AC60 -> 0 | AI60: Sukanthan PK | AJ60: NHP157 | AK60: R10 | AL60: 0 | AM60: =AF60 -> 0 | AN60: =AL60-AM60 -> 0
A61: Ajmal Shan | B61: NHP683 | C61: BDE | D61: R10 | E61: =ROUND(SUMIF('Target Achieved- Input'!$B$2:$B$90,'Incentive Report- Output'!B61,'Target Achieved- Input'!$G$2:$G$90),0) -> 55 | F61: =ROUND(SUMIF('Target Achieved- Input'!$B$2:$B$90,'Incentive Report- Output'!B61,'Target Achieved- Input'!$H$2:$H$90),0) -> 72 | G61: =SUMIF('Target Achieved- Input'!$L$2:$L$90,'Incentive Report- Output'!B61,'Target Achieved- Input'!$O$2:$O$90) -> 16 | H61: =SUMIF('Target Achieved- Input'!$S$2:$S$90,'Incentive Report- Output'!B61,'Target Achieved- Input'!$V$2:$V$90) -> 5 | I61: =SUMIF('Target Achieved- Input'!$L$2:$L$90,'Incentive Report- Output'!B61,'Target Achieved- Input'!$AC$2:$AC$90) -> 2 | J61: =G61-H61 -> 11 | K61: =IFERROR(J61/E61,0) -> 0.2 | L61: =E61*33000 -> 1815000 | M61: =SUMIF('Target Achieved- Input'!$L$2:$L$90,'Incentive Report- Output'!B61,'Target Achieved- Input'!$M$2:$M$90) -> 671434 | N61: =SUMIF('Target Achieved- Input'!$S$2:$S$90,'Incentive Report- Output'!B61,'Target Achieved- Input'!$U$2:$U$90) -> 153766.95 | O61: =SUMIF('Target Achieved- Input'!$L$2:$L$90,'Incentive Report- Output'!B61,'Target Achieved- Input'!$N$2:$N$90)-N61 -> 415244.92 | P61: =IFERROR(O61/L61,0) -> 0.22878508 | Q61: =MAX(P61,K61) -> 0.22878508 | R61: 0 | S61: =(LOOKUP(Q61,Policy!$L$12:$M$16)+R61)*O61 -> 0 | AA61: 0 | AB61: 0 | AC61: 0 | AD61: =IF(AF61>200000,AF61-200000,0) -> 0 | AE61: =AF61-AD61 -> 0 | AF61: =S61+W61+AB61+AC61 -> 0 | AI61: Ajmal Shan | AJ61: NHP683 | AK61: R10 | AL61: 0 | AM61: =AF61 -> 0 | AN61: =AL61-AM61 -> 0
A62: Sachin V Nair | B62: NHP159 | C62: BDE | D62: R10 | E62: =ROUND(SUMIF('Target Achieved- Input'!$B$2:$B$90,'Incentive Report- Output'!B62,'Target Achieved- Input'!$G$2:$G$90),0) -> 50 | F62: =ROUND(SUMIF('Target Achieved- Input'!$B$2:$B$90,'Incentive Report- Output'!B62,'Target Achieved- Input'!$H$2:$H$90),0) -> 65 | G62: =SUMIF('Target Achieved- Input'!$L$2:$L$90,'Incentive Report- Output'!B62,'Target Achieved- Input'!$O$2:$O$90) -> 10 | H62: =SUMIF('Target Achieved- Input'!$S$2:$S$90,'Incentive Report- Output'!B62,'Target Achieved- Input'!$V$2:$V$90) -> 5 | I62: =SUMIF('Target Achieved- Input'!$L$2:$L$90,'Incentive Report- Output'!B62,'Target Achieved- Input'!$AC$2:$AC$90) -> 0 | J62: =G62-H62 -> 5 | K62: =IFERROR(J62/E62,0) -> 0.1 | L62: =E62*33000 -> 1650000 | M62: =SUMIF('Target Achieved- Input'!$L$2:$L$90,'Incentive Report- Output'!B62,'Target Achieved- Input'!$M$2:$M$90) -> 476090 | N62: =SUMIF('Target Achieved- Input'!$S$2:$S$90,'Incentive Report- Output'!B62,'Target Achieved- Input'!$U$2:$U$90) -> 218470.34 | O62: =SUMIF('Target Achieved- Input'!$L$2:$L$90,'Incentive Report- Output'!B62,'Target Achieved- Input'!$N$2:$N$90)-N62 -> 184995.76 | P62: =IFERROR(O62/L62,0) -> 0.11211864 | Q62: =MAX(P62,K62) -> 0.11211864 | R62: 0 | S62: =(LOOKUP(Q62,Policy!$L$12:$M$16)+R62)*O62 -> 0 | AA62: 0 | AB62: 0 | AC62: 0 | AD62: =IF(AF62>200000,AF62-200000,0) -> 0 | AE62: =AF62-AD62 -> 0 | AF62: =S62+W62+AB62+AC62 -> 0 | AI62: Sachin V Nair | AJ62: NHP159 | AK62: R10 | AL62: 0 | AM62: =AF62 -> 0 | AN62: =AL62-AM62 -> 0
A63: Sudharsan Raja R | B63: NHP744 | C63: BDE | D63: R10 | E63: =ROUND(SUMIF('Target Achieved- Input'!$B$2:$B$90,'Incentive Report- Output'!B63,'Target Achieved- Input'!$G$2:$G$90),0) -> 55 | F63: =ROUND(SUMIF('Target Achieved- Input'!$B$2:$B$90,'Incentive Report- Output'!B63,'Target Achieved- Input'!$H$2:$H$90),0) -> 72 | G63: =SUMIF('Target Achieved- Input'!$L$2:$L$90,'Incentive Report- Output'!B63,'Target Achieved- Input'!$O$2:$O$90) -> 18 | H63: =SUMIF('Target Achieved- Input'!$S$2:$S$90,'Incentive Report- Output'!B63,'Target Achieved- Input'!$V$2:$V$90) -> 7 | I63: =SUMIF('Target Achieved- Input'!$L$2:$L$90,'Incentive Report- Output'!B63,'Target Achieved- Input'!$AC$2:$AC$90) -> 0 | J63: =G63-H63 -> 11 | K63: =IFERROR(J63/E63,0) -> 0.2 | L63: =E63*33000 -> 1815000 | M63: =SUMIF('Target Achieved- Input'!$L$2:$L$90,'Incentive Report- Output'!B63,'Target Achieved- Input'!$M$2:$M$90) -> 942982 | N63: =SUMIF('Target Achieved- Input'!$S$2:$S$90,'Incentive Report- Output'!B63,'Target Achieved- Input'!$U$2:$U$90) -> 321180.51 | O63: =SUMIF('Target Achieved- Input'!$L$2:$L$90,'Incentive Report- Output'!B63,'Target Achieved- Input'!$N$2:$N$90)-N63 -> 477956.78 | P63: =IFERROR(O63/L63,0) -> 0.26333707 | Q63: =MAX(P63,K63) -> 0.26333707 | R63: 0 | S63: =(LOOKUP(Q63,Policy!$L$12:$M$16)+R63)*O63 -> 0 | AA63: 0 | AB63: 0 | AC63: 0 | AD63: =IF(AF63>200000,AF63-200000,0) -> 0 | AE63: =AF63-AD63 -> 0 | AF63: =S63+W63+AB63+AC63 -> 0 | AI63: Sudharsan Raja R | AJ63: NHP744 | AK63: R10 | AL63: 0 | AM63: =AF63 -> 0 | AN63: =AL63-AM63 -> 0
A64: Ushaswini K | B64: NHP681 | C64: BDE | D64: R10 | E64: =ROUND(SUMIF('Target Achieved- Input'!$B$2:$B$90,'Incentive Report- Output'!B64,'Target Achieved- Input'!$G$2:$G$90),0) -> 60 | F64: =ROUND(SUMIF('Target Achieved- Input'!$B$2:$B$90,'Incentive Report- Output'!B64,'Target Achieved- Input'!$H$2:$H$90),0) -> 78 | G64: =SUMIF('Target Achieved- Input'!$L$2:$L$90,'Incentive Report- Output'!B64,'Target Achieved- Input'!$O$2:$O$90) -> 43 | H64: =SUMIF('Target Achieved- Input'!$S$2:$S$90,'Incentive Report- Output'!B64,'Target Achieved- Input'!$V$2:$V$90) -> 0 | I64: =SUMIF('Target Achieved- Input'!$L$2:$L$90,'Incentive Report- Output'!B64,'Target Achieved- Input'!$AC$2:$AC$90) -> 1 | J64: =G64-H64 -> 43 | K64: =IFERROR(J64/E64,0) -> 0.71666667 | L64: =E64*33000 -> 1980000 | M64: =SUMIF('Target Achieved- Input'!$L$2:$L$90,'Incentive Report- Output'!B64,'Target Achieved- Input'!$M$2:$M$90) -> 2153357 | N64: =SUMIF('Target Achieved- Input'!$S$2:$S$90,'Incentive Report- Output'!B64,'Target Achieved- Input'!$U$2:$U$90) -> 0 | O64: =SUMIF('Target Achieved- Input'!$L$2:$L$90,'Incentive Report- Output'!B64,'Target Achieved- Input'!$N$2:$N$90)-N64 -> 1824878.8 | P64: =IFERROR(O64/L64,0) -> 0.92165597 | Q64: =MAX(P64,K64) -> 0.92165597 | R64: 0 | S64: =(LOOKUP(Q64,Policy!$L$12:$M$16)+R64)*O64 -> 18248.788 | AA64: 0 | AB64: 0 | AC64: 0 | AD64: =IF(AF64>200000,AF64-200000,0) -> 0 | AE64: =AF64-AD64 -> 18248.788 | AF64: =S64+W64+AB64+AC64 -> 18248.788 | AI64: Ushaswini K | AJ64: NHP681 | AK64: R10 | AL64: 18248.788 | AM64: =AF64 -> 18248.788 | AN64: =AL64-AM64 -> 0
A65: Anoof | B65: NHP668 | C65: BDE | D65: R10 | E65: =ROUND(SUMIF('Target Achieved- Input'!$B$2:$B$90,'Incentive Report- Output'!B65,'Target Achieved- Input'!$G$2:$G$90),0) -> 40 | F65: =ROUND(SUMIF('Target Achieved- Input'!$B$2:$B$90,'Incentive Report- Output'!B65,'Target Achieved- Input'!$H$2:$H$90),0) -> 52 | G65: =SUMIF('Target Achieved- Input'!$L$2:$L$90,'Incentive Report- Output'!B65,'Target Achieved- Input'!$O$2:$O$90) -> 11 | H65: =SUMIF('Target Achieved- Input'!$S$2:$S$90,'Incentive Report- Output'!B65,'Target Achieved- Input'!$V$2:$V$90) -> 5 | I65: =SUMIF('Target Achieved- Input'!$L$2:$L$90,'Incentive Report- Output'!B65,'Target Achieved- Input'!$AC$2:$AC$90) -> 2 | J65: =G65-H65 -> 6 | K65: =IFERROR(J65/E65,0) -> 0.15 | L65: =E65*33000 -> 1320000 | M65: =SUMIF('Target Achieved- Input'!$L$2:$L$90,'Incentive Report- Output'!B65,'Target Achieved- Input'!$M$2:$M$90) -> 446439 | N65: =SUMIF('Target Achieved- Input'!$S$2:$S$90,'Incentive Report- Output'!B65,'Target Achieved- Input'!$U$2:$U$90) -> 207326.27 | O65: =SUMIF('Target Achieved- Input'!$L$2:$L$90,'Incentive Report- Output'!B65,'Target Achieved- Input'!$N$2:$N$90)-N65 -> 171011.86 | P65: =IFERROR(O65/L65,0) -> 0.12955444 | Q65: =MAX(P65,K65) -> 0.15 | R65: 0 | S65: =(LOOKUP(Q65,Policy!$L$12:$M$16)+R65)*O65 -> 0 | AA65: 0 | AB65: 0 | AC65: 0 | AD65: =IF(AF65>200000,AF65-200000,0) -> 0 | AE65: =AF65-AD65 -> 0 | AF65: =S65+W65+AB65+AC65 -> 0 | AI65: Anoof | AJ65: NHP668 | AK65: R10 | AL65: 0 | AM65: =AF65 -> 0 | AN65: =AL65-AM65 -> 0
A66: Arundas Aravind | B66: NHP782 | C66: BDE | D66: R10 | E66: =ROUND(SUMIF('Target Achieved- Input'!$B$2:$B$90,'Incentive Report- Output'!B66,'Target Achieved- Input'!$G$2:$G$90),0) -> 50 | F66: =ROUND(SUMIF('Target Achieved- Input'!$B$2:$B$90,'Incentive Report- Output'!B66,'Target Achieved- Input'!$H$2:$H$90),0) -> 65 | G66: =SUMIF('Target Achieved- Input'!$L$2:$L$90,'Incentive Report- Output'!B66,'Target Achieved- Input'!$O$2:$O$90) -> 18 | H66: =SUMIF('Target Achieved- Input'!$S$2:$S$90,'Incentive Report- Output'!B66,'Target Achieved- Input'!$V$2:$V$90) -> 3 | I66: =SUMIF('Target Achieved- Input'!$L$2:$L$90,'Incentive Report- Output'!B66,'Target Achieved- Input'!$AC$2:$AC$90) -> 1 | J66: =G66-H66 -> 15 | K66: =IFERROR(J66/E66,0) -> 0.3 | L66: =E66*33000 -> 1650000 | M66: =SUMIF('Target Achieved- Input'!$L$2:$L$90,'Incentive Report- Output'!B66,'Target Achieved- Input'!$M$2:$M$90) -> 885732 | N66: =SUMIF('Target Achieved- Input'!$S$2:$S$90,'Incentive Report- Output'!B66,'Target Achieved- Input'!$U$2:$U$90) -> 172878.81 | O66: =SUMIF('Target Achieved- Input'!$L$2:$L$90,'Incentive Report- Output'!B66,'Target Achieved- Input'!$N$2:$N$90)-N66 -> 577741.53 | P66: =IFERROR(O66/L66,0) -> 0.35014638 | Q66: =MAX(P66,K66) -> 0.35014638 | R66: 0 | S66: =(LOOKUP(Q66,Policy!$L$12:$M$16)+R66)*O66 -> 0 | AA66: 0 | AB66: 0 | AC66: 0 | AD66: =IF(AF66>200000,AF66-200000,0) -> 0 | AE66: =AF66-AD66 -> 0 | AF66: =S66+W66+AB66+AC66 -> 0 | AI66: Arundas Aravind | AJ66: NHP782 | AK66: R10 | AL66: 0 | AM66: =AF66 -> 0 | AN66: =AL66-AM66 -> 0
A67: TOTAL | D67: R10 | E67: =SUM(E60:E66) -> 360 | F67: =SUM(F60:F66) -> 469 | G67: =SUM(G60:G66) -> 136 | H67: =SUM(H60:H66) -> 31 | I67: =SUM(I60:I66) -> 9 | J67: =SUM(J60:J66) -> 105 | L67: =SUM(L60:L66) -> 11880000 | M67: =SUM(M60:M66) -> 6356114 | N67: =SUM(N60:N66) -> 1320228 | O67: =SUM(O60:O66) -> 4066309.3 | S67: =SUM(S60:S66) -> 18248.788 | T67: =SUM(T60:T66) -> 0 | U67: =SUM(U60:U66) -> 0 | V67: =SUM(V60:V66) -> 0 | W67: =SUM(W60:W66) -> 0 | X67: =SUM(X60:X66) -> 360 | Y67: =SUM(Y60:Y66) -> 105 | Z67: =SUM(Z60:Z66) -> 0.29166667 | ... AF67: =SUM(AF60:AF66) -> 18248.788 | AI67: TOTAL | AK67: R10 | AL67: 18248.788 | AM67: =SUM(AM60:AM66) -> 18248.788 | AN67: =SUM(AN60:AN66) -> 0
A68: Srinivasan G | B68: NHP248 | C68: RM | D68: R11 | E68: =ROUND(SUMIF('Target Achieved- Input'!$B$2:$B$90,'Incentive Report- Output'!B68,'Target Achieved- Input'!$G$2:$G$90),0) -> 60 | F68: =ROUND(SUMIF('Target Achieved- Input'!$B$2:$B$90,'Incentive Report- Output'!B68,'Target Achieved- Input'!$H$2:$H$90),0) -> 78 | G68: =SUMIF('Target Achieved- Input'!$L$2:$L$90,'Incentive Report- Output'!B68,'Target Achieved- Input'!$O$2:$O$90) -> 41 | H68: =SUMIF('Target Achieved- Input'!$S$2:$S$90,'Incentive Report- Output'!B68,'Target Achieved- Input'!$V$2:$V$90) -> 13 | I68: =SUMIF('Target Achieved- Input'!$L$2:$L$90,'Incentive Report- Output'!B68,'Target Achieved- Input'!$AC$2:$AC$90) -> 1 | J68: =G68-H68 -> 28 | K68: =IFERROR(J68/E68,0) -> 0.46666667 | L68: =E68*33000 -> 1980000 | M68: =SUMIF('Target Achieved- Input'!$L$2:$L$90,'Incentive Report- Output'!B68,'Target Achieved- Input'!$M$2:$M$90) -> 2000309 | N68: =SUMIF('Target Achieved- Input'!$S$2:$S$90,'Incentive Report- Output'!B68,'Target Achieved- Input'!$U$2:$U$90) -> 543760.17 | O68: =SUMIF('Target Achieved- Input'!$L$2:$L$90,'Incentive Report- Output'!B68,'Target Achieved- Input'!$N$2:$N$90)-N68 -> 1151416.9 | P68: =IFERROR(O68/L68,0) -> 0.58152371 | Q68: =MAX(P68,K68) -> 0.58152371 | R68: 0 | S68: =(LOOKUP(Q68,Policy!$L$12:$M$16)+R68)*O68 -> 5757.0847 | AA68: 0 | AB68: 0 | AC68: 0 | AD68: =IF(AF68>200000,AF68-200000,0) -> 0 | AE68: =AF68-AD68 -> 5757.0847 | AF68: =S68+W68+AB68+AC68 -> 5757.0847 | AI68: Srinivasan G | AJ68: NHP248 | AK68: R11 | AL68: 16951.771 | AM68: =AF68 -> 5757.0847 | AN68: =AL68-AM68 -> 11194.686
A69: Aattreya Ravindran | B69: NHP785 | C69: BDE | D69: R11 | E69: =ROUND(SUMIF('Target Achieved- Input'!$B$2:$B$90,'Incentive Report- Output'!B69,'Target Achieved- Input'!$G$2:$G$90),0) -> 50 | F69: =ROUND(SUMIF('Target Achieved- Input'!$B$2:$B$90,'Incentive Report- Output'!B69,'Target Achieved- Input'!$H$2:$H$90),0) -> 65 | G69: =SUMIF('Target Achieved- Input'!$L$2:$L$90,'Incentive Report- Output'!B69,'Target Achieved- Input'!$O$2:$O$90) -> 24 | H69: =SUMIF('Target Achieved- Input'!$S$2:$S$90,'Incentive Report- Output'!B69,'Target Achieved- Input'!$V$2:$V$90) -> 13 | I69: =SUMIF('Target Achieved- Input'!$L$2:$L$90,'Incentive Report- Output'!B69,'Target Achieved- Input'!$AC$2:$AC$90) -> 4 | J69: =G69-H69 -> 11 | K69: =IFERROR(J69/E69,0) -> 0.22 | L69: =E69*33000 -> 1650000 | M69: =SUMIF('Target Achieved- Input'!$L$2:$L$90,'Incentive Report- Output'!B69,'Target Achieved- Input'!$M$2:$M$90) -> 1017626 | N69: =SUMIF('Target Achieved- Input'!$S$2:$S$90,'Incentive Report- Output'!B69,'Target Achieved- Input'!$U$2:$U$90) -> 493209.32 | O69: =SUMIF('Target Achieved- Input'!$L$2:$L$90,'Incentive Report- Output'!B69,'Target Achieved- Input'!$N$2:$N$90)-N69 -> 369185.59 | P69: =IFERROR(O69/L69,0) -> 0.22374884 | Q69: =MAX(P69,K69) -> 0.22374884 | R69: 0 | S69: =(LOOKUP(Q69,Policy!$L$12:$M$16)+R69)*O69 -> 0 | AA69: 0 | AB69: 0 | AC69: 0 | AD69: =IF(AF69>200000,AF69-200000,0) -> 0 | AE69: =AF69-AD69 -> 0 | AF69: =S69+W69+AB69+AC69 -> 0 | AI69: Aattreya Ravindran | AJ69: NHP785 | AK69: R11 | AL69: 4311.9746 | AM69: =AF69 -> 0 | AN69: =AL69-AM69 -> 4311.9746
A70: Hari Haran | B70: NHP552 | C70: BDE | D70: R11 | E70: =ROUND(SUMIF('Target Achieved- Input'!$B$2:$B$90,'Incentive Report- Output'!B70,'Target Achieved- Input'!$G$2:$G$90),0) -> 60 | F70: =ROUND(SUMIF('Target Achieved- Input'!$B$2:$B$90,'Incentive Report- Output'!B70,'Target Achieved- Input'!$H$2:$H$90),0) -> 78 | G70: =SUMIF('Target Achieved- Input'!$L$2:$L$90,'Incentive Report- Output'!B70,'Target Achieved- Input'!$O$2:$O$90) -> 36 | H70: =SUMIF('Target Achieved- Input'!$S$2:$S$90,'Incentive Report- Output'!B70,'Target Achieved- Input'!$V$2:$V$90) -> 0 | I70: =SUMIF('Target Achieved- Input'!$L$2:$L$90,'Incentive Report- Output'!B70,'Target Achieved- Input'!$AC$2:$AC$90) -> 2 | J70: =G70-H70 -> 36 | K70: =IFERROR(J70/E70,0) -> 0.6 | L70: =E70*33000 -> 1980000 | M70: =SUMIF('Target Achieved- Input'!$L$2:$L$90,'Incentive Report- Output'!B70,'Target Achieved- Input'!$M$2:$M$90) -> 1727714 | N70: =SUMIF('Target Achieved- Input'!$S$2:$S$90,'Incentive Report- Output'!B70,'Target Achieved- Input'!$U$2:$U$90) -> 0 | O70: =SUMIF('Target Achieved- Input'!$L$2:$L$90,'Incentive Report- Output'!B70,'Target Achieved- Input'!$N$2:$N$90)-N70 -> 1464164.4 | P70: =IFERROR(O70/L70,0) -> 0.73947697 | Q70: =MAX(P70,K70) -> 0.73947697 | R70: 0 | S70: =(LOOKUP(Q70,Policy!$L$12:$M$16)+R70)*O70 -> 7320.822 | AA70: 0 | AB70: 0 | AC70: 0 | AD70: =IF(AF70>200000,AF70-200000,0) -> 0 | AE70: =AF70-AD70 -> 7320.822 | AF70: =S70+W70+AB70+AC70 -> 7320.822 | AI70: Hari Haran | AJ70: NHP552 | AK70: R11 | AL70: 7320.822 | AM70: =AF70 -> 7320.822 | AN70: =AL70-AM70 -> 0
A71: Jeyaganesh Balaji | B71: NHP545 | C71: BDE | D71: R11 | E71: =ROUND(SUMIF('Target Achieved- Input'!$B$2:$B$90,'Incentive Report- Output'!B71,'Target Achieved- Input'!$G$2:$G$90),0) -> 50 | F71: =ROUND(SUMIF('Target Achieved- Input'!$B$2:$B$90,'Incentive Report- Output'!B71,'Target Achieved- Input'!$H$2:$H$90),0) -> 65 | G71: =SUMIF('Target Achieved- Input'!$L$2:$L$90,'Incentive Report- Output'!B71,'Target Achieved- Input'!$O$2:$O$90) -> 33 | H71: =SUMIF('Target Achieved- Input'!$S$2:$S$90,'Incentive Report- Output'!B71,'Target Achieved- Input'!$V$2:$V$90) -> 6 | I71: =SUMIF('Target Achieved- Input'!$L$2:$L$90,'Incentive Report- Output'!B71,'Target Achieved- Input'!$AC$2:$AC$90) -> 2 | J71: =G71-H71 -> 27 | K71: =IFERROR(J71/E71,0) -> 0.54 | L71: =E71*33000 -> 1650000 | M71: =SUMIF('Target Achieved- Input'!$L$2:$L$90,'Incentive Report- Output'!B71,'Target Achieved- Input'!$M$2:$M$90) -> 1541067 | N71: =SUMIF('Target Achieved- Input'!$S$2:$S$90,'Incentive Report- Output'!B71,'Target Achieved- Input'!$U$2:$U$90) -> 206477.97 | O71: =SUMIF('Target Achieved- Input'!$L$2:$L$90,'Incentive Report- Output'!B71,'Target Achieved- Input'!$N$2:$N$90)-N71 -> 1099511 | P71: =IFERROR(O71/L71,0) -> 0.66637031 | Q71: =MAX(P71,K71) -> 0.66637031 | R71: 0 | S71: =(LOOKUP(Q71,Policy!$L$12:$M$16)+R71)*O71 -> 5497.5551 | AA71: 0 | AB71: 0 | AC71: 0 | AD71: =IF(AF71>200000,AF71-200000,0) -> 0 | AE71: =AF71-AD71 -> 5497.5551 | AF71: =S71+W71+AB71+AC71 -> 5497.5551 | AI71: Jeyaganesh Balaji | AJ71: NHP545 | AK71: R11 | AL71: 6529.9449 | AM71: =AF71 -> 5497.5551 | AN71: =AL71-AM71 -> 1032.3898
A72: Nirmal Raj | B72: NHP380 | C72: SBM | D72: R11 | E72: =ROUND(SUMIF('Target Achieved- Input'!$B$2:$B$90,'Incentive Report- Output'!B72,'Target Achieved- Input'!$G$2:$G$90),0) -> 60 | F72: =ROUND(SUMIF('Target Achieved- Input'!$B$2:$B$90,'Incentive Report- Output'!B72,'Target Achieved- Input'!$H$2:$H$90),0) -> 78 | G72: =SUMIF('Target Achieved- Input'!$L$2:$L$90,'Incentive Report- Output'!B72,'Target Achieved- Input'!$O$2:$O$90) -> 65 | H72: =SUMIF('Target Achieved- Input'!$S$2:$S$90,'Incentive Report- Output'!B72,'Target Achieved- Input'!$V$2:$V$90) -> 9 | I72: =SUMIF('Target Achieved- Input'!$L$2:$L$90,'Incentive Report- Output'!B72,'Target Achieved- Input'!$AC$2:$AC$90) -> 4 | J72: =G72-H72 -> 56 | K72: =IFERROR(J72/E72,0) -> 0.93333333 | L72: =E72*33000 -> 1980000 | M72: =SUMIF('Target Achieved- Input'!$L$2:$L$90,'Incentive Report- Output'!B72,'Target Achieved- Input'!$M$2:$M$90) -> 3512535 | N72: =SUMIF('Target Achieved- Input'!$S$2:$S$90,'Incentive Report- Output'!B72,'Target Achieved- Input'!$U$2:$U$90) -> 391517.8 | O72: =SUMIF('Target Achieved- Input'!$L$2:$L$90,'Incentive Report- Output'!B72,'Target Achieved- Input'!$N$2:$N$90)-N72 -> 2585206.8 | P72: =IFERROR(O72/L72,0) -> 1.30566 | Q72: =MAX(P72,K72) -> 1.30566 | R72: 0 | S72: =(LOOKUP(Q72,Policy!$L$12:$M$16)+R72)*O72 -> 77556.203 | T72: =L70 -> 1980000 | U72: =O70 -> 1464164.4 | V72: =IFERROR(U72/T72,0) -> 0.73947697 | W72: =LOOKUP(V72,Policy!$L$18:$M$21)*U72 -> 0 | AA72: 0 | AB72: 0 | AC72: 0 | AD72: =IF(AF72>200000,AF72-200000,0) -> 0 | AE72: =AF72-AD72 -> 77556.203 | AF72: =S72+W72+AB72+AC72 -> 77556.203 | AI72: Nirmal Raj | AJ72: NHP380 | AK72: R11 | AL72: 89301.737 | AM72: =AF72 -> 77556.203 | AN72: =AL72-AM72 -> 11745.534
A73: Santhosh G | B73: NHP719 | C73: BDE | D73: R11 | E73: =ROUND(SUMIF('Target Achieved- Input'!$B$2:$B$90,'Incentive Report- Output'!B73,'Target Achieved- Input'!$G$2:$G$90),0) -> 55 | F73: =ROUND(SUMIF('Target Achieved- Input'!$B$2:$B$90,'Incentive Report- Output'!B73,'Target Achieved- Input'!$H$2:$H$90),0) -> 72 | G73: =SUMIF('Target Achieved- Input'!$L$2:$L$90,'Incentive Report- Output'!B73,'Target Achieved- Input'!$O$2:$O$90) -> 49 | H73: =SUMIF('Target Achieved- Input'!$S$2:$S$90,'Incentive Report- Output'!B73,'Target Achieved- Input'!$V$2:$V$90) -> 11 | I73: =SUMIF('Target Achieved- Input'!$L$2:$L$90,'Incentive Report- Output'!B73,'Target Achieved- Input'!$AC$2:$AC$90) -> 5 | J73: =G73-H73 -> 38 | K73: =IFERROR(J73/E73,0) -> 0.69090909 | L73: =E73*33000 -> 1815000 | M73: =SUMIF('Target Achieved- Input'!$L$2:$L$90,'Incentive Report- Output'!B73,'Target Achieved- Input'!$M$2:$M$90) -> 2123251 | N73: =SUMIF('Target Achieved- Input'!$S$2:$S$90,'Incentive Report- Output'!B73,'Target Achieved- Input'!$U$2:$U$90) -> 432194.07 | O73: =SUMIF('Target Achieved- Input'!$L$2:$L$90,'Incentive Report- Output'!B73,'Target Achieved- Input'!$N$2:$N$90)-N73 -> 1367171.2 | P73: =IFERROR(O73/L73,0) -> 0.75326236 | Q73: =MAX(P73,K73) -> 0.75326236 | R73: 0 | S73: =(LOOKUP(Q73,Policy!$L$12:$M$16)+R73)*O73 -> 6835.8559 | AA73: 0 | AB73: 0 | AC73: 0 | AD73: =IF(AF73>200000,AF73-200000,0) -> 0 | AE73: =AF73-AD73 -> 6835.8559 | AF73: =S73+W73+AB73+AC73 -> 6835.8559 | AI73: Santhosh G | AJ73: NHP719 | AK73: R11 | AL73: 17993.653 | AM73: =AF73 -> 6835.8559 | AN73: =AL73-AM73 -> 11157.797
A74: TOTAL | D74: R11 | E74: =SUM(E68:E73) -> 335 | F74: =SUM(F68:F73) -> 436 | G74: =SUM(G68:G73) -> 248 | H74: =SUM(H68:H73) -> 52 | I74: =SUM(I68:I73) -> 18 | J74: =SUM(J68:J73) -> 196 | L74: =SUM(L68:L73) -> 11055000 | M74: =SUM(M68:M73) -> 11922502 | N74: =SUM(N68:N73) -> 2067159.3 | O74: =SUM(O68:O73) -> 8036655.9 | S74: =SUM(S68:S73) -> 102967.52 | T74: =SUM(T68:T73) -> 1980000 | U74: =SUM(U68:U73) -> 1464164.4 | V74: =SUM(V68:V73) -> 0.73947697 | W74: =SUM(W68:W73) -> 0 | X74: =SUM(X69:X73) -> 0 | Y74: =SUM(Y69:Y73) -> 0 | Z74: =SUM(Z69:Z73) -> 0 | AA74: =SUM(AA68:AA73) -> 0 | AB74: =SUM(AB68:AB73) -> 0 | AC74: =SUM(AC68:AC73) -> 0 | AD74: =SUM(AD68:AD73) -> 0 | AE74: =SUM(AE68:AE73) -> 102967.52 | AF74: =SUM(AF68:AF73) -> 102967.52 | AI74: TOTAL | AK74: R11 | AL74: 142409.9 | AM74: =SUM(AM68:AM73) -> 102967.52 | AN74: =SUM(AN68:AN73) -> 39442.381
A75: Abhishek Bhat | B75: NHP444 | C75: BDE | D75: R12 | E75: =ROUND(SUMIF('Target Achieved- Input'!$B$2:$B$90,'Incentive Report- Output'!B75,'Target Achieved- Input'!$G$2:$G$90),0) -> 55 | F75: =ROUND(SUMIF('Target Achieved- Input'!$B$2:$B$90,'Incentive Report- Output'!B75,'Target Achieved- Input'!$H$2:$H$90),0) -> 72 | G75: =SUMIF('Target Achieved- Input'!$L$2:$L$90,'Incentive Report- Output'!B75,'Target Achieved- Input'!$O$2:$O$90) -> 30 | H75: =SUMIF('Target Achieved- Input'!$S$2:$S$90,'Incentive Report- Output'!B75,'Target Achieved- Input'!$V$2:$V$90) -> 8 | I75: =SUMIF('Target Achieved- Input'!$L$2:$L$90,'Incentive Report- Output'!B75,'Target Achieved- Input'!$AC$2:$AC$90) -> 0 | J75: =G75-H75 -> 22 | K75: =IFERROR(J75/E75,0) -> 0.4 | L75: =E75*33000 -> 1815000 | M75: =SUMIF('Target Achieved- Input'!$L$2:$L$90,'Incentive Report- Output'!B75,'Target Achieved- Input'!$M$2:$M$90) -> 1408170 | N75: =SUMIF('Target Achieved- Input'!$S$2:$S$90,'Incentive Report- Output'!B75,'Target Achieved- Input'!$U$2:$U$90) -> 323976.27 | O75: =SUMIF('Target Achieved- Input'!$L$2:$L$90,'Incentive Report- Output'!B75,'Target Achieved- Input'!$N$2:$N$90)-N75 -> 869388.14 | P75: =IFERROR(O75/L75,0) -> 0.47900173 | Q75: =MAX(P75,K75) -> 0.47900173 | R75: 0 | S75: =(LOOKUP(Q75,Policy!$L$12:$M$16)+R75)*O75 -> 0 | AA75: 0 | AB75: 0 | AC75: 0 | AD75: =IF(AF75>200000,AF75-200000,0) -> 0 | AE75: =AF75-AD75 -> 0 | AF75: =S75+W75+AB75+AC75 -> 0 | AI75: Abhishek Bhat | AJ75: NHP444 | AK75: R12 | AL75: 5966.822 | AM75: =AF75 -> 0 | AN75: =AL75-AM75 -> 5966.822
A76: Mohammed Sufian Shareeq | B76: NHP518 | C76: SBM | D76: R12 | E76: =ROUND(SUMIF('Target Achieved- Input'!$B$2:$B$90,'Incentive Report- Output'!B76,'Target Achieved- Input'!$G$2:$G$90),0) -> 60 | F76: =ROUND(SUMIF('Target Achieved- Input'!$B$2:$B$90,'Incentive Report- Output'!B76,'Target Achieved- Input'!$H$2:$H$90),0) -> 78 | G76: =SUMIF('Target Achieved- Input'!$L$2:$L$90,'Incentive Report- Output'!B76,'Target Achieved- Input'!$O$2:$O$90) -> 38 | H76: =SUMIF('Target Achieved- Input'!$S$2:$S$90,'Incentive Report- Output'!B76,'Target Achieved- Input'!$V$2:$V$90) -> 1 | I76: =SUMIF('Target Achieved- Input'!$L$2:$L$90,'Incentive Report- Output'!B76,'Target Achieved- Input'!$AC$2:$AC$90) -> 7 | J76: =G76-H76 -> 37 | K76: =IFERROR(J76/E76,0) -> 0.61666667 | L76: =E76*33000 -> 1980000 | M76: =SUMIF('Target Achieved- Input'!$L$2:$L$90,'Incentive Report- Output'!B76,'Target Achieved- Input'!$M$2:$M$90) -> 1598612 | N76: =SUMIF('Target Achieved- Input'!$S$2:$S$90,'Incentive Report- Output'!B76,'Target Achieved- Input'!$U$2:$U$90) -> 5083.8983 | O76: =SUMIF('Target Achieved- Input'!$L$2:$L$90,'Incentive Report- Output'!B76,'Target Achieved- Input'!$N$2:$N$90)-N76 -> 1349672 | P76: =IFERROR(O76/L76,0) -> 0.68165254 | Q76: =MAX(P76,K76) -> 0.68165254 | R76: 0 | S76: =(LOOKUP(Q76,Policy!$L$12:$M$16)+R76)*O76 -> 6748.3602 | AA76: 0 | AB76: 0 | AC76: 0 | AD76: =IF(AF76>200000,AF76-200000,0) -> 0 | AE76: =AF76-AD76 -> 6748.3602 | AF76: =S76+W76+AB76+AC76 -> 6748.3602 | AI76: Mohammed Sufian Shareeq | AJ76: NHP518 | AK76: R12 | AL76: 6773.7797 | AM76: =AF76 -> 6748.3602 | AN76: =AL76-AM76 -> 25.419492
A77: Prajwal Hubballi | B77: NHP829 | C77: BDE | D77: R12 | E77: =ROUND(SUMIF('Target Achieved- Input'!$B$2:$B$90,'Incentive Report- Output'!B77,'Target Achieved- Input'!$G$2:$G$90),0) -> 0 | F77: =ROUND(SUMIF('Target Achieved- Input'!$B$2:$B$90,'Incentive Report- Output'!B77,'Target Achieved- Input'!$H$2:$H$90),0) -> 0 | G77: =SUMIF('Target Achieved- Input'!$L$2:$L$90,'Incentive Report- Output'!B77,'Target Achieved- Input'!$O$2:$O$90) -> 0 | H77: =SUMIF('Target Achieved- Input'!$S$2:$S$90,'Incentive Report- Output'!B77,'Target Achieved- Input'!$V$2:$V$90) -> 0 | I77: =SUMIF('Target Achieved- Input'!$L$2:$L$90,'Incentive Report- Output'!B77,'Target Achieved- Input'!$AC$2:$AC$90) -> 0 | J77: =G77-H77 -> 0 | K77: =IFERROR(J77/E77,0) -> 0 | L77: =E77*33000 -> 0 | M77: =SUMIF('Target Achieved- Input'!$L$2:$L$90,'Incentive Report- Output'!B77,'Target Achieved- Input'!$M$2:$M$90) -> 0 | N77: =SUMIF('Target Achieved- Input'!$S$2:$S$90,'Incentive Report- Output'!B77,'Target Achieved- Input'!$U$2:$U$90) -> 0 | O77: =SUMIF('Target Achieved- Input'!$L$2:$L$90,'Incentive Report- Output'!B77,'Target Achieved- Input'!$N$2:$N$90)-N77 -> 0 | P77: =IFERROR(O77/L77,0) -> 0 | Q77: =MAX(P77,K77) -> 0 | R77: 0 | S77: =(LOOKUP(Q77,Policy!$L$12:$M$16)+R77)*O77 -> 0 | AA77: 0 | AB77: 0 | AC77: 0 | AD77: =IF(AF77>200000,AF77-200000,0) -> 0 | AE77: =AF77-AD77 -> 0 | AF77: =S77+W77+AB77+AC77 -> 0 | AI77: Prajwal Hubballi | AJ77: NHP829 | AK77: R12 | AL77: 0 | AM77: =AF77 -> 0 | AN77: =AL77-AM77 -> 0
A78: Shrihari R Kulkarni | B78: NHP279 | C78: BDE | D78: R12 | E78: =ROUND(SUMIF('Target Achieved- Input'!$B$2:$B$90,'Incentive Report- Output'!B78,'Target Achieved- Input'!$G$2:$G$90),0) -> 50 | F78: =ROUND(SUMIF('Target Achieved- Input'!$B$2:$B$90,'Incentive Report- Output'!B78,'Target Achieved- Input'!$H$2:$H$90),0) -> 65 | G78: =SUMIF('Target Achieved- Input'!$L$2:$L$90,'Incentive Report- Output'!B78,'Target Achieved- Input'!$O$2:$O$90) -> 26 | H78: =SUMIF('Target Achieved- Input'!$S$2:$S$90,'Incentive Report- Output'!B78,'Target Achieved- Input'!$V$2:$V$90) -> 13 | I78: =SUMIF('Target Achieved- Input'!$L$2:$L$90,'Incentive Report- Output'!B78,'Target Achieved- Input'!$AC$2:$AC$90) -> 0 | J78: =G78-H78 -> 13 | K78: =IFERROR(J78/E78,0) -> 0.26 | L78: =E78*33000 -> 1650000 | M78: =SUMIF('Target Achieved- Input'!$L$2:$L$90,'Incentive Report- Output'!B78,'Target Achieved- Input'!$M$2:$M$90) -> 1307024 | N78: =SUMIF('Target Achieved- Input'!$S$2:$S$90,'Incentive Report- Output'!B78,'Target Achieved- Input'!$U$2:$U$90) -> 546980.51 | O78: =SUMIF('Target Achieved- Input'!$L$2:$L$90,'Incentive Report- Output'!B78,'Target Achieved- Input'!$N$2:$N$90)-N78 -> 560666.95 | P78: =IFERROR(O78/L78,0) -> 0.33979815 | Q78: =MAX(P78,K78) -> 0.33979815 | R78: 0 | S78: =(LOOKUP(Q78,Policy!$L$12:$M$16)+R78)*O78 -> 0 | AA78: 0 | AB78: 0 | AC78: 0 | AD78: =IF(AF78>200000,AF78-200000,0) -> 0 | AE78: =AF78-AD78 -> 0 | AF78: =S78+W78+AB78+AC78 -> 0 | AI78: Shrihari R Kulkarni | AJ78: NHP279 | AK78: R12 | AL78: 5538.2373 | AM78: =AF78 -> 0 | AN78: =AL78-AM78 -> 5538.2373
A79: TOTAL | D79: R12 | E79: =SUM(E75:E78) -> 165 | F79: =SUM(F75:F78) -> 215 | G79: =SUM(G75:G78) -> 94 | H79: =SUM(H75:H78) -> 22 | I79: =SUM(I75:I78) -> 7 | J79: =SUM(J75:J78) -> 72 | L79: =SUM(L75:L78) -> 5445000 | M79: =SUM(M75:M78) -> 4313806 | N79: =SUM(N75:N78) -> 876040.68 | O79: =SUM(O75:O78) -> 2779727.1 | S79: =SUM(S75:S78) -> 6748.3602 | T79: =SUM(T75:T78) -> 0 | U79: =SUM(U75:U78) -> 0 | V79: =SUM(V75:V78) -> 0 | W79: =SUM(W75:W78) -> 0 | X79: =SUM(X75:X78) -> 0 | Y79: =SUM(Y75:Y78) -> 0 | Z79: =SUM(Z75:Z78) -> 0 | ... AF79: =SUM(AF75:AF78) -> 6748.3602 | AI79: TOTAL | AK79: R12 | AL79: 18278.839 | AM79: =SUM(AM75:AM78) -> 6748.3602 | AN79: =SUM(AN75:AN78) -> 11530.479
A80: Saif Khan | B80: NHP147 | C80: RM | D80: R13 | E80: =ROUND(SUMIF('Target Achieved- Input'!$B$2:$B$90,'Incentive Report- Output'!B80,'Target Achieved- Input'!$G$2:$G$90),0) -> 55 | F80: =ROUND(SUMIF('Target Achieved- Input'!$B$2:$B$90,'Incentive Report- Output'!B80,'Target Achieved- Input'!$H$2:$H$90),0) -> 72 | G80: =SUMIF('Target Achieved- Input'!$L$2:$L$90,'Incentive Report- Output'!B80,'Target Achieved- Input'!$O$2:$O$90) -> 20 | H80: =SUMIF('Target Achieved- Input'!$S$2:$S$90,'Incentive Report- Output'!B80,'Target Achieved- Input'!$V$2:$V$90) -> 20 | I80: =SUMIF('Target Achieved- Input'!$L$2:$L$90,'Incentive Report- Output'!B80,'Target Achieved- Input'!$AC$2:$AC$90) -> 0 | J80: =G80-H80 -> 0 | K80: =IFERROR(J80/E80,0) -> 0 | L80: =E80*33000 -> 1815000 | M80: =SUMIF('Target Achieved- Input'!$L$2:$L$90,'Incentive Report- Output'!B80,'Target Achieved- Input'!$M$2:$M$90) -> 1087630 | N80: =SUMIF('Target Achieved- Input'!$S$2:$S$90,'Incentive Report- Output'!B80,'Target Achieved- Input'!$U$2:$U$90) -> 921720.34 | O80: =SUMIF('Target Achieved- Input'!$L$2:$L$90,'Incentive Report- Output'!B80,'Target Achieved- Input'!$N$2:$N$90)-N80 -> 0 | P80: =IFERROR(O80/L80,0) -> 0 | Q80: =MAX(P80,K80) -> 0 | R80: 0 | S80: =(LOOKUP(Q80,Policy!$L$12:$M$16)+R80)*O80 -> 0 | AA80: 0 | AB80: 0 | AC80: 0 | AD80: =IF(AF80>200000,AF80-200000,0) -> 0 | AE80: =AF80-AD80 -> 0 | AF80: =S80+W80+AB80+AC80 -> 0 | AI80: Saif Khan | AJ80: NHP147 | AK80: R13 | AL80: 4608.6017 | AM80: =AF80 -> 0 | AN80: =AL80-AM80 -> 4608.6017
A81: Arshad Hussain | B81: NHP364 | C81: BDE | D81: R13 | E81: =ROUND(SUMIF('Target Achieved- Input'!$B$2:$B$90,'Incentive Report- Output'!B81,'Target Achieved- Input'!$G$2:$G$90),0) -> 60 | F81: =ROUND(SUMIF('Target Achieved- Input'!$B$2:$B$90,'Incentive Report- Output'!B81,'Target Achieved- Input'!$H$2:$H$90),0) -> 78 | G81: =SUMIF('Target Achieved- Input'!$L$2:$L$90,'Incentive Report- Output'!B81,'Target Achieved- Input'!$O$2:$O$90) -> 25 | H81: =SUMIF('Target Achieved- Input'!$S$2:$S$90,'Incentive Report- Output'!B81,'Target Achieved- Input'!$V$2:$V$90) -> 8 | I81: =SUMIF('Target Achieved- Input'!$L$2:$L$90,'Incentive Report- Output'!B81,'Target Achieved- Input'!$AC$2:$AC$90) -> 4 | J81: =G81-H81 -> 17 | K81: =IFERROR(J81/E81,0) -> 0.28333333 | L81: =E81*33000 -> 1980000 | M81: =SUMIF('Target Achieved- Input'!$L$2:$L$90,'Incentive Report- Output'!B81,'Target Achieved- Input'!$M$2:$M$90) -> 1147575 | N81: =SUMIF('Target Achieved- Input'!$S$2:$S$90,'Incentive Report- Output'!B81,'Target Achieved- Input'!$U$2:$U$90) -> 228213.56 | O81: =SUMIF('Target Achieved- Input'!$L$2:$L$90,'Incentive Report- Output'!B81,'Target Achieved- Input'!$N$2:$N$90)-N81 -> 744307.63 | P81: =IFERROR(O81/L81,0) -> 0.37591294 | Q81: =MAX(P81,K81) -> 0.37591294 | R81: 0 | S81: =(LOOKUP(Q81,Policy!$L$12:$M$16)+R81)*O81 -> 0 | AA81: 0 | AB81: 0 | AC81: 0 | AD81: =IF(AF81>200000,AF81-200000,0) -> 0 | AE81: =AF81-AD81 -> 0 | AF81: =S81+W81+AB81+AC81 -> 0 | AI81: Arshad Hussain | AJ81: NHP364 | AK81: R13 | AL81: 0 | AM81: =AF81 -> 0 | AN81: =AL81-AM81 -> 0
A82: Nenavath Laxman | B82: NHP536 | C82: BDE | D82: R13 | E82: =ROUND(SUMIF('Target Achieved- Input'!$B$2:$B$90,'Incentive Report- Output'!B82,'Target Achieved- Input'!$G$2:$G$90),0) -> 60 | F82: =ROUND(SUMIF('Target Achieved- Input'!$B$2:$B$90,'Incentive Report- Output'!B82,'Target Achieved- Input'!$H$2:$H$90),0) -> 78 | G82: =SUMIF('Target Achieved- Input'!$L$2:$L$90,'Incentive Report- Output'!B82,'Target Achieved- Input'!$O$2:$O$90) -> 13 | H82: =SUMIF('Target Achieved- Input'!$S$2:$S$90,'Incentive Report- Output'!B82,'Target Achieved- Input'!$V$2:$V$90) -> 13 | I82: =SUMIF('Target Achieved- Input'!$L$2:$L$90,'Incentive Report- Output'!B82,'Target Achieved- Input'!$AC$2:$AC$90) -> 1 | J82: =G82-H82 -> 0 | K82: =IFERROR(J82/E82,0) -> 0 | L82: =E82*33000 -> 1980000 | M82: =SUMIF('Target Achieved- Input'!$L$2:$L$90,'Incentive Report- Output'!B82,'Target Achieved- Input'!$M$2:$M$90) -> 678987 | N82: =SUMIF('Target Achieved- Input'!$S$2:$S$90,'Incentive Report- Output'!B82,'Target Achieved- Input'!$U$2:$U$90) -> 575412.71 | O82: =SUMIF('Target Achieved- Input'!$L$2:$L$90,'Incentive Report- Output'!B82,'Target Achieved- Input'!$N$2:$N$90)-N82 -> 0 | P82: =IFERROR(O82/L82,0) -> 0 | Q82: =MAX(P82,K82) -> 0 | R82: 0 | S82: =(LOOKUP(Q82,Policy!$L$12:$M$16)+R82)*O82 -> 0 | AA82: 0 | AB82: 0 | AC82: 0 | AD82: =IF(AF82>200000,AF82-200000,0) -> 0 | AE82: =AF82-AD82 -> 0 | AF82: =S82+W82+AB82+AC82 -> 0 | AI82: Nenavath Laxman | AJ82: NHP536 | AK82: R13 | AL82: 0 | AM82: =AF82 -> 0 | AN82: =AL82-AM82 -> 0
A83: Shaktinandan Akhilesh | B83: NHP736 | C83: BDE | D83: R13 | E83: =ROUND(SUMIF('Target Achieved- Input'!$B$2:$B$90,'Incentive Report- Output'!B83,'Target Achieved- Input'!$G$2:$G$90),0) -> 55 | F83: =ROUND(SUMIF('Target Achieved- Input'!$B$2:$B$90,'Incentive Report- Output'!B83,'Target Achieved- Input'!$H$2:$H$90),0) -> 72 | G83: =SUMIF('Target Achieved- Input'!$L$2:$L$90,'Incentive Report- Output'!B83,'Target Achieved- Input'!$O$2:$O$90) -> 13 | H83: =SUMIF('Target Achieved- Input'!$S$2:$S$90,'Incentive Report- Output'!B83,'Target Achieved- Input'!$V$2:$V$90) -> 13 | I83: =SUMIF('Target Achieved- Input'!$L$2:$L$90,'Incentive Report- Output'!B83,'Target Achieved- Input'!$AC$2:$AC$90) -> 0 | J83: =G83-H83 -> 0 | K83: =IFERROR(J83/E83,0) -> 0 | L83: =E83*33000 -> 1815000 | M83: =SUMIF('Target Achieved- Input'!$L$2:$L$90,'Incentive Report- Output'!B83,'Target Achieved- Input'!$M$2:$M$90) -> 645737 | N83: =SUMIF('Target Achieved- Input'!$S$2:$S$90,'Incentive Report- Output'!B83,'Target Achieved- Input'!$U$2:$U$90) -> 547234.75 | O83: =SUMIF('Target Achieved- Input'!$L$2:$L$90,'Incentive Report- Output'!B83,'Target Achieved- Input'!$N$2:$N$90)-N83 -> 0 | P83: =IFERROR(O83/L83,0) -> 0 | Q83: =MAX(P83,K83) -> 0 | R83: 0 | S83: =(LOOKUP(Q83,Policy!$L$12:$M$16)+R83)*O83 -> 0 | AA83: 0 | AB83: 0 | AC83: 0 | AD83: =IF(AF83>200000,AF83-200000,0) -> 0 | AE83: =AF83-AD83 -> 0 | AF83: =S83+W83+AB83+AC83 -> 0 | AI83: Shaktinandan Akhilesh | AJ83: NHP736 | AK83: R13 | AL83: 0 | AM83: =AF83 -> 0 | AN83: =AL83-AM83 -> 0
A84: Suresh Kumar Thakur | B84: NHP211 | C84: BDE | D84: R13 | E84: =ROUND(SUMIF('Target Achieved- Input'!$B$2:$B$90,'Incentive Report- Output'!B84,'Target Achieved- Input'!$G$2:$G$90),0) -> 60 | F84: =ROUND(SUMIF('Target Achieved- Input'!$B$2:$B$90,'Incentive Report- Output'!B84,'Target Achieved- Input'!$H$2:$H$90),0) -> 78 | G84: =SUMIF('Target Achieved- Input'!$L$2:$L$90,'Incentive Report- Output'!B84,'Target Achieved- Input'!$O$2:$O$90) -> 25 | H84: =SUMIF('Target Achieved- Input'!$S$2:$S$90,'Incentive Report- Output'!B84,'Target Achieved- Input'!$V$2:$V$90) -> 2 | I84: =SUMIF('Target Achieved- Input'!$L$2:$L$90,'Incentive Report- Output'!B84,'Target Achieved- Input'!$AC$2:$AC$90) -> 0 | J84: =G84-H84 -> 23 | K84: =IFERROR(J84/E84,0) -> 0.38333333 | L84: =E84*33000 -> 1980000 | M84: =SUMIF('Target Achieved- Input'!$L$2:$L$90,'Incentive Report- Output'!B84,'Target Achieved- Input'!$M$2:$M$90) -> 1179175 | N84: =SUMIF('Target Achieved- Input'!$S$2:$S$90,'Incentive Report- Output'!B84,'Target Achieved- Input'!$U$2:$U$90) -> 99150.847 | O84: =SUMIF('Target Achieved- Input'!$L$2:$L$90,'Incentive Report- Output'!B84,'Target Achieved- Input'!$N$2:$N$90)-N84 -> 900150 | P84: =IFERROR(O84/L84,0) -> 0.45462121 | Q84: =MAX(P84,K84) -> 0.45462121 | R84: 0 | S84: =(LOOKUP(Q84,Policy!$L$12:$M$16)+R84)*O84 -> 0 | AA84: 0 | AB84: 0 | AC84: 0 | AD84: =IF(AF84>200000,AF84-200000,0) -> 0 | AE84: =AF84-AD84 -> 0 | AF84: =S84+W84+AB84+AC84 -> 0 | AI84: Suresh Kumar Thakur | AJ84: NHP211 | AK84: R13 | AL84: 4996.5042 | AM84: =AF84 -> 0 | AN84: =AL84-AM84 -> 4996.5042
A85: Ranjith D | B85: NHP610 | C85: BDE | D85: R13 | E85: =ROUND(SUMIF('Target Achieved- Input'!$B$2:$B$90,'Incentive Report- Output'!B85,'Target Achieved- Input'!$G$2:$G$90),0) -> 55 | F85: =ROUND(SUMIF('Target Achieved- Input'!$B$2:$B$90,'Incentive Report- Output'!B85,'Target Achieved- Input'!$H$2:$H$90),0) -> 72 | G85: =SUMIF('Target Achieved- Input'!$L$2:$L$90,'Incentive Report- Output'!B85,'Target Achieved- Input'!$O$2:$O$90) -> 31 | H85: =SUMIF('Target Achieved- Input'!$S$2:$S$90,'Incentive Report- Output'!B85,'Target Achieved- Input'!$V$2:$V$90) -> 6 | I85: =SUMIF('Target Achieved- Input'!$L$2:$L$90,'Incentive Report- Output'!B85,'Target Achieved- Input'!$AC$2:$AC$90) -> 1 | J85: =G85-H85 -> 25 | K85: =IFERROR(J85/E85,0) -> 0.45454545 | L85: =E85*33000 -> 1815000 | M85: =SUMIF('Target Achieved- Input'!$L$2:$L$90,'Incentive Report- Output'!B85,'Target Achieved- Input'!$M$2:$M$90) -> 1358469 | N85: =SUMIF('Target Achieved- Input'!$S$2:$S$90,'Incentive Report- Output'!B85,'Target Achieved- Input'!$U$2:$U$90) -> 239528.81 | O85: =SUMIF('Target Achieved- Input'!$L$2:$L$90,'Incentive Report- Output'!B85,'Target Achieved- Input'!$N$2:$N$90)-N85 -> 911716.1 | P85: =IFERROR(O85/L85,0) -> 0.50232292 | Q85: =MAX(P85,K85) -> 0.50232292 | R85: 0 | S85: =(LOOKUP(Q85,Policy!$L$12:$M$16)+R85)*O85 -> 4558.5805 | AA85: 0 | AB85: 0 | AC85: 0 | AD85: =IF(AF85>200000,AF85-200000,0) -> 0 | AE85: =AF85-AD85 -> 4558.5805 | AF85: =S85+W85+AB85+AC85 -> 4558.5805 | AI85: Ranjith D | AJ85: NHP610 | AK85: R13 | AL85: 5756.2246 | AM85: =AF85 -> 4558.5805 | AN85: =AL85-AM85 -> 1197.6441
A86: TOTAL | D86: R13 | E86: =SUM(E80:E85) -> 345 | F86: =SUM(F80:F85) -> 450 | G86: =SUM(G80:G85) -> 127 | H86: =SUM(H80:H85) -> 62 | I86: =SUM(I80:I85) -> 6 | J86: =SUM(J80:J85) -> 65 | L86: =SUM(L80:L85) -> 11385000 | M86: =SUM(M80:M85) -> 6097573 | N86: =SUM(N80:N85) -> 2611261 | O86: =SUM(O80:O85) -> 2556173.7 | S86: =SUM(S80:S85) -> 4558.5805 | T86: =SUM(T80:T85) -> 0 | U86: =SUM(U80:U85) -> 0 | V86: =SUM(V80:V85) -> 0 | W86: =SUM(W80:W85) -> 0 | X86: =SUM(X81:X85) -> 0 | Y86: =SUM(Y81:Y85) -> 0 | Z86: =SUM(Z81:Z85) -> 0 | AA86: =SUM(AA80:AA85) -> 0 | AB86: =SUM(AB80:AB85) -> 0 | AC86: =SUM(AC80:AC85) -> 0 | AD86: =SUM(AD80:AD85) -> 0 | AE86: =SUM(AE80:AE85) -> 4558.5805 | AF86: =SUM(AF80:AF85) -> 4558.5805 | AI86: TOTAL | AK86: R13 | AL86: 15361.331 | AM86: =SUM(AM80:AM85) -> 4558.5805 | AN86: =SUM(AN81:AN85) -> 6194.1483
A87: Rameez Arman | B87: NHP218 | C87: RM | D87: R14 | E87: =ROUND(SUMIF('Target Achieved- Input'!$B$2:$B$90,'Incentive Report- Output'!B87,'Target Achieved- Input'!$G$2:$G$90),0) -> 55 | F87: =ROUND(SUMIF('Target Achieved- Input'!$B$2:$B$90,'Incentive Report- Output'!B87,'Target Achieved- Input'!$H$2:$H$90),0) -> 72 | G87: =SUMIF('Target Achieved- Input'!$L$2:$L$90,'Incentive Report- Output'!B87,'Target Achieved- Input'!$O$2:$O$90) -> 26 | H87: =SUMIF('Target Achieved- Input'!$S$2:$S$90,'Incentive Report- Output'!B87,'Target Achieved- Input'!$V$2:$V$90) -> 1 | I87: =SUMIF('Target Achieved- Input'!$L$2:$L$90,'Incentive Report- Output'!B87,'Target Achieved- Input'!$AC$2:$AC$90) -> 1 | J87: =G87-H87 -> 25 | K87: =IFERROR(J87/E87,0) -> 0.45454545 | L87: =E87*33000 -> 1815000 | M87: =SUMIF('Target Achieved- Input'!$L$2:$L$90,'Incentive Report- Output'!B87,'Target Achieved- Input'!$M$2:$M$90) -> 1272624 | N87: =SUMIF('Target Achieved- Input'!$S$2:$S$90,'Incentive Report- Output'!B87,'Target Achieved- Input'!$U$2:$U$90) -> 22583.898 | O87: =SUMIF('Target Achieved- Input'!$L$2:$L$90,'Incentive Report- Output'!B87,'Target Achieved- Input'!$N$2:$N$90)-N87 -> 1055911 | P87: =IFERROR(O87/L87,0) -> 0.58176916 | Q87: =MAX(P87,K87) -> 0.58176916 | R87: 0 | S87: =(LOOKUP(Q87,Policy!$L$12:$M$16)+R87)*O87 -> 5279.5551 | AA87: 0 | AB87: 0 | AC87: 0 | AD87: =IF(AF87>200000,AF87-200000,0) -> 0 | AE87: =AF87-AD87 -> 5279.5551 | AF87: =S87+W87+AB87+AC87 -> 5279.5551 | AI87: Rameez Arman | AJ87: NHP218 | AK87: R14 | AL87: 5392.4746 | AM87: =AF87 -> 5279.5551 | AN87: =AL87-AM87 -> 112.91949
A88: Amey Jadhav | B88: NHP671 | C88: BDE | D88: R14 | E88: =ROUND(SUMIF('Target Achieved- Input'!$B$2:$B$90,'Incentive Report- Output'!B88,'Target Achieved- Input'!$G$2:$G$90),0) -> 50 | F88: =ROUND(SUMIF('Target Achieved- Input'!$B$2:$B$90,'Incentive Report- Output'!B88,'Target Achieved- Input'!$H$2:$H$90),0) -> 65 | G88: =SUMIF('Target Achieved- Input'!$L$2:$L$90,'Incentive Report- Output'!B88,'Target Achieved- Input'!$O$2:$O$90) -> 31 | H88: =SUMIF('Target Achieved- Input'!$S$2:$S$90,'Incentive Report- Output'!B88,'Target Achieved- Input'!$V$2:$V$90) -> 0 | I88: =SUMIF('Target Achieved- Input'!$L$2:$L$90,'Incentive Report- Output'!B88,'Target Achieved- Input'!$AC$2:$AC$90) -> 0 | J88: =G88-H88 -> 31 | K88: =IFERROR(J88/E88,0) -> 0.62 | L88: =E88*33000 -> 1650000 | M88: =SUMIF('Target Achieved- Input'!$L$2:$L$90,'Incentive Report- Output'!B88,'Target Achieved- Input'!$M$2:$M$90) -> 1722069 | N88: =SUMIF('Target Achieved- Input'!$S$2:$S$90,'Incentive Report- Output'!B88,'Target Achieved- Input'!$U$2:$U$90) -> 0 | O88: =SUMIF('Target Achieved- Input'!$L$2:$L$90,'Incentive Report- Output'!B88,'Target Achieved- Input'!$N$2:$N$90)-N88 -> 1459380.5 | P88: =IFERROR(O88/L88,0) -> 0.88447304 | Q88: =MAX(P88,K88) -> 0.88447304 | R88: 0 | S88: =(LOOKUP(Q88,Policy!$L$12:$M$16)+R88)*O88 -> 14593.805 | AA88: 0 | AB88: 0 | AC88: 0 | AD88: =IF(AF88>200000,AF88-200000,0) -> 0 | AE88: =AF88-AD88 -> 14593.805 | AF88: =S88+W88+AB88+AC88 -> 14593.805 | AI88: Amey Jadhav | AJ88: NHP671 | AK88: R14 | AL88: 14593.805 | AM88: =AF88 -> 14593.805 | AN88: =AL88-AM88 -> 0
A89: Loka Phanindra | B89: NHP365 | C89: BDE | D89: R14 | E89: =ROUND(SUMIF('Target Achieved- Input'!$B$2:$B$90,'Incentive Report- Output'!B89,'Target Achieved- Input'!$G$2:$G$90),0) -> 60 | F89: =ROUND(SUMIF('Target Achieved- Input'!$B$2:$B$90,'Incentive Report- Output'!B89,'Target Achieved- Input'!$H$2:$H$90),0) -> 78 | G89: =SUMIF('Target Achieved- Input'!$L$2:$L$90,'Incentive Report- Output'!B89,'Target Achieved- Input'!$O$2:$O$90) -> 67 | H89: =SUMIF('Target Achieved- Input'!$S$2:$S$90,'Incentive Report- Output'!B89,'Target Achieved- Input'!$V$2:$V$90) -> 0 | I89: =SUMIF('Target Achieved- Input'!$L$2:$L$90,'Incentive Report- Output'!B89,'Target Achieved- Input'!$AC$2:$AC$90) -> 2 | J89: =G89-H89 -> 67 | K89: =IFERROR(J89/E89,0) -> 1.1166667 | L89: =E89*33000 -> 1980000 | M89: =SUMIF('Target Achieved- Input'!$L$2:$L$90,'Incentive Report- Output'!B89,'Target Achieved- Input'!$M$2:$M$90) -> 3088833 | N89: =SUMIF('Target Achieved- Input'!$S$2:$S$90,'Incentive Report- Output'!B89,'Target Achieved- Input'!$U$2:$U$90) -> 0 | O89: =SUMIF('Target Achieved- Input'!$L$2:$L$90,'Incentive Report- Output'!B89,'Target Achieved- Input'!$N$2:$N$90)-N89 -> 2617655.1 | P89: =IFERROR(O89/L89,0) -> 1.322048 | Q89: =MAX(P89,K89) -> 1.322048 | R89: 0 | S89: =(LOOKUP(Q89,Policy!$L$12:$M$16)+R89)*O89 -> 78529.653 | AA89: 0 | AB89: 0 | AC89: 0 | AD89: =IF(AF89>200000,AF89-200000,0) -> 0 | AE89: =AF89-AD89 -> 78529.653 | AF89: =S89+W89+AB89+AC89 -> 78529.653 | AI89: Loka Phanindra | AJ89: NHP365 | AK89: R14 | AL89: 78529.653 | AM89: =AF89 -> 78529.653 | AN89: =AL89-AM89 -> 0
